Workbook

Sheet README
A1: US State IVF Access Dataset (2026 snapshot)
A3: Version | B3: v1.0
A4: Release date | B4: 2026-03-12
A5: Contents | B5: data, codebook, index_logic, methodology
A7: How to cite
A8: Suggested citation | B8: US State IVF Access Dataset (2026 snapshot), compiled by user with structured coding support from OpenAI ChatGPT.
A10: State IVF Access Index
A11: Scale | B11: 0-100
A12: Interpretation | B12: Higher scores indicate stronger insurance access, more inclusive eligibility, fewer embryo/personhood constraints, and greater clinic/utilization access.
A14: Key sources
A15: https://triagecancer.org/state-laws/health-insurance-fertility-services
A16: https://www.reproductivefacts.org/patient-advocacy/state-and-territory-infertility-insurance-laws/
A17: https://surrogacy360.org/wp-content/uploads/2024/08/Regulation-Details-in-the-US-by-State_8.6.24.pdf
A18: https://www.cdc.gov/art/php/surveillance-state-specific/index.html
A19: https://www.cms.gov/marketplace/in-person-assisters/training-webinars/training/marketplaces-map
A20: https://ballotpedia.org/State_government_trifectas
A21: https://www.guttmacher.org/united-states/abortion

Sheet data
A1: state | B1: state_abbrev | C1: year | D1: policy_status | E1: policy_start_year | F1: policy_end_year | G1: policy_last_updated | H1: insurance_mandate | I1: mandate_scope | J1: coverage_type | K1: cycle_limit | L1: lifetime_limit | M1: financial_cap | N1: medication_coverage | O1: fertility_preservation_coverage | P1: donor_gamete_coverage | Q1: embryo_transfer_limit | R1: religious_exemption | S1: medicaid_ivf_coverage | T1: medicaid_infertility_services | U1: state_subsidy_program | V1: public_funding_amount | W1: state_employee_ivf_coverage | X1: marital_requirement | Y1: infertility_definition | Z1: prior_treatment_requirement | AA1: age_limit_female | AB1: age_limit_male | AC1: residency_requirement | AD1: lgbtq_access | AE1: single_parent_access | AF1: gender_identity_access | AG1: donor_requirement_rules | AH1: embryo_personhood_law | AI1: embryo_storage_regulation | AJ1: embryo_disposition_rules | AK1: embryo_research_restrictions | AL1: fetal_personhood_related_laws | AM1: surrogacy_status | AN1: commercial_surrogacy_allowed | AO1: surrogacy_contract_enforceable | AP1: gestational_surrogacy_only | AQ1: parentage_rules | AR1: clinic_licensing_requirement | AS1: state_reporting_requirements | AT1: success_rate_reporting | AU1: lab_regulation | AV1: mandate_year_enacted | AW1: mandate_last_revised | AX1: major_policy_change | AY1: policy_strength_score | AZ1: ivf_clinics_count | BA1: ivf_cycles_per_year | BB1: population | BC1: insurance_market_type | BD1: political_control | BE1: abortion_policy_index | BF1: policy_source | BG1: statute_link | BH1: secondary_source | BI1: coding_notes | BJ1: coder_initials | BK1: verification_status | BL1: clinic_density_per_million | BM1: cycle_rate_per_million | BN1: subscore_insurance | BO1: subscore_equity | BP1: subscore_surrogacy | BQ1: subscore_embryo_regulation | BR1: subscore_repro_policy_env | BS1: subscore_clinic_density | BT1: subscore_cycle_rate | BU1: ivf_access_index | BV1: ivf_access_tier
A2: Alabama | B2: AL | C2: 2026 | D2: current_snapshot | E2: 0 | F2: NA | G2: 2026-03-12 | H2: none_identified | I2: No statewide infertility/IVF coverage mandate identified in source used | J2: no_statewide_ivf_mandate_identified | K2: 0 | L2: 0 | M2: 0 | N2: 0 | O2: not identified | P2: 0 | Q2: 0 | R2: 0 | U2: none_identified | V2: 0 | X2: no_statewide_ivf_treatment_eligibility_rule_identified | Y2: no_statewide_ivf_treatment_eligibility_rule_identified | Z2: no_statewide_ivf_treatment_eligibility_rule_identified | AA2: not_applicable_no_statewide_ivf_treatment_mandate | AB2: not_applicable_no_statewide_ivf_treatment_mandate | AC2: none stated in source used | AD2: no_statewide_ivf_treatment_eligibility_rule_identified | AE2: no_statewide_ivf_treatment_eligibility_rule_identified | AF2: no_statewide_ivf_treatment_eligibility_rule_identified | AG2: no_statewide_ivf_treatment_eligibility_rule_identified | AH2: yes_court_ruling_frozen_embryos_children | AI2: legal_uncertainty_after_2024_ruling | AJ2: legal_uncertainty_after_2024_ruling; 2024 immunity law for IVF providers does not resolve embryo status | AK2: not identified in secondary sources used | AL2: 2018 constitutional amendment on rights of unborn children cited in 2024 ruling | AM2: restricted | AN2: yes | AO2: no_or_unclear | AP2: unclear | AQ2: adoption or post-birth process often required | AR2: no_fertility_specific_state_clinic_license_coded_in_this_pass | AS2: federal_CDC_NASS_reporting_baseline | AT2: federal_FCSRCA_CDC_public_reporting | AU2: CLIA_CMS_FDA_baseline; state_variation_not_fully_coded | AV2: 0 | AW2: 0 | AX2: 0 | AY2: =BU2 -> 12 | AZ2: 5 | BA2: 1694 | BB2: 5157699 | BC2: FFM | BD2: republican_trifecta | BE2: near_total_ban_or_total_ban_environment | BF2: No statewide infertility/IVF mandate identified in Triage Cancer state-law chart | BG2: https://triagecancer.org/state-laws/health-insurance-fertility-services | BH2: https://triagecancer.org/state-laws/health-insurance-fertility-services; https://surrogacy360.org/wp-content/uploads/2024/08/Regulation-Details-in-the-US-by-State_8.6.24.pdf; https://www.reuters.com/business/healthcare-pharmaceuticals/alabamas-highest-court-ruled-frozen-embryos-are-people-what-is-next-2024-02-23/; https://www.asrm.org/advocacy-and-policy/reproductive-rights/summary-reports/state-abortion-laws-potential-implications-for-reproductive-medicine/; https://www.guttmacher.org/2025/12/state-policy-trends-2025-full-year-analysis; https://www.reuters.com/world/us/republican-alabama-governor-signs-ivf-protections-into-law-2024-03-07/; https://www.cdc.gov/art/php/nass/index.html; https://www.cdc.gov/art/success-rates/index.html; https://www.cms.gov/medicare/quality/clinical-laboratory-improvement-amendments; https://www.cms.gov/marketplace/in-person-assisters/training-webinars/training/marketplaces-map; https://ballotpedia.org/State_government_trifectas; https://www.britannica.com/topic/largest-U-S-state-by-population; https://www.guttmacher.org/united-states/abortion | BI2: Starter row only. Needs primary-law verification for Medicaid, public funding, eligibility, embryo rules, surrogacy, clinic regulation, and utilization variables. Surrogacy fields coded from Surrogacy360 2024 state-by-state summary; interpret as starter classification requiring legal review for publication. Eligibility/LGBTQ fields on this row were filled as a 2026 starter classification based on absence of a statewide IVF-treatment mandate or unclear scope in the source used; this should not be interpreted as a full review of all private plans or clinic access in the state. Embryo/personhood/disposition fields were filled conservatively in this pass. Unless a state had a clear embryo-specific rule in the secondary sources used, values were set to not_identified_in_secondary_sources_used rather than treated as definitive absence of law. Clinic/reporting fields in this pass were coded from federal baselines: CDC NASS/FCSRCA reporting and CMS CLIA materials; insurance marketplace type from CMS Plan Year 2026 marketplace map; political control from Ballotpedia current trifecta status; population uses 2024 state estimate table summarized by Britannica from U.S. Census data. IVF clinic counts and cycle counts remain blank pending direct state-level CDC extraction. | BJ2: RRM | BK2: partially_filled_needs_primary_law_review | BL2: =IFERROR((AZ2/BB2)*1000000,0) -> 0.96942454 | BM2: =IFERROR((BA2/BB2)*1000000,0) -> 328.44104 | BN2: =IFERROR(VLOOKUP(H2,index_logic!$A$4:$B$8,2,FALSE),0) -> 0 | BO2: =IFERROR(VLOOKUP(AD2,index_logic!$D$4:$E$21,2,FALSE),0) -> 3 | BP2: =IFERROR(VLOOKUP(AM2,index_logic!$G$4:$H$6,2,FALSE),0) -> 3 | BQ2: =IFERROR(VLOOKUP(AH2,index_logic!$J$4:$K$6,2,FALSE),0) -> 0 | BR2: =IFERROR(VLOOKUP(BE2,index_logic!$M$4:$N$7,2,FALSE),0) -> 0 | BS2: =IFERROR(VLOOKUP(BL2,index_logic!$P$4:$Q$9,2,TRUE),0) -> 4 | BT2: =IFERROR(VLOOKUP(BM2,index_logic!$S$4:$T$9,2,TRUE),0) -> 2 | BU2: =BN2+BO2+BP2+BQ2+BR2+BS2+BT2 -> 12 | BV2: =IF(BU2>=80,"Very High",IF(BU2>=65,"High",IF(BU2>=50,"Moderate",IF(BU2>=35,"Low","Very Low")))) -> Very Low
A3: Alaska | B3: AK | C3: 2026 | D3: current_snapshot | E3: 0 | F3: NA | G3: 2026-03-12 | H3: none_identified | I3: No statewide infertility/IVF coverage mandate identified in source used | J3: no_statewide_ivf_mandate_identified | K3: 0 | L3: 0 | M3: 0 | N3: 0 | O3: not identified | P3: 0 | Q3: 0 | R3: 0 | U3: none_identified | V3: 0 | X3: no_statewide_ivf_treatment_eligibility_rule_identified | Y3: no_statewide_ivf_treatment_eligibility_rule_identified | Z3: no_statewide_ivf_treatment_eligibility_rule_identified | AA3: not_applicable_no_statewide_ivf_treatment_mandate | AB3: not_applicable_no_statewide_ivf_treatment_mandate | AC3: none stated in source used | AD3: no_statewide_ivf_treatment_eligibility_rule_identified | AE3: no_statewide_ivf_treatment_eligibility_rule_identified | AF3: no_statewide_ivf_treatment_eligibility_rule_identified | AG3: no_statewide_ivf_treatment_eligibility_rule_identified | AH3: not_identified_in_secondary_sources_used | AI3: not_identified_in_secondary_sources_used | AJ3: not_identified_in_secondary_sources_used | AK3: not_identified_in_secondary_sources_used | AL3: not_identified_in_secondary_sources_used | AM3: restricted | AN3: unclear | AO3: no_or_unclear | AP3: unclear | AQ3: adoption or post-birth process often required | AR3: no_fertility_specific_state_clinic_license_coded_in_this_pass | AS3: federal_CDC_NASS_reporting_baseline | AT3: federal_FCSRCA_CDC_public_reporting | AU3: CLIA_CMS_FDA_baseline; state_variation_not_fully_coded | AV3: 0 | AW3: 0 | AX3: 0 | AY3: =BU3 -> 38 | AZ3: 1 | BA3: 192 | BB3: 740133 | BC3: FFM | BD3: divided_government | BE3: supportive_or_protective | BF3: No statewide infertility/IVF mandate identified in Triage Cancer state-law chart | BG3: https://triagecancer.org/state-laws/health-insurance-fertility-services | BH3: https://triagecancer.org/state-laws/health-insurance-fertility-services; https://surrogacy360.org/wp-content/uploads/2024/08/Regulation-Details-in-the-US-by-State_8.6.24.pdf; https://www.asrm.org/advocacy-and-policy/reproductive-rights/summary-reports/state-abortion-laws-potential-implications-for-reproductive-medicine/; https://www.guttmacher.org/2025/12/state-policy-trends-2025-full-year-analysis; https://www.cdc.gov/art/php/nass/index.html; https://www.cdc.gov/art/success-rates/index.html; https://www.cms.gov/medicare/quality/clinical-laboratory-improvement-amendments; https://www.cms.gov/marketplace/in-person-assisters/training-webinars/training/marketplaces-map; https://ballotpedia.org/State_government_trifectas; https://www.britannica.com/topic/largest-U-S-state-by-population; https://www.guttmacher.org/united-states/abortion | BI3: Starter row only. Needs primary-law verification for Medicaid, public funding, eligibility, embryo rules, surrogacy, clinic regulation, and utilization variables. Surrogacy fields coded from Surrogacy360 2024 state-by-state summary; interpret as starter classification requiring legal review for publication. Eligibility/LGBTQ fields on this row were filled as a 2026 starter classification based on absence of a statewide IVF-treatment mandate or unclear scope in the source used; this should not be interpreted as a full review of all private plans or clinic access in the state. Embryo/personhood/disposition fields were filled conservatively in this pass. Unless a state had a clear embryo-specific rule in the secondary sources used, values were set to not_identified_in_secondary_sources_used rather than treated as definitive absence of law. Clinic/reporting fields in this pass were coded from federal baselines: CDC NASS/FCSRCA reporting and CMS CLIA materials; insurance marketplace type from CMS Plan Year 2026 marketplace map; political control from Ballotpedia current trifecta status; population uses 2024 state estimate table summarized by Britannica from U.S. Census data. IVF clinic counts and cycle counts remain blank pending direct state-level CDC extraction. | BJ3: RRM | BK3: partially_filled_needs_primary_law_review | BL3: =IFERROR((AZ3/BB3)*1000000,0) -> 1.3511085 | BM3: =IFERROR((BA3/BB3)*1000000,0) -> 259.41284 | BN3: =IFERROR(VLOOKUP(H3,index_logic!$A$4:$B$8,2,FALSE),0) -> 0 | BO3: =IFERROR(VLOOKUP(AD3,index_logic!$D$4:$E$21,2,FALSE),0) -> 3 | BP3: =IFERROR(VLOOKUP(AM3,index_logic!$G$4:$H$6,2,FALSE),0) -> 3 | BQ3: =IFERROR(VLOOKUP(AH3,index_logic!$J$4:$K$6,2,FALSE),0) -> 15 | BR3: =IFERROR(VLOOKUP(BE3,index_logic!$M$4:$N$7,2,FALSE),0) -> 10 | BS3: =IFERROR(VLOOKUP(BL3,index_logic!$P$4:$Q$9,2,TRUE),0) -> 5 | BT3: =IFERROR(VLOOKUP(BM3,index_logic!$S$4:$T$9,2,TRUE),0) -> 2 | BU3: =BN3+BO3+BP3+BQ3+BR3+BS3+BT3 -> 38 | BV3: =IF(BU3>=80,"Very High",IF(BU3>=65,"High",IF(BU3>=50,"Moderate",IF(BU3>=35,"Low","Very Low")))) -> Low
A4: Arizona | B4: AZ | C4: 2026 | D4: current_snapshot | E4: 0 | F4: NA | G4: 2026-03-12 | H4: none_identified | I4: No statewide infertility/IVF coverage mandate identified in source used | J4: no_statewide_ivf_mandate_identified | K4: 0 | L4: 0 | M4: 0 | N4: 0 | O4: not identified | P4: 0 | Q4: 0 | R4: 0 | U4: none_identified | V4: 0 | X4: no_statewide_ivf_treatment_eligibility_rule_identified | Y4: no_statewide_ivf_treatment_eligibility_rule_identified | Z4: no_statewide_ivf_treatment_eligibility_rule_identified | AA4: not_applicable_no_statewide_ivf_treatment_mandate | AB4: not_applicable_no_statewide_ivf_treatment_mandate | AC4: none stated in source used | AD4: no_statewide_ivf_treatment_eligibility_rule_identified | AE4: no_statewide_ivf_treatment_eligibility_rule_identified | AF4: no_statewide_ivf_treatment_eligibility_rule_identified | AG4: no_statewide_ivf_treatment_eligibility_rule_identified | AH4: not_identified_in_secondary_sources_used | AI4: not_identified_in_secondary_sources_used | AJ4: not_identified_in_secondary_sources_used | AK4: not_identified_in_secondary_sources_used | AL4: not_identified_in_secondary_sources_used | AM4: restricted | AN4: unclear | AO4: limited | AP4: unclear | AQ4: limited court recognition; extra conditions apply | AR4: no_fertility_specific_state_clinic_license_coded_in_this_pass | AS4: federal_CDC_NASS_reporting_baseline | AT4: federal_FCSRCA_CDC_public_reporting | AU4: CLIA_CMS_FDA_baseline; state_variation_not_fully_coded | AV4: 0 | AW4: 0 | AX4: 0 | AY4: =BU4 -> 31 | AZ4: 10 | BA4: 3680 | BB4: 7582384 | BC4: FFM | BD4: divided_government | BE4: restrictive | BF4: No statewide infertility/IVF mandate identified in Triage Cancer state-law chart | BG4: https://triagecancer.org/state-laws/health-insurance-fertility-services | BH4: https://triagecancer.org/state-laws/health-insurance-fertility-services; https://surrogacy360.org/wp-content/uploads/2024/08/Regulation-Details-in-the-US-by-State_8.6.24.pdf; https://www.asrm.org/advocacy-and-policy/reproductive-rights/summary-reports/state-abortion-laws-potential-implications-for-reproductive-medicine/; https://www.guttmacher.org/2025/12/state-policy-trends-2025-full-year-analysis; https://www.cdc.gov/art/php/nass/index.html; https://www.cdc.gov/art/success-rates/index.html; https://www.cms.gov/medicare/quality/clinical-laboratory-improvement-amendments; https://www.cms.gov/marketplace/in-person-assisters/training-webinars/training/marketplaces-map; https://ballotpedia.org/State_government_trifectas; https://www.britannica.com/topic/largest-U-S-state-by-population; https://www.guttmacher.org/united-states/abortion | BI4: Starter row only. Needs primary-law verification for Medicaid, public funding, eligibility, embryo rules, surrogacy, clinic regulation, and utilization variables. Surrogacy fields coded from Surrogacy360 2024 state-by-state summary; interpret as starter classification requiring legal review for publication. Eligibility/LGBTQ fields on this row were filled as a 2026 starter classification based on absence of a statewide IVF-treatment mandate or unclear scope in the source used; this should not be interpreted as a full review of all private plans or clinic access in the state. Embryo/personhood/disposition fields were filled conservatively in this pass. Unless a state had a clear embryo-specific rule in the secondary sources used, values were set to not_identified_in_secondary_sources_used rather than treated as definitive absence of law. Clinic/reporting fields in this pass were coded from federal baselines: CDC NASS/FCSRCA reporting and CMS CLIA materials; insurance marketplace type from CMS Plan Year 2026 marketplace map; political control from Ballotpedia current trifecta status; population uses 2024 state estimate table summarized by Britannica from U.S. Census data. IVF clinic counts and cycle counts remain blank pending direct state-level CDC extraction. | BJ4: RRM | BK4: partially_filled_needs_primary_law_review | BL4: =IFERROR((AZ4/BB4)*1000000,0) -> 1.3188464 | BM4: =IFERROR((BA4/BB4)*1000000,0) -> 485.33548 | BN4: =IFERROR(VLOOKUP(H4,index_logic!$A$4:$B$8,2,FALSE),0) -> 0 | BO4: =IFERROR(VLOOKUP(AD4,index_logic!$D$4:$E$21,2,FALSE),0) -> 3 | BP4: =IFERROR(VLOOKUP(AM4,index_logic!$G$4:$H$6,2,FALSE),0) -> 3 | BQ4: =IFERROR(VLOOKUP(AH4,index_logic!$J$4:$K$6,2,FALSE),0) -> 15 | BR4: =IFERROR(VLOOKUP(BE4,index_logic!$M$4:$N$7,2,FALSE),0) -> 3 | BS4: =IFERROR(VLOOKUP(BL4,index_logic!$P$4:$Q$9,2,TRUE),0) -> 5 | BT4: =IFERROR(VLOOKUP(BM4,index_logic!$S$4:$T$9,2,TRUE),0) -> 2 | BU4: =BN4+BO4+BP4+BQ4+BR4+BS4+BT4 -> 31 | BV4: =IF(BU4>=80,"Very High",IF(BU4>=65,"High",IF(BU4>=50,"Moderate",IF(BU4>=35,"Low","Very Low")))) -> Very Low
A5: Arkansas | B5: AR | C5: 2026 | D5: active | E5: 1987 | F5: NA | G5: 2026-03-12 | H5: cover | I5: IVF coverage in individual and group policies with maternity benefits (except HMOs) | J5: IVF-specific | K5: not specified | L5: $15,000 lifetime maximum | M5: 15000 | N5: unclear | O5: not identified | P5: not specified | Q5: not specified | R5: not identified | S5: not identified | T5: not identified | U5: none_identified | V5: 0 | W5: not identified | X5: married_spousal_gametes_required | Y5: 2 years unexplained infertility or specified medical conditions | Z5: must first fail less costly covered infertility treatment | AA5: not specified in source used | AB5: not specified in source used | AC5: none stated in source used | AD5: restricted_spouse_and_spousal_sperm_requirement | AE5: excluded_spouse_required | AF5: not explicitly addressed; sex/marriage-linked eligibility | AG5: patient oocytes must be fertilized with spouse sperm | AH5: not_identified_in_secondary_sources_used | AI5: not_identified_in_secondary_sources_used | AJ5: not_identified_in_secondary_sources_used | AK5: not_identified_in_secondary_sources_used | AL5: not_identified_in_secondary_sources_used | AM5: restricted | AN5: unclear | AO5: no_or_unclear | AP5: unclear | AQ5: adoption or post-birth process often required | AR5: no_fertility_specific_state_clinic_license_coded_in_this_pass | AS5: federal_CDC_NASS_reporting_baseline | AT5: federal_FCSRCA_CDC_public_reporting | AU5: CLIA_CMS_FDA_baseline; state_variation_not_fully_coded | AV5: 1987 | AW5: 2026 | AX5: 0 | AY5: =BU5 -> 52 | AZ5: 1 | BA5: 1113 | BB5: 3088354 | BC5: SBM-FP | BD5: republican_trifecta | BE5: near_total_ban_or_total_ban_environment | BF5: AR Code § 23-85-137 | BG5: https://law.justia.com/codes/arkansas/title-23/subtitle-3/chapter-85/section-23-85-137/ | BH5: https://triagecancer.org/state-laws/health-insurance-fertility-services; https://surrogacy360.org/wp-content/uploads/2024/08/Regulation-Details-in-the-US-by-State_8.6.24.pdf; https://www.reproductivefacts.org/patient-advocacy/state-and-territory-infertility-insurance-laws/arkansas/; https://www.asrm.org/advocacy-and-policy/reproductive-rights/summary-reports/state-abortion-laws-potential-implications-for-reproductive-medicine/; https://www.guttmacher.org/2025/12/state-policy-trends-2025-full-year-analysis; https://www.cdc.gov/art/php/nass/index.html; https://www.cdc.gov/art/success-rates/index.html; https://www.cms.gov/medicare/quality/clinical-laboratory-improvement-amendments; https://www.cms.gov/marketplace/in-person-assisters/training-webinars/training/marketplaces-map; https://ballotpedia.org/State_government_trifectas; https://www.britannica.com/topic/largest-U-S-state-by-population; https://www.guttmacher.org/united-states/abortion | BI5: Triage chart says IVF required; cryopreservation included; $15,000 lifetime max; coverage applies to policies with maternity benefits except HMOs. Surrogacy fields coded from Surrogacy360 2024 state-by-state summary; interpret as starter classification requiring legal review for publication. Eligibility/LGBTQ fields updated in this pass using current 2026 state-law summaries and/or statute text where available; some entries remain conservative where the source did not clearly resolve LGBTQ or gender-identity treatment eligibility. Embryo/personhood/disposition fields were filled conservatively in this pass. Unless a state had a clear embryo-specific rule in the secondary sources used, values were set to not_identified_in_secondary_sources_used rather than treated as definitive absence of law. Clinic/reporting fields in this pass were coded from federal baselines: CDC NASS/FCSRCA reporting and CMS CLIA materials; insurance marketplace type from CMS Plan Year 2026 marketplace map; political control from Ballotpedia current trifecta status; population uses 2024 state estimate table summarized by Britannica from U.S. Census data. IVF clinic counts and cycle counts remain blank pending direct state-level CDC extraction. | BJ5: RRM | BK5: partially_filled_needs_primary_law_review | BL5: =IFERROR((AZ5/BB5)*1000000,0) -> 0.32379708 | BM5: =IFERROR((BA5/BB5)*1000000,0) -> 360.38615 | BN5: =IFERROR(VLOOKUP(H5,index_logic!$A$4:$B$8,2,FALSE),0) -> 30 | BO5: =IFERROR(VLOOKUP(AD5,index_logic!$D$4:$E$21,2,FALSE),0) -> 0 | BP5: =IFERROR(VLOOKUP(AM5,index_logic!$G$4:$H$6,2,FALSE),0) -> 3 | BQ5: =IFERROR(VLOOKUP(AH5,index_logic!$J$4:$K$6,2,FALSE),0) -> 15 | BR5: =IFERROR(VLOOKUP(BE5,index_logic!$M$4:$N$7,2,FALSE),0) -> 0 | BS5: =IFERROR(VLOOKUP(BL5,index_logic!$P$4:$Q$9,2,TRUE),0) -> 2 | BT5: =IFERROR(VLOOKUP(BM5,index_logic!$S$4:$T$9,2,TRUE),0) -> 2 | BU5: =BN5+BO5+BP5+BQ5+BR5+BS5+BT5 -> 52 | BV5: =IF(BU5>=80,"Very High",IF(BU5>=65,"High",IF(BU5>=50,"Moderate",IF(BU5>=35,"Low","Very Low")))) -> Moderate
A6: California | B6: CA | C6: 2026 | D6: active | E6: 2026 | F6: NA | G6: 2026-03-12 | H6: mixed_cover_offer | I6: Large group must cover infertility diagnosis/treatment incl IVF; small group must offer coverage | J6: Infertility + IVF (large group); offer-only for small group | K6: 3 oocyte retrievals | L6: not specified | M6: not specified | N6: yes | O6: yes | P6: not specified | Q6: Unlimited embryo transfers under ASRM guidelines | R6: yes | S6: excluded for Medi-Cal managed care | T6: Medi-Cal managed care excluded from SB 729 infertility coverage | U6: none_identified | V6: 0 | W6: CalPERS plans exempt until 2027-07-01 | X6: none stated | Y6: broad definition noted by source; includes same-sex couples and single people | Z6: none stated in source used | AA6: not specified in source used | AB6: not specified in source used | AC6: none stated in source used | AD6: explicitly inclusive | AE6: explicitly inclusive | AF6: not explicitly addressed in source used | AG6: none stated in source used | AH6: not_identified_in_secondary_sources_used | AI6: not_identified_in_secondary_sources_used | AJ6: not_identified_in_secondary_sources_used | AK6: not_identified_in_secondary_sources_used | AL6: not_identified_in_secondary_sources_used | AM6: legal | AN6: yes | AO6: yes | AP6: yes | AQ6: court-recognized parentage available | AR6: no_fertility_specific_state_clinic_license_coded_in_this_pass | AS6: federal_CDC_NASS_reporting_baseline | AT6: federal_FCSRCA_CDC_public_reporting | AU6: CLIA_CMS_FDA_baseline; state_variation_not_fully_coded | AV6: 2024 | AW6: 2026 | AX6: 0 | AY6: =BU6 -> 88 | AZ6: 85 | BA6: 63018 | BB6: 39431263 | BC6: SBM | BD6: democratic_trifecta | BE6: supportive_or_protective | BF6: SB 729 (2024); SB 600 (2019) | BG6: https://leginfo.legislature.ca.gov/faces/billTextClient.xhtml?bill_id=202320240SB729 | BH6: https://triagecancer.org/state-laws/health-insurance-fertility-services; https://surrogacy360.org/wp-content/uploads/2024/08/Regulation-Details-in-the-US-by-State_8.6.24.pdf; https://calmatters.org/newsletter/ivf-law-expansion/; https://www.asrm.org/advocacy-and-policy/reproductive-rights/summary-reports/state-abortion-laws-potential-implications-for-reproductive-medicine/; https://www.guttmacher.org/2025/12/state-policy-trends-2025-full-year-analysis; https://www.cdc.gov/art/php/nass/index.html; https://www.cdc.gov/art/success-rates/index.html; https://www.cms.gov/medicare/quality/clinical-laboratory-improvement-amendments; https://www.cms.gov/marketplace/in-person-assisters/training-webinars/training/marketplaces-map; https://ballotpedia.org/State_government_trifectas; https://www.britannica.com/topic/largest-U-S-state-by-population; https://www.guttmacher.org/united-states/abortion | BI6: Triage notes implementation delayed to 2026-01-01 from 2025-07-01; source also lists fertility preservation coverage under SB 600. Surrogacy fields coded from Surrogacy360 2024 state-by-state summary; interpret as starter classification requiring legal review for publication. Eligibility/LGBTQ fields updated in this pass using current 2026 state-law summaries and/or statute text where available; some entries remain conservative where the source did not clearly resolve LGBTQ or gender-identity treatment eligibility. Embryo/personhood/disposition fields were filled conservatively in this pass. Unless a state had a clear embryo-specific rule in the secondary sources used, values were set to not_identified_in_secondary_sources_used rather than treated as definitive absence of law. Clinic/reporting fields in this pass were coded from federal baselines: CDC NASS/FCSRCA reporting and CMS CLIA materials; insurance marketplace type from CMS Plan Year 2026 marketplace map; political control from Ballotpedia current trifecta status; population uses 2024 state estimate table summarized by Britannica from U.S. Census data. IVF clinic counts and cycle counts remain blank pending direct state-level CDC extraction. | BJ6: RRM | BK6: partially_filled_needs_primary_law_review | BL6: =IFERROR((AZ6/BB6)*1000000,0) -> 2.1556499 | BM6: =IFERROR((BA6/BB6)*1000000,0) -> 1598.1735 | BN6: =IFERROR(VLOOKUP(H6,index_logic!$A$4:$B$8,2,FALSE),0) -> 22 | BO6: =IFERROR(VLOOKUP(AD6,index_logic!$D$4:$E$21,2,FALSE),0) -> 20 | BP6: =IFERROR(VLOOKUP(AM6,index_logic!$G$4:$H$6,2,FALSE),0) -> 10 | BQ6: =IFERROR(VLOOKUP(AH6,index_logic!$J$4:$K$6,2,FALSE),0) -> 15 | BR6: =IFERROR(VLOOKUP(BE6,index_logic!$M$4:$N$7,2,FALSE),0) -> 10 | BS6: =IFERROR(VLOOKUP(BL6,index_logic!$P$4:$Q$9,2,TRUE),0) -> 5 | BT6: =IFERROR(VLOOKUP(BM6,index_logic!$S$4:$T$9,2,TRUE),0) -> 6 | BU6: =BN6+BO6+BP6+BQ6+BR6+BS6+BT6 -> 88 | BV6: =IF(BU6>=80,"Very High",IF(BU6>=65,"High",IF(BU6>=50,"Moderate",IF(BU6>=35,"Low","Very Low")))) -> Very High
A7: Colorado | B7: CO | C7: 2026 | D7: active | E7: 2022 | F7: NA | G7: 2026-03-12 | H7: cover | I7: Infertility diagnosis, treatment, and standard fertility preservation | J7: Comprehensive infertility + IVF | K7: 3 oocyte retrievals | L7: not specified | M7: not specified | N7: yes | O7: yes | P7: not specified | Q7: Unlimited embryo transfers under ASRM guidelines | R7: yes | S7: not identified | T7: not identified | U7: none_identified | V7: 0 | W7: not identified | X7: none stated | Y7: includes inability to reproduce as an individual or with the person's partner | Z7: none stated in source used | AA7: no arbitrary age limit allowed | AB7: no arbitrary age limit allowed | AC7: none stated in source used | AD7: inclusive gender-neutral definition | AE7: inclusive individual-or-partner definition | AF7: gender-neutral definition; no explicit gender-identity clause cited | AG7: none stated in source used | AH7: not_identified_in_secondary_sources_used | AI7: not_identified_in_secondary_sources_used | AJ7: not_identified_in_secondary_sources_used | AK7: not_identified_in_secondary_sources_used | AL7: not_identified_in_secondary_sources_used | AM7: legal | AN7: yes | AO7: yes | AP7: no | AQ7: court-recognized parentage available | AR7: no_fertility_specific_state_clinic_license_coded_in_this_pass | AS7: federal_CDC_NASS_reporting_baseline | AT7: federal_FCSRCA_CDC_public_reporting | AU7: CLIA_CMS_FDA_baseline; state_variation_not_fully_coded | AV7: 2020 | AW7: 2022 | AX7: 0 | AY7: =BU7 -> 92 | AZ7: 11 | BA7: 5258 | BB7: 5957493 | BC7: SBM | BD7: democratic_trifecta | BE7: supportive_or_protective | BF7: HB20-1158 (Colorado Building Families Act) | BG7: https://leg.colorado.gov/bills/hb20-1158 | BH7: https://triagecancer.org/state-laws/health-insurance-fertility-services; https://surrogacy360.org/wp-content/uploads/2024/08/Regulation-Details-in-the-US-by-State_8.6.24.pdf; https://www.reproductivefacts.org/patient-advocacy/state-and-territory-infertility-insurance-laws/colorado/; https://www.asrm.org/advocacy-and-policy/reproductive-rights/summary-reports/state-abortion-laws-potential-implications-for-reproductive-medicine/; https://www.guttmacher.org/2025/12/state-policy-trends-2025-full-year-analysis; https://www.cdc.gov/art/php/nass/index.html; https://www.cdc.gov/art/success-rates/index.html; https://www.cms.gov/medicare/quality/clinical-laboratory-improvement-amendments; https://www.cms.gov/marketplace/in-person-assisters/training-webinars/training/marketplaces-map; https://ballotpedia.org/State_government_trifectas; https://www.britannica.com/topic/largest-U-S-state-by-population; https://www.guttmacher.org/united-states/abortion | BI7: Triage notes individual/small-group coverage may depend on federal cost-defrayal determinations. Surrogacy fields coded from Surrogacy360 2024 state-by-state summary; interpret as starter classification requiring legal review for publication. Eligibility/LGBTQ fields updated in this pass using current 2026 state-law summaries and/or statute text where available; some entries remain conservative where the source did not clearly resolve LGBTQ or gender-identity treatment eligibility. Embryo/personhood/disposition fields were filled conservatively in this pass. Unless a state had a clear embryo-specific rule in the secondary sources used, values were set to not_identified_in_secondary_sources_used rather than treated as definitive absence of law. Clinic/reporting fields in this pass were coded from federal baselines: CDC NASS/FCSRCA reporting and CMS CLIA materials; insurance marketplace type from CMS Plan Year 2026 marketplace map; political control from Ballotpedia current trifecta status; population uses 2024 state estimate table summarized by Britannica from U.S. Census data. IVF clinic counts and cycle counts remain blank pending direct state-level CDC extraction. | BJ7: RRM | BK7: partially_filled_needs_primary_law_review | BL7: =IFERROR((AZ7/BB7)*1000000,0) -> 1.8464143 | BM7: =IFERROR((BA7/BB7)*1000000,0) -> 882.58601 | BN7: =IFERROR(VLOOKUP(H7,index_logic!$A$4:$B$8,2,FALSE),0) -> 30 | BO7: =IFERROR(VLOOKUP(AD7,index_logic!$D$4:$E$21,2,FALSE),0) -> 18 | BP7: =IFERROR(VLOOKUP(AM7,index_logic!$G$4:$H$6,2,FALSE),0) -> 10 | BQ7: =IFERROR(VLOOKUP(AH7,index_logic!$J$4:$K$6,2,FALSE),0) -> 15 | BR7: =IFERROR(VLOOKUP(BE7,index_logic!$M$4:$N$7,2,FALSE),0) -> 10 | BS7: =IFERROR(VLOOKUP(BL7,index_logic!$P$4:$Q$9,2,TRUE),0) -> 5 | BT7: =IFERROR(VLOOKUP(BM7,index_logic!$S$4:$T$9,2,TRUE),0) -> 4 | BU7: =BN7+BO7+BP7+BQ7+BR7+BS7+BT7 -> 92 | BV7: =IF(BU7>=80,"Very High",IF(BU7>=65,"High",IF(BU7>=50,"Moderate",IF(BU7>=35,"Low","Very Low")))) -> Very High
A8: Connecticut | B8: CT | C8: 2026 | D8: active | E8: 2018 | F8: NA | G8: 2026-03-12 | H8: cover | I8: Medically necessary infertility diagnosis and treatment, including IVF | J8: Infertility + IVF | K8: lifetime cycle limits apply (source does not specify count) | L8: lifetime cycle limits | M8: not specified | N8: yes | O8: yes | P8: not specified | Q8: not specified | R8: yes | S8: not identified | T8: not identified | U8: none_identified | V8: 0 | W8: not identified | X8: none stated | Y8: individual unable to conceive, produce conception, or sustain successful pregnancy during 1-year period, or treatment is medically necessary | Z8: less expensive medically viable treatment first before IVF/GIFT/ZIFT/low tubal ovum transfer unless likely unsuccessful | AA8: up to age 40 for IVF-related services | AB8: not specified in source used | AC8: none stated in source used | AD8: gender-neutral individual definition; not explicitly addressed beyond that | AE8: likely inclusive via individual definition | AF8: not explicitly addressed in source used | AG8: none stated in source used | AH8: not_identified_in_secondary_sources_used | AI8: not_identified_in_secondary_sources_used | AJ8: not_identified_in_secondary_sources_used | AK8: not_identified_in_secondary_sources_used | AL8: not_identified_in_secondary_sources_used | AM8: legal | AN8: yes | AO8: yes | AP8: no | AQ8: court-recognized parentage available | AR8: no_fertility_specific_state_clinic_license_coded_in_this_pass | AS8: federal_CDC_NASS_reporting_baseline | AT8: federal_FCSRCA_CDC_public_reporting | AU8: CLIA_CMS_FDA_baseline; state_variation_not_fully_coded | AV8: 2017 | AW8: 2018 | AX8: 0 | AY8: =BU8 -> 88 | AZ8: 7 | BA8: 4497 | BB8: 3675069 | BC8: SBM | BD8: democratic_trifecta | BE8: supportive_or_protective | BF8: HB 7124 (2017) | BG8: https://www.cga.ct.gov/asp/cgabillstatus/cgabillstatus.asp?selBillType=Bill&bill_num=HB07124&which_year=2017 | BH8: https://triagecancer.org/state-laws/health-insurance-fertility-services; https://surrogacy360.org/wp-content/uploads/2024/08/Regulation-Details-in-the-US-by-State_8.6.24.pdf; https://www.reproductivefacts.org/patient-advocacy/state-and-territory-infertility-insurance-laws/connecticut/; https://www.asrm.org/advocacy-and-policy/reproductive-rights/summary-reports/state-abortion-laws-potential-implications-for-reproductive-medicine/; https://www.guttmacher.org/2025/12/state-policy-trends-2025-full-year-analysis; https://www.cdc.gov/art/php/nass/index.html; https://www.cdc.gov/art/success-rates/index.html; https://www.cms.gov/medicare/quality/clinical-laboratory-improvement-amendments; https://www.cms.gov/marketplace/in-person-assisters/training-webinars/training/marketplaces-map; https://ballotpedia.org/State_government_trifectas; https://www.britannica.com/topic/largest-U-S-state-by-population; https://www.guttmacher.org/united-states/abortion | BI8: Source notes age cap up to 40 and requirement to try less costly treatments first. Surrogacy fields coded from Surrogacy360 2024 state-by-state summary; interpret as starter classification requiring legal review for publication. Eligibility/LGBTQ fields updated in this pass using current 2026 state-law summaries and/or statute text where available; some entries remain conservative where the source did not clearly resolve LGBTQ or gender-identity treatment eligibility. Embryo/personhood/disposition fields were filled conservatively in this pass. Unless a state had a clear embryo-specific rule in the secondary sources used, values were set to not_identified_in_secondary_sources_used rather than treated as definitive absence of law. Clinic/reporting fields in this pass were coded from federal baselines: CDC NASS/FCSRCA reporting and CMS CLIA materials; insurance marketplace type from CMS Plan Year 2026 marketplace map; political control from Ballotpedia current trifecta status; population uses 2024 state estimate table summarized by Britannica from U.S. Census data. IVF clinic counts and cycle counts remain blank pending direct state-level CDC extraction. | BJ8: RRM | BK8: partially_filled_needs_primary_law_review | BL8: =IFERROR((AZ8/BB8)*1000000,0) -> 1.9047261 | BM8: =IFERROR((BA8/BB8)*1000000,0) -> 1223.6505 | BN8: =IFERROR(VLOOKUP(H8,index_logic!$A$4:$B$8,2,FALSE),0) -> 30 | BO8: =IFERROR(VLOOKUP(AD8,index_logic!$D$4:$E$21,2,FALSE),0) -> 12 | BP8: =IFERROR(VLOOKUP(AM8,index_logic!$G$4:$H$6,2,FALSE),0) -> 10 | BQ8: =IFERROR(VLOOKUP(AH8,index_logic!$J$4:$K$6,2,FALSE),0) -> 15 | BR8: =IFERROR(VLOOKUP(BE8,index_logic!$M$4:$N$7,2,FALSE),0) -> 10 | BS8: =IFERROR(VLOOKUP(BL8,index_logic!$P$4:$Q$9,2,TRUE),0) -> 5 | BT8: =IFERROR(VLOOKUP(BM8,index_logic!$S$4:$T$9,2,TRUE),0) -> 6 | BU8: =BN8+BO8+BP8+BQ8+BR8+BS8+BT8 -> 88 | BV8: =IF(BU8>=80,"Very High",IF(BU8>=65,"High",IF(BU8>=50,"Moderate",IF(BU8>=35,"Low","Very Low")))) -> Very High
A9: Delaware | B9: DE | C9: 2026 | D9: active | E9: 2018 | F9: NA | G9: 2026-03-12 | H9: cover | I9: Infertility diagnosis and treatment including IVF + fertility preservation | J9: Comprehensive infertility + IVF | K9: 6 completed egg retrievals per lifetime | L9: 6 egg retrievals lifetime | M9: not specified | N9: yes | O9: yes | P9: not specified | Q9: Unlimited embryo transfers under ASRM guidelines | R9: not identified | S9: not identified | T9: not identified | U9: none_identified | V9: 0 | W9: not identified | X9: none stated | Y9: individual unable to procreate or carry pregnancy to live birth | Z9: reasonable effort with less costly covered treatment first; no more than 3 ovulation induction or IUI cycles before IVF unless IVF medically necessary | AA9: retrieval before 45; transfer before 50 | AB9: not specified in source used | AC9: none stated in source used | AD9: inclusive individual definition and coverage extends to non-spouse dependents | AE9: likely inclusive individual definition | AF9: not explicitly addressed in source used | AG9: none stated in source used | AH9: not_identified_in_secondary_sources_used | AI9: not_identified_in_secondary_sources_used | AJ9: not_identified_in_secondary_sources_used | AK9: not_identified_in_secondary_sources_used | AL9: not_identified_in_secondary_sources_used | AM9: legal | AN9: yes | AO9: yes | AP9: yes_or_unspecified_genetic | AQ9: court-recognized parentage available | AR9: no_fertility_specific_state_clinic_license_coded_in_this_pass | AS9: federal_CDC_NASS_reporting_baseline | AT9: federal_FCSRCA_CDC_public_reporting | AU9: CLIA_CMS_FDA_baseline; state_variation_not_fully_coded | AV9: 2018 | AW9: 2018 | AX9: 0 | AY9: =BU9 -> 92 | AZ9: 2 | BA9: 1076 | BB9: 1051917 | BC9: FFM | BD9: democratic_trifecta | BE9: supportive_or_protective | BF9: S 139 (2018) | BG9: https://legis.delaware.gov/BillDetail?LegislationId=26219 | BH9: https://triagecancer.org/state-laws/health-insurance-fertility-services; https://surrogacy360.org/wp-content/uploads/2024/08/Regulation-Details-in-the-US-by-State_8.6.24.pdf; https://www.reproductivefacts.org/patient-advocacy/state-and-territory-infertility-insurance-laws/delaware/; https://www.asrm.org/advocacy-and-policy/reproductive-rights/summary-reports/state-abortion-laws-potential-implications-for-reproductive-medicine/; https://www.guttmacher.org/2025/12/state-policy-trends-2025-full-year-analysis; https://www.cdc.gov/art/php/nass/index.html; https://www.cdc.gov/art/success-rates/index.html; https://www.cms.gov/medicare/quality/clinical-laboratory-improvement-amendments; https://www.cms.gov/marketplace/in-person-assisters/training-webinars/training/marketplaces-map; https://ballotpedia.org/State_government_trifectas; https://www.britannica.com/topic/largest-U-S-state-by-population; https://www.guttmacher.org/united-states/abortion | BI9: Source says insurers may not impose different cost sharing or restrictions compared with other medical services. Surrogacy fields coded from Surrogacy360 2024 state-by-state summary; interpret as starter classification requiring legal review for publication. Eligibility/LGBTQ fields updated in this pass using current 2026 state-law summaries and/or statute text where available; some entries remain conservative where the source did not clearly resolve LGBTQ or gender-identity treatment eligibility. Embryo/personhood/disposition fields were filled conservatively in this pass. Unless a state had a clear embryo-specific rule in the secondary sources used, values were set to not_identified_in_secondary_sources_used rather than treated as definitive absence of law. Clinic/reporting fields in this pass were coded from federal baselines: CDC NASS/FCSRCA reporting and CMS CLIA materials; insurance marketplace type from CMS Plan Year 2026 marketplace map; political control from Ballotpedia current trifecta status; population uses 2024 state estimate table summarized by Britannica from U.S. Census data. IVF clinic counts and cycle counts remain blank pending direct state-level CDC extraction. | BJ9: RRM | BK9: partially_filled_needs_primary_law_review | BL9: =IFERROR((AZ9/BB9)*1000000,0) -> 1.9012907 | BM9: =IFERROR((BA9/BB9)*1000000,0) -> 1022.8944 | BN9: =IFERROR(VLOOKUP(H9,index_logic!$A$4:$B$8,2,FALSE),0) -> 30 | BO9: =IFERROR(VLOOKUP(AD9,index_logic!$D$4:$E$21,2,FALSE),0) -> 18 | BP9: =IFERROR(VLOOKUP(AM9,index_logic!$G$4:$H$6,2,FALSE),0) -> 10 | BQ9: =IFERROR(VLOOKUP(AH9,index_logic!$J$4:$K$6,2,FALSE),0) -> 15 | BR9: =IFERROR(VLOOKUP(BE9,index_logic!$M$4:$N$7,2,FALSE),0) -> 10 | BS9: =IFERROR(VLOOKUP(BL9,index_logic!$P$4:$Q$9,2,TRUE),0) -> 5 | BT9: =IFERROR(VLOOKUP(BM9,index_logic!$S$4:$T$9,2,TRUE),0) -> 4 | BU9: =BN9+BO9+BP9+BQ9+BR9+BS9+BT9 -> 92 | BV9: =IF(BU9>=80,"Very High",IF(BU9>=65,"High",IF(BU9>=50,"Moderate",IF(BU9>=35,"Low","Very Low")))) -> Very High
A10: Florida | B10: FL | C10: 2026 | D10: active | E10: 0 | F10: NA | G10: 2026-03-12 | H10: none_for_ivf | I10: No statewide infertility/IVF coverage mandate identified in source; fertility preservation law only | J10: fertility_preservation_only | K10: 0 | L10: 0 | M10: 0 | N10: 0 | O10: yes | P10: 0 | Q10: 0 | R10: 0 | S10: not identified | T10: not identified | U10: none_identified | V10: 0 | W10: fertility_preservation_only in state group plan | X10: no_statewide_ivf_treatment_rule_identified_fertility_preservation_only_law | Y10: no_statewide_ivf_treatment_rule_identified_fertility_preservation_only_law | Z10: no_statewide_ivf_treatment_rule_identified_fertility_preservation_only_law | AA10: not_applicable_no_statewide_ivf_treatment_mandate | AB10: not_applicable_no_statewide_ivf_treatment_mandate | AC10: none stated in source used | AD10: no_statewide_ivf_treatment_rule_identified_fertility_preservation_only_law | AE10: no_statewide_ivf_treatment_rule_identified_fertility_preservation_only_law | AF10: no_statewide_ivf_treatment_rule_identified_fertility_preservation_only_law | AG10: no_statewide_ivf_treatment_rule_identified_fertility_preservation_only_law | AH10: not_identified_in_secondary_sources_used | AI10: not_identified_in_secondary_sources_used | AJ10: not_identified_in_secondary_sources_used | AK10: not_identified_in_secondary_sources_used | AL10: not_identified_in_secondary_sources_used | AM10: restricted | AN10: limited_expense_payment | AO10: limited | AP10: unclear | AQ10: limited court recognition; extra conditions apply | AR10: no_fertility_specific_state_clinic_license_coded_in_this_pass | AS10: federal_CDC_NASS_reporting_baseline | AT10: federal_FCSRCA_CDC_public_reporting | AU10: CLIA_CMS_FDA_baseline; state_variation_not_fully_coded | AV10: 0 | AW10: 0 | AX10: 0 | AY10: =BU10 -> 34 | AZ10: 27 | BA10: 12743 | BB10: 23372215 | BC10: FFM | BD10: republican_trifecta | BE10: restrictive | BF10: HB 677 (2025) | BG10: https://www.flsenate.gov/Session/Bill/2025/677 | BH10: https://triagecancer.org/state-laws/health-insurance-fertility-services; https://surrogacy360.org/wp-content/uploads/2024/08/Regulation-Details-in-the-US-by-State_8.6.24.pdf; https://www.asrm.org/advocacy-and-policy/reproductive-rights/summary-reports/state-abortion-laws-potential-implications-for-reproductive-medicine/; https://www.guttmacher.org/2025/12/state-policy-trends-2025-full-year-analysis; https://www.cdc.gov/art/php/nass/index.html; https://www.cdc.gov/art/success-rates/index.html; https://www.cms.gov/medicare/quality/clinical-laboratory-improvement-amendments; https://www.cms.gov/marketplace/in-person-assisters/training-webinars/training/marketplaces-map; https://ballotpedia.org/State_government_trifectas; https://www.britannica.com/topic/largest-U-S-state-by-population; https://www.guttmacher.org/united-states/abortion | BI10: State group health insurance must cover fertility retrieval/preservation for cancer-related iatrogenic infertility effective 2026-01-01. Surrogacy fields coded from Surrogacy360 2024 state-by-state summary; interpret as starter classification requiring legal review for publication. Eligibility/LGBTQ fields on this row were filled as a 2026 starter classification based on absence of a statewide IVF-treatment mandate or unclear scope in the source used; this should not be interpreted as a full review of all private plans or clinic access in the state. Embryo/personhood/disposition fields were filled conservatively in this pass. Unless a state had a clear embryo-specific rule in the secondary sources used, values were set to not_identified_in_secondary_sources_used rather than treated as definitive absence of law. Clinic/reporting fields in this pass were coded from federal baselines: CDC NASS/FCSRCA reporting and CMS CLIA materials; insurance marketplace type from CMS Plan Year 2026 marketplace map; political control from Ballotpedia current trifecta status; population uses 2024 state estimate table summarized by Britannica from U.S. Census data. IVF clinic counts and cycle counts remain blank pending direct state-level CDC extraction. | BJ10: RRM | BK10: partially_filled_needs_primary_law_review | BL10: =IFERROR((AZ10/BB10)*1000000,0) -> 1.1552179 | BM10: =IFERROR((BA10/BB10)*1000000,0) -> 545.22004 | BN10: =IFERROR(VLOOKUP(H10,index_logic!$A$4:$B$8,2,FALSE),0) -> 4 | BO10: =IFERROR(VLOOKUP(AD10,index_logic!$D$4:$E$21,2,FALSE),0) -> 3 | BP10: =IFERROR(VLOOKUP(AM10,index_logic!$G$4:$H$6,2,FALSE),0) -> 3 | BQ10: =IFERROR(VLOOKUP(AH10,index_logic!$J$4:$K$6,2,FALSE),0) -> 15 | BR10: =IFERROR(VLOOKUP(BE10,index_logic!$M$4:$N$7,2,FALSE),0) -> 3 | BS10: =IFERROR(VLOOKUP(BL10,index_logic!$P$4:$Q$9,2,TRUE),0) -> 4 | BT10: =IFERROR(VLOOKUP(BM10,index_logic!$S$4:$T$9,2,TRUE),0) -> 2 | BU10: =BN10+BO10+BP10+BQ10+BR10+BS10+BT10 -> 34 | BV10: =IF(BU10>=80,"Very High",IF(BU10>=65,"High",IF(BU10>=50,"Moderate",IF(BU10>=35,"Low","Very Low")))) -> Very Low
A11: Georgia | B11: GA | C11: 2026 | D11: current_snapshot | E11: 0 | F11: NA | G11: 2026-03-12 | H11: none_identified | I11: No statewide infertility/IVF coverage mandate identified in source used | J11: no_statewide_ivf_mandate_identified | K11: 0 | L11: 0 | M11: 0 | N11: 0 | O11: not identified | P11: 0 | Q11: 0 | R11: 0 | U11: none_identified | V11: 0 | X11: no_statewide_ivf_treatment_eligibility_rule_identified | Y11: no_statewide_ivf_treatment_eligibility_rule_identified | Z11: no_statewide_ivf_treatment_eligibility_rule_identified | AA11: not_applicable_no_statewide_ivf_treatment_mandate | AB11: not_applicable_no_statewide_ivf_treatment_mandate | AC11: none stated in source used | AD11: no_statewide_ivf_treatment_eligibility_rule_identified | AE11: no_statewide_ivf_treatment_eligibility_rule_identified | AF11: no_statewide_ivf_treatment_eligibility_rule_identified | AG11: no_statewide_ivf_treatment_eligibility_rule_identified | AH11: not_identified_in_secondary_sources_used | AI11: not_identified_in_secondary_sources_used | AJ11: not_identified_in_secondary_sources_used | AK11: not_identified_in_secondary_sources_used | AL11: not_identified_in_secondary_sources_used | AM11: restricted | AN11: unclear | AO11: no_or_unclear | AP11: unclear | AQ11: adoption or post-birth process often required | AR11: no_fertility_specific_state_clinic_license_coded_in_this_pass | AS11: federal_CDC_NASS_reporting_baseline | AT11: federal_FCSRCA_CDC_public_reporting | AU11: CLIA_CMS_FDA_baseline; state_variation_not_fully_coded | AV11: 0 | AW11: 0 | AX11: 0 | AY11: =BU11 -> 31 | AZ11: 17 | BA11: 7664 | BB11: 11180878 | BC11: SBM | BD11: republican_trifecta | BE11: restrictive | BF11: No statewide infertility/IVF mandate identified in Triage Cancer state-law chart | BG11: https://triagecancer.org/state-laws/health-insurance-fertility-services | BH11: https://triagecancer.org/state-laws/health-insurance-fertility-services; https://surrogacy360.org/wp-content/uploads/2024/08/Regulation-Details-in-the-US-by-State_8.6.24.pdf; https://www.asrm.org/advocacy-and-policy/reproductive-rights/summary-reports/state-abortion-laws-potential-implications-for-reproductive-medicine/; https://www.guttmacher.org/2025/12/state-policy-trends-2025-full-year-analysis; https://www.cdc.gov/art/php/nass/index.html; https://www.cdc.gov/art/success-rates/index.html; https://www.cms.gov/medicare/quality/clinical-laboratory-improvement-amendments; https://www.cms.gov/marketplace/in-person-assisters/training-webinars/training/marketplaces-map; https://ballotpedia.org/State_government_trifectas; https://www.britannica.com/topic/largest-U-S-state-by-population; https://www.guttmacher.org/united-states/abortion | BI11: Starter row only. Needs primary-law verification for Medicaid, public funding, eligibility, embryo rules, surrogacy, clinic regulation, and utilization variables. Surrogacy fields coded from Surrogacy360 2024 state-by-state summary; interpret as starter classification requiring legal review for publication. Eligibility/LGBTQ fields on this row were filled as a 2026 starter classification based on absence of a statewide IVF-treatment mandate or unclear scope in the source used; this should not be interpreted as a full review of all private plans or clinic access in the state. Embryo/personhood/disposition fields were filled conservatively in this pass. Unless a state had a clear embryo-specific rule in the secondary sources used, values were set to not_identified_in_secondary_sources_used rather than treated as definitive absence of law. Clinic/reporting fields in this pass were coded from federal baselines: CDC NASS/FCSRCA reporting and CMS CLIA materials; insurance marketplace type from CMS Plan Year 2026 marketplace map; political control from Ballotpedia current trifecta status; population uses 2024 state estimate table summarized by Britannica from U.S. Census data. IVF clinic counts and cycle counts remain blank pending direct state-level CDC extraction. | BJ11: RRM | BK11: partially_filled_needs_primary_law_review | BL11: =IFERROR((AZ11/BB11)*1000000,0) -> 1.520453 | BM11: =IFERROR((BA11/BB11)*1000000,0) -> 685.45601 | BN11: =IFERROR(VLOOKUP(H11,index_logic!$A$4:$B$8,2,FALSE),0) -> 0 | BO11: =IFERROR(VLOOKUP(AD11,index_logic!$D$4:$E$21,2,FALSE),0) -> 3 | BP11: =IFERROR(VLOOKUP(AM11,index_logic!$G$4:$H$6,2,FALSE),0) -> 3 | BQ11: =IFERROR(VLOOKUP(AH11,index_logic!$J$4:$K$6,2,FALSE),0) -> 15 | BR11: =IFERROR(VLOOKUP(BE11,index_logic!$M$4:$N$7,2,FALSE),0) -> 3 | BS11: =IFERROR(VLOOKUP(BL11,index_logic!$P$4:$Q$9,2,TRUE),0) -> 5 | BT11: =IFERROR(VLOOKUP(BM11,index_logic!$S$4:$T$9,2,TRUE),0) -> 2 | BU11: =BN11+BO11+BP11+BQ11+BR11+BS11+BT11 -> 31 | BV11: =IF(BU11>=80,"Very High",IF(BU11>=65,"High",IF(BU11>=50,"Moderate",IF(BU11>=35,"Low","Very Low")))) -> Very Low
A12: Hawaii | B12: HI | C12: 2026 | D12: active | E12: 1989 | F12: NA | G12: 2026-03-12 | H12: cover | I12: One-time outpatient IVF benefit where eligibility is met | J12: IVF-specific, one-time benefit | K12: 1 outpatient IVF benefit | L12: one-time benefit | M12: not specified | N12: not specified | O12: not identified | P12: no; source says own eggs and spouse sperm | Q12: not specified | R12: not identified | S12: not identified | T12: not identified | U12: none_identified | V12: 0 | W12: not identified | X12: married_spousal_gametes_required | Y12: 5-year infertility history or specified medical conditions | Z12: must first fail other applicable covered infertility treatments | AA12: not specified in source used | AB12: not specified in source used | AC12: none stated in source used | AD12: restricted_current_statute uses spouse requirement | AE12: excluded_current_statute uses spouse requirement | AF12: not explicitly addressed; current statute uses spouse/sex-specific framing | AG12: patient oocytes must be fertilized with spouse sperm | AH12: not_identified_in_secondary_sources_used | AI12: not_identified_in_secondary_sources_used | AJ12: not_identified_in_secondary_sources_used | AK12: not_identified_in_secondary_sources_used | AL12: not_identified_in_secondary_sources_used | AM12: restricted | AN12: unclear | AO12: no_or_unclear | AP12: unclear | AQ12: adoption or post-birth process often required | AR12: no_fertility_specific_state_clinic_license_coded_in_this_pass | AS12: federal_CDC_NASS_reporting_baseline | AT12: federal_FCSRCA_CDC_public_reporting | AU12: CLIA_CMS_FDA_baseline; state_variation_not_fully_coded | AV12: 1989 | AW12: 2024 | AX12: 0 | AY12: =BU12 -> 65 | AZ12: 3 | BA12: 992 | BB12: 1446146 | BC12: FFM | BD12: democratic_trifecta | BE12: supportive_or_protective | BF12: HI Rev Stat § 431:10A-116.5 | BG12: https://law.justia.com/codes/hawaii/title-24/chapter-431/section-431-10a-116-5/ | BH12: https://triagecancer.org/state-laws/health-insurance-fertility-services; https://surrogacy360.org/wp-content/uploads/2024/08/Regulation-Details-in-the-US-by-State_8.6.24.pdf; https://www.reproductivefacts.org/patient-advocacy/state-and-territory-infertility-insurance-laws/hawaii/; https://law.justia.com/codes/hawaii/title-24/chapter-431/section-431-10a-116-5/; https://www.asrm.org/advocacy-and-policy/reproductive-rights/summary-reports/state-abortion-laws-potential-implications-for-reproductive-medicine/; https://www.guttmacher.org/2025/12/state-policy-trends-2025-full-year-analysis; https://www.cdc.gov/art/php/nass/index.html; https://www.cdc.gov/art/success-rates/index.html; https://www.cms.gov/medicare/quality/clinical-laboratory-improvement-amendments; https://www.cms.gov/marketplace/in-person-assisters/training-webinars/training/marketplaces-map; https://ballotpedia.org/State_government_trifectas; https://www.britannica.com/topic/largest-U-S-state-by-population; https://www.guttmacher.org/united-states/abortion | BI12: Source also notes 5 years infertility or certain medical conditions as eligibility routes. Surrogacy fields coded from Surrogacy360 2024 state-by-state summary; interpret as starter classification requiring legal review for publication. Eligibility/LGBTQ fields updated in this pass using current 2026 state-law summaries and/or statute text where available; some entries remain conservative where the source did not clearly resolve LGBTQ or gender-identity treatment eligibility. Embryo/personhood/disposition fields were filled conservatively in this pass. Unless a state had a clear embryo-specific rule in the secondary sources used, values were set to not_identified_in_secondary_sources_used rather than treated as definitive absence of law. Clinic/reporting fields in this pass were coded from federal baselines: CDC NASS/FCSRCA reporting and CMS CLIA materials; insurance marketplace type from CMS Plan Year 2026 marketplace map; political control from Ballotpedia current trifecta status; population uses 2024 state estimate table summarized by Britannica from U.S. Census data. IVF clinic counts and cycle counts remain blank pending direct state-level CDC extraction. | BJ12: RRM | BK12: partially_filled_needs_primary_law_review | BL12: =IFERROR((AZ12/BB12)*1000000,0) -> 2.0744793 | BM12: =IFERROR((BA12/BB12)*1000000,0) -> 685.96117 | BN12: =IFERROR(VLOOKUP(H12,index_logic!$A$4:$B$8,2,FALSE),0) -> 30 | BO12: =IFERROR(VLOOKUP(AD12,index_logic!$D$4:$E$21,2,FALSE),0) -> 0 | BP12: =IFERROR(VLOOKUP(AM12,index_logic!$G$4:$H$6,2,FALSE),0) -> 3 | BQ12: =IFERROR(VLOOKUP(AH12,index_logic!$J$4:$K$6,2,FALSE),0) -> 15 | BR12: =IFERROR(VLOOKUP(BE12,index_logic!$M$4:$N$7,2,FALSE),0) -> 10 | BS12: =IFERROR(VLOOKUP(BL12,index_logic!$P$4:$Q$9,2,TRUE),0) -> 5 | BT12: =IFERROR(VLOOKUP(BM12,index_logic!$S$4:$T$9,2,TRUE),0) -> 2 | BU12: =BN12+BO12+BP12+BQ12+BR12+BS12+BT12 -> 65 | BV12: =IF(BU12>=80,"Very High",IF(BU12>=65,"High",IF(BU12>=50,"Moderate",IF(BU12>=35,"Low","Very Low")))) -> High
A13: Idaho | B13: ID | C13: 2026 | D13: current_snapshot | E13: 0 | F13: NA | G13: 2026-03-12 | H13: none_identified | I13: No statewide infertility/IVF coverage mandate identified in source used | J13: no_statewide_ivf_mandate_identified | K13: 0 | L13: 0 | M13: 0 | N13: 0 | O13: not identified | P13: 0 | Q13: 0 | R13: 0 | U13: none_identified | V13: 0 | X13: no_statewide_ivf_treatment_eligibility_rule_identified | Y13: no_statewide_ivf_treatment_eligibility_rule_identified | Z13: no_statewide_ivf_treatment_eligibility_rule_identified | AA13: not_applicable_no_statewide_ivf_treatment_mandate | AB13: not_applicable_no_statewide_ivf_treatment_mandate | AC13: none stated in source used | AD13: no_statewide_ivf_treatment_eligibility_rule_identified | AE13: no_statewide_ivf_treatment_eligibility_rule_identified | AF13: no_statewide_ivf_treatment_eligibility_rule_identified | AG13: no_statewide_ivf_treatment_eligibility_rule_identified | AH13: not_identified_in_secondary_sources_used | AI13: not_identified_in_secondary_sources_used | AJ13: not_identified_in_secondary_sources_used | AK13: not_identified_in_secondary_sources_used | AL13: not_identified_in_secondary_sources_used | AM13: legal_with_restrictions | AN13: unclear | AO13: yes | AP13: unclear | AQ13: court-recognized parentage available | AR13: no_fertility_specific_state_clinic_license_coded_in_this_pass | AS13: federal_CDC_NASS_reporting_baseline | AT13: federal_FCSRCA_CDC_public_reporting | AU13: CLIA_CMS_FDA_baseline; state_variation_not_fully_coded | AV13: 0 | AW13: 0 | AX13: 0 | AY13: =BU13 -> 31 | AZ13: 2 | BA13: 1067 | BB13: 2001619 | BC13: SBM | BD13: republican_trifecta | BE13: near_total_ban_or_total_ban_environment | BF13: No statewide infertility/IVF mandate identified in Triage Cancer state-law chart | BG13: https://triagecancer.org/state-laws/health-insurance-fertility-services | BH13: https://triagecancer.org/state-laws/health-insurance-fertility-services; https://surrogacy360.org/wp-content/uploads/2024/08/Regulation-Details-in-the-US-by-State_8.6.24.pdf; https://www.asrm.org/advocacy-and-policy/reproductive-rights/summary-reports/state-abortion-laws-potential-implications-for-reproductive-medicine/; https://www.guttmacher.org/2025/12/state-policy-trends-2025-full-year-analysis; https://www.cdc.gov/art/php/nass/index.html; https://www.cdc.gov/art/success-rates/index.html; https://www.cms.gov/medicare/quality/clinical-laboratory-improvement-amendments; https://www.cms.gov/marketplace/in-person-assisters/training-webinars/training/marketplaces-map; https://ballotpedia.org/State_government_trifectas; https://www.britannica.com/topic/largest-U-S-state-by-population; https://www.guttmacher.org/united-states/abortion | BI13: Starter row only. Needs primary-law verification for Medicaid, public funding, eligibility, embryo rules, surrogacy, clinic regulation, and utilization variables. Surrogacy fields coded from Surrogacy360 2024 state-by-state summary; interpret as starter classification requiring legal review for publication. Eligibility/LGBTQ fields on this row were filled as a 2026 starter classification based on absence of a statewide IVF-treatment mandate or unclear scope in the source used; this should not be interpreted as a full review of all private plans or clinic access in the state. Embryo/personhood/disposition fields were filled conservatively in this pass. Unless a state had a clear embryo-specific rule in the secondary sources used, values were set to not_identified_in_secondary_sources_used rather than treated as definitive absence of law. Clinic/reporting fields in this pass were coded from federal baselines: CDC NASS/FCSRCA reporting and CMS CLIA materials; insurance marketplace type from CMS Plan Year 2026 marketplace map; political control from Ballotpedia current trifecta status; population uses 2024 state estimate table summarized by Britannica from U.S. Census data. IVF clinic counts and cycle counts remain blank pending direct state-level CDC extraction. | BJ13: RRM | BK13: partially_filled_needs_primary_law_review | BL13: =IFERROR((AZ13/BB13)*1000000,0) -> 0.99919115 | BM13: =IFERROR((BA13/BB13)*1000000,0) -> 533.06848 | BN13: =IFERROR(VLOOKUP(H13,index_logic!$A$4:$B$8,2,FALSE),0) -> 0 | BO13: =IFERROR(VLOOKUP(AD13,index_logic!$D$4:$E$21,2,FALSE),0) -> 3 | BP13: =IFERROR(VLOOKUP(AM13,index_logic!$G$4:$H$6,2,FALSE),0) -> 7 | BQ13: =IFERROR(VLOOKUP(AH13,index_logic!$J$4:$K$6,2,FALSE),0) -> 15 | BR13: =IFERROR(VLOOKUP(BE13,index_logic!$M$4:$N$7,2,FALSE),0) -> 0 | BS13: =IFERROR(VLOOKUP(BL13,index_logic!$P$4:$Q$9,2,TRUE),0) -> 4 | BT13: =IFERROR(VLOOKUP(BM13,index_logic!$S$4:$T$9,2,TRUE),0) -> 2 | BU13: =BN13+BO13+BP13+BQ13+BR13+BS13+BT13 -> 31 | BV13: =IF(BU13>=80,"Very High",IF(BU13>=65,"High",IF(BU13>=50,"Moderate",IF(BU13>=35,"Low","Very Low")))) -> Very Low
A14: Illinois | B14: IL | C14: 2026 | D14: active | E14: 2026 | F14: NA | G14: 2026-03-12 | H14: cover | I14: Infertility diagnosis and treatment including IVF for group policies with >25 employees | J14: Infertility + IVF | K14: 4 oocyte retrievals, with additional retrievals after live birth | L14: 4 retrievals before live birth reset | M14: not specified | N14: yes | O14: yes | P14: not specified | Q14: not specified | R14: yes (faith-based employers) | S14: not identified | T14: fertility_preservation_only under HB 2617 | U14: none_identified | V14: 0 | W14: not identified | X14: none stated in source used | Y14: not fully parsed from statute in source used; treatment law uses infertility diagnosis and treatment in ASRM/SART clinics | Z14: less costly treatments must fail before IVF | AA14: not specified in source used | AB14: not specified in source used | AC14: none stated in source used | AD14: not fully specified in source used | AE14: not fully specified in source used | AF14: not fully specified in source used | AG14: none stated in source used | AH14: not_identified_in_secondary_sources_used | AI14: not_identified_in_secondary_sources_used | AJ14: not_identified_in_secondary_sources_used | AK14: not_identified_in_secondary_sources_used | AL14: not_identified_in_secondary_sources_used | AM14: legal_with_restrictions | AN14: yes | AO14: yes | AP14: yes_or_unspecified_genetic | AQ14: court-recognized parentage available | AR14: no_fertility_specific_state_clinic_license_coded_in_this_pass | AS14: federal_CDC_NASS_reporting_baseline | AT14: federal_FCSRCA_CDC_public_reporting | AU14: CLIA_CMS_FDA_baseline; state_variation_not_fully_coded | AV14: 2022 | AW14: 2026 | AX14: 0 | AY14: =BU14 -> 80 | AZ14: 15 | BA14: 15552 | BB14: 12710158 | BC14: SBM | BD14: democratic_trifecta | BE14: supportive_or_protective | BF14: 215 ILCS 5/356m; HB 2617 (2017) for fertility preservation | BG14: https://www.ilga.gov/Documents/legislation/ilcs/documents/021500050K356m.htm | BH14: https://triagecancer.org/state-laws/health-insurance-fertility-services; https://surrogacy360.org/wp-content/uploads/2024/08/Regulation-Details-in-the-US-by-State_8.6.24.pdf; https://www.asrm.org/advocacy-and-policy/reproductive-rights/summary-reports/state-abortion-laws-potential-implications-for-reproductive-medicine/; https://www.guttmacher.org/2025/12/state-policy-trends-2025-full-year-analysis; https://www.cdc.gov/art/php/nass/index.html; https://www.cdc.gov/art/success-rates/index.html; https://www.cms.gov/medicare/quality/clinical-laboratory-improvement-amendments; https://www.cms.gov/marketplace/in-person-assisters/training-webinars/training/marketplaces-map; https://ballotpedia.org/State_government_trifectas; https://www.britannica.com/topic/largest-U-S-state-by-population; https://www.guttmacher.org/united-states/abortion | BI14: Source says less costly treatments must fail before IVF; fertility preservation law separately bars discrimination on sexual orientation, marital status, and gender identity. Surrogacy fields coded from Surrogacy360 2024 state-by-state summary; interpret as starter classification requiring legal review for publication. Eligibility/LGBTQ fields updated in this pass using current 2026 state-law summaries and/or statute text where available; some entries remain conservative where the source did not clearly resolve LGBTQ or gender-identity treatment eligibility. Embryo/personhood/disposition fields were filled conservatively in this pass. Unless a state had a clear embryo-specific rule in the secondary sources used, values were set to not_identified_in_secondary_sources_used rather than treated as definitive absence of law. Clinic/reporting fields in this pass were coded from federal baselines: CDC NASS/FCSRCA reporting and CMS CLIA materials; insurance marketplace type from CMS Plan Year 2026 marketplace map; political control from Ballotpedia current trifecta status; population uses 2024 state estimate table summarized by Britannica from U.S. Census data. IVF clinic counts and cycle counts remain blank pending direct state-level CDC extraction. | BJ14: RRM | BK14: partially_filled_needs_primary_law_review | BL14: =IFERROR((AZ14/BB14)*1000000,0) -> 1.1801584 | BM14: =IFERROR((BA14/BB14)*1000000,0) -> 1223.5883 | BN14: =IFERROR(VLOOKUP(H14,index_logic!$A$4:$B$8,2,FALSE),0) -> 30 | BO14: =IFERROR(VLOOKUP(AD14,index_logic!$D$4:$E$21,2,FALSE),0) -> 8 | BP14: =IFERROR(VLOOKUP(AM14,index_logic!$G$4:$H$6,2,FALSE),0) -> 7 | BQ14: =IFERROR(VLOOKUP(AH14,index_logic!$J$4:$K$6,2,FALSE),0) -> 15 | BR14: =IFERROR(VLOOKUP(BE14,index_logic!$M$4:$N$7,2,FALSE),0) -> 10 | BS14: =IFERROR(VLOOKUP(BL14,index_logic!$P$4:$Q$9,2,TRUE),0) -> 4 | BT14: =IFERROR(VLOOKUP(BM14,index_logic!$S$4:$T$9,2,TRUE),0) -> 6 | BU14: =BN14+BO14+BP14+BQ14+BR14+BS14+BT14 -> 80 | BV14: =IF(BU14>=80,"Very High",IF(BU14>=65,"High",IF(BU14>=50,"Moderate",IF(BU14>=35,"Low","Very Low")))) -> Very High
A15: Indiana | B15: IN | C15: 2026 | D15: current_snapshot | E15: 0 | F15: NA | G15: 2026-03-12 | H15: none_identified | I15: No statewide infertility/IVF coverage mandate identified in source used | J15: no_statewide_ivf_mandate_identified | K15: 0 | L15: 0 | M15: 0 | N15: 0 | O15: not identified | P15: 0 | Q15: 0 | R15: 0 | U15: none_identified | V15: 0 | X15: no_statewide_ivf_treatment_eligibility_rule_identified | Y15: no_statewide_ivf_treatment_eligibility_rule_identified | Z15: no_statewide_ivf_treatment_eligibility_rule_identified | AA15: not_applicable_no_statewide_ivf_treatment_mandate | AB15: not_applicable_no_statewide_ivf_treatment_mandate | AC15: none stated in source used | AD15: no_statewide_ivf_treatment_eligibility_rule_identified | AE15: no_statewide_ivf_treatment_eligibility_rule_identified | AF15: no_statewide_ivf_treatment_eligibility_rule_identified | AG15: no_statewide_ivf_treatment_eligibility_rule_identified | AH15: not_identified_in_secondary_sources_used | AI15: not_identified_in_secondary_sources_used | AJ15: not_identified_in_secondary_sources_used | AK15: not_identified_in_secondary_sources_used | AL15: not_identified_in_secondary_sources_used | AM15: restricted | AN15: unclear | AO15: no_or_unclear | AP15: unclear | AQ15: adoption or post-birth process often required | AR15: no_fertility_specific_state_clinic_license_coded_in_this_pass | AS15: federal_CDC_NASS_reporting_baseline | AT15: federal_FCSRCA_CDC_public_reporting | AU15: CLIA_CMS_FDA_baseline; state_variation_not_fully_coded | AV15: 0 | AW15: 0 | AX15: 0 | AY15: =BU15 -> 27 | AZ15: 7 | BA15: 4145 | BB15: 6924275 | BC15: FFM | BD15: republican_trifecta | BE15: near_total_ban_or_total_ban_environment | BF15: No statewide infertility/IVF mandate identified in Triage Cancer state-law chart | BG15: https://triagecancer.org/state-laws/health-insurance-fertility-services | BH15: https://triagecancer.org/state-laws/health-insurance-fertility-services; https://surrogacy360.org/wp-content/uploads/2024/08/Regulation-Details-in-the-US-by-State_8.6.24.pdf; https://www.asrm.org/advocacy-and-policy/reproductive-rights/summary-reports/state-abortion-laws-potential-implications-for-reproductive-medicine/; https://www.guttmacher.org/2025/12/state-policy-trends-2025-full-year-analysis; https://www.cdc.gov/art/php/nass/index.html; https://www.cdc.gov/art/success-rates/index.html; https://www.cms.gov/medicare/quality/clinical-laboratory-improvement-amendments; https://www.cms.gov/marketplace/in-person-assisters/training-webinars/training/marketplaces-map; https://ballotpedia.org/State_government_trifectas; https://www.britannica.com/topic/largest-U-S-state-by-population; https://www.guttmacher.org/united-states/abortion | BI15: Starter row only. Needs primary-law verification for Medicaid, public funding, eligibility, embryo rules, surrogacy, clinic regulation, and utilization variables. Surrogacy fields coded from Surrogacy360 2024 state-by-state summary; interpret as starter classification requiring legal review for publication. Eligibility/LGBTQ fields on this row were filled as a 2026 starter classification based on absence of a statewide IVF-treatment mandate or unclear scope in the source used; this should not be interpreted as a full review of all private plans or clinic access in the state. Embryo/personhood/disposition fields were filled conservatively in this pass. Unless a state had a clear embryo-specific rule in the secondary sources used, values were set to not_identified_in_secondary_sources_used rather than treated as definitive absence of law. Clinic/reporting fields in this pass were coded from federal baselines: CDC NASS/FCSRCA reporting and CMS CLIA materials; insurance marketplace type from CMS Plan Year 2026 marketplace map; political control from Ballotpedia current trifecta status; population uses 2024 state estimate table summarized by Britannica from U.S. Census data. IVF clinic counts and cycle counts remain blank pending direct state-level CDC extraction. | BJ15: RRM | BK15: partially_filled_needs_primary_law_review | BL15: =IFERROR((AZ15/BB15)*1000000,0) -> 1.0109362 | BM15: =IFERROR((BA15/BB15)*1000000,0) -> 598.61863 | BN15: =IFERROR(VLOOKUP(H15,index_logic!$A$4:$B$8,2,FALSE),0) -> 0 | BO15: =IFERROR(VLOOKUP(AD15,index_logic!$D$4:$E$21,2,FALSE),0) -> 3 | BP15: =IFERROR(VLOOKUP(AM15,index_logic!$G$4:$H$6,2,FALSE),0) -> 3 | BQ15: =IFERROR(VLOOKUP(AH15,index_logic!$J$4:$K$6,2,FALSE),0) -> 15 | BR15: =IFERROR(VLOOKUP(BE15,index_logic!$M$4:$N$7,2,FALSE),0) -> 0 | BS15: =IFERROR(VLOOKUP(BL15,index_logic!$P$4:$Q$9,2,TRUE),0) -> 4 | BT15: =IFERROR(VLOOKUP(BM15,index_logic!$S$4:$T$9,2,TRUE),0) -> 2 | BU15: =BN15+BO15+BP15+BQ15+BR15+BS15+BT15 -> 27 | BV15: =IF(BU15>=80,"Very High",IF(BU15>=65,"High",IF(BU15>=50,"Moderate",IF(BU15>=35,"Low","Very Low")))) -> Very Low
A16: Iowa | B16: IA | C16: 2026 | D16: current_snapshot | E16: 0 | F16: NA | G16: 2026-03-12 | H16: none_identified | I16: No statewide infertility/IVF coverage mandate identified in source used | J16: no_statewide_ivf_mandate_identified | K16: 0 | L16: 0 | M16: 0 | N16: 0 | O16: not identified | P16: 0 | Q16: 0 | R16: 0 | U16: none_identified | V16: 0 | X16: no_statewide_ivf_treatment_eligibility_rule_identified | Y16: no_statewide_ivf_treatment_eligibility_rule_identified | Z16: no_statewide_ivf_treatment_eligibility_rule_identified | AA16: not_applicable_no_statewide_ivf_treatment_mandate | AB16: not_applicable_no_statewide_ivf_treatment_mandate | AC16: none stated in source used | AD16: no_statewide_ivf_treatment_eligibility_rule_identified | AE16: no_statewide_ivf_treatment_eligibility_rule_identified | AF16: no_statewide_ivf_treatment_eligibility_rule_identified | AG16: no_statewide_ivf_treatment_eligibility_rule_identified | AH16: not_identified_in_secondary_sources_used | AI16: not_identified_in_secondary_sources_used | AJ16: not_identified_in_secondary_sources_used | AK16: not_identified_in_secondary_sources_used | AL16: not_identified_in_secondary_sources_used | AM16: restricted | AN16: yes | AO16: limited | AP16: yes_or_unspecified_genetic | AQ16: limited court recognition; extra conditions apply | AR16: no_fertility_specific_state_clinic_license_coded_in_this_pass | AS16: federal_CDC_NASS_reporting_baseline | AT16: federal_FCSRCA_CDC_public_reporting | AU16: CLIA_CMS_FDA_baseline; state_variation_not_fully_coded | AV16: 0 | AW16: 0 | AX16: 0 | AY16: =BU16 -> 31 | AZ16: 4 | BA16: 2267 | BB16: 3241488 | BC16: FFM | BD16: republican_trifecta | BE16: restrictive | BF16: No statewide infertility/IVF mandate identified in Triage Cancer state-law chart | BG16: https://triagecancer.org/state-laws/health-insurance-fertility-services | BH16: https://triagecancer.org/state-laws/health-insurance-fertility-services; https://surrogacy360.org/wp-content/uploads/2024/08/Regulation-Details-in-the-US-by-State_8.6.24.pdf; https://www.asrm.org/advocacy-and-policy/reproductive-rights/summary-reports/state-abortion-laws-potential-implications-for-reproductive-medicine/; https://www.guttmacher.org/2025/12/state-policy-trends-2025-full-year-analysis; https://www.cdc.gov/art/php/nass/index.html; https://www.cdc.gov/art/success-rates/index.html; https://www.cms.gov/medicare/quality/clinical-laboratory-improvement-amendments; https://www.cms.gov/marketplace/in-person-assisters/training-webinars/training/marketplaces-map; https://ballotpedia.org/State_government_trifectas; https://www.britannica.com/topic/largest-U-S-state-by-population; https://www.guttmacher.org/united-states/abortion | BI16: Starter row only. Needs primary-law verification for Medicaid, public funding, eligibility, embryo rules, surrogacy, clinic regulation, and utilization variables. Surrogacy fields coded from Surrogacy360 2024 state-by-state summary; interpret as starter classification requiring legal review for publication. Eligibility/LGBTQ fields on this row were filled as a 2026 starter classification based on absence of a statewide IVF-treatment mandate or unclear scope in the source used; this should not be interpreted as a full review of all private plans or clinic access in the state. Embryo/personhood/disposition fields were filled conservatively in this pass. Unless a state had a clear embryo-specific rule in the secondary sources used, values were set to not_identified_in_secondary_sources_used rather than treated as definitive absence of law. Clinic/reporting fields in this pass were coded from federal baselines: CDC NASS/FCSRCA reporting and CMS CLIA materials; insurance marketplace type from CMS Plan Year 2026 marketplace map; political control from Ballotpedia current trifecta status; population uses 2024 state estimate table summarized by Britannica from U.S. Census data. IVF clinic counts and cycle counts remain blank pending direct state-level CDC extraction. | BJ16: RRM | BK16: partially_filled_needs_primary_law_review | BL16: =IFERROR((AZ16/BB16)*1000000,0) -> 1.2340012 | BM16: =IFERROR((BA16/BB16)*1000000,0) -> 699.37017 | BN16: =IFERROR(VLOOKUP(H16,index_logic!$A$4:$B$8,2,FALSE),0) -> 0 | BO16: =IFERROR(VLOOKUP(AD16,index_logic!$D$4:$E$21,2,FALSE),0) -> 3 | BP16: =IFERROR(VLOOKUP(AM16,index_logic!$G$4:$H$6,2,FALSE),0) -> 3 | BQ16: =IFERROR(VLOOKUP(AH16,index_logic!$J$4:$K$6,2,FALSE),0) -> 15 | BR16: =IFERROR(VLOOKUP(BE16,index_logic!$M$4:$N$7,2,FALSE),0) -> 3 | BS16: =IFERROR(VLOOKUP(BL16,index_logic!$P$4:$Q$9,2,TRUE),0) -> 5 | BT16: =IFERROR(VLOOKUP(BM16,index_logic!$S$4:$T$9,2,TRUE),0) -> 2 | BU16: =BN16+BO16+BP16+BQ16+BR16+BS16+BT16 -> 31 | BV16: =IF(BU16>=80,"Very High",IF(BU16>=65,"High",IF(BU16>=50,"Moderate",IF(BU16>=35,"Low","Very Low")))) -> Very Low
A17: Kansas | B17: KS | C17: 2026 | D17: current_snapshot | E17: 0 | F17: NA | G17: 2026-03-12 | H17: none_identified | I17: No statewide infertility/IVF coverage mandate identified in source used | J17: no_statewide_ivf_mandate_identified | K17: 0 | L17: 0 | M17: 0 | N17: 0 | O17: not identified | P17: 0 | Q17: 0 | R17: 0 | U17: none_identified | V17: 0 | X17: no_statewide_ivf_treatment_eligibility_rule_identified | Y17: no_statewide_ivf_treatment_eligibility_rule_identified | Z17: no_statewide_ivf_treatment_eligibility_rule_identified | AA17: not_applicable_no_statewide_ivf_treatment_mandate | AB17: not_applicable_no_statewide_ivf_treatment_mandate | AC17: none stated in source used | AD17: no_statewide_ivf_treatment_eligibility_rule_identified | AE17: no_statewide_ivf_treatment_eligibility_rule_identified | AF17: no_statewide_ivf_treatment_eligibility_rule_identified | AG17: no_statewide_ivf_treatment_eligibility_rule_identified | AH17: not_identified_in_secondary_sources_used | AI17: not_identified_in_secondary_sources_used | AJ17: not_identified_in_secondary_sources_used | AK17: not_identified_in_secondary_sources_used | AL17: not_identified_in_secondary_sources_used | AM17: restricted | AN17: unclear | AO17: limited | AP17: no | AQ17: limited court recognition; extra conditions apply | AR17: no_fertility_specific_state_clinic_license_coded_in_this_pass | AS17: federal_CDC_NASS_reporting_baseline | AT17: federal_FCSRCA_CDC_public_reporting | AU17: CLIA_CMS_FDA_baseline; state_variation_not_fully_coded | AV17: 0 | AW17: 0 | AX17: 0 | AY17: =BU17 -> 34 | AZ17: 3 | BA17: 1885 | BB17: 2970606 | BC17: FFM | BD17: divided_government | BE17: mixed | BF17: No statewide infertility/IVF mandate identified in Triage Cancer state-law chart | BG17: https://triagecancer.org/state-laws/health-insurance-fertility-services | BH17: https://triagecancer.org/state-laws/health-insurance-fertility-services; https://surrogacy360.org/wp-content/uploads/2024/08/Regulation-Details-in-the-US-by-State_8.6.24.pdf; https://www.asrm.org/advocacy-and-policy/reproductive-rights/summary-reports/state-abortion-laws-potential-implications-for-reproductive-medicine/; https://www.guttmacher.org/2025/12/state-policy-trends-2025-full-year-analysis; https://www.cdc.gov/art/php/nass/index.html; https://www.cdc.gov/art/success-rates/index.html; https://www.cms.gov/medicare/quality/clinical-laboratory-improvement-amendments; https://www.cms.gov/marketplace/in-person-assisters/training-webinars/training/marketplaces-map; https://ballotpedia.org/State_government_trifectas; https://www.britannica.com/topic/largest-U-S-state-by-population; https://www.guttmacher.org/united-states/abortion | BI17: Starter row only. Needs primary-law verification for Medicaid, public funding, eligibility, embryo rules, surrogacy, clinic regulation, and utilization variables. Surrogacy fields coded from Surrogacy360 2024 state-by-state summary; interpret as starter classification requiring legal review for publication. Eligibility/LGBTQ fields on this row were filled as a 2026 starter classification based on absence of a statewide IVF-treatment mandate or unclear scope in the source used; this should not be interpreted as a full review of all private plans or clinic access in the state. Embryo/personhood/disposition fields were filled conservatively in this pass. Unless a state had a clear embryo-specific rule in the secondary sources used, values were set to not_identified_in_secondary_sources_used rather than treated as definitive absence of law. Clinic/reporting fields in this pass were coded from federal baselines: CDC NASS/FCSRCA reporting and CMS CLIA materials; insurance marketplace type from CMS Plan Year 2026 marketplace map; political control from Ballotpedia current trifecta status; population uses 2024 state estimate table summarized by Britannica from U.S. Census data. IVF clinic counts and cycle counts remain blank pending direct state-level CDC extraction. | BJ17: RRM | BK17: partially_filled_needs_primary_law_review | BL17: =IFERROR((AZ17/BB17)*1000000,0) -> 1.009895 | BM17: =IFERROR((BA17/BB17)*1000000,0) -> 634.55066 | BN17: =IFERROR(VLOOKUP(H17,index_logic!$A$4:$B$8,2,FALSE),0) -> 0 | BO17: =IFERROR(VLOOKUP(AD17,index_logic!$D$4:$E$21,2,FALSE),0) -> 3 | BP17: =IFERROR(VLOOKUP(AM17,index_logic!$G$4:$H$6,2,FALSE),0) -> 3 | BQ17: =IFERROR(VLOOKUP(AH17,index_logic!$J$4:$K$6,2,FALSE),0) -> 15 | BR17: =IFERROR(VLOOKUP(BE17,index_logic!$M$4:$N$7,2,FALSE),0) -> 7 | BS17: =IFERROR(VLOOKUP(BL17,index_logic!$P$4:$Q$9,2,TRUE),0) -> 4 | BT17: =IFERROR(VLOOKUP(BM17,index_logic!$S$4:$T$9,2,TRUE),0) -> 2 | BU17: =BN17+BO17+BP17+BQ17+BR17+BS17+BT17 -> 34 | BV17: =IF(BU17>=80,"Very High",IF(BU17>=65,"High",IF(BU17>=50,"Moderate",IF(BU17>=35,"Low","Very Low")))) -> Very Low
A18: Kentucky | B18: KY | C18: 2026 | D18: active | E18: 0 | F18: NA | G18: 2026-03-12 | H18: none_for_ivf | I18: No statewide infertility/IVF coverage mandate identified in source; fertility preservation law only | J18: fertility_preservation_only | K18: 0 | L18: 0 | M18: 0 | N18: 0 | O18: yes | P18: 0 | Q18: 0 | R18: 0 | S18: not identified | T18: fertility_preservation_only | U18: none_identified | V18: 0 | W18: not identified | X18: no_statewide_ivf_treatment_rule_identified_fertility_preservation_only_law | Y18: no_statewide_ivf_treatment_rule_identified_fertility_preservation_only_law | Z18: no_statewide_ivf_treatment_rule_identified_fertility_preservation_only_law | AA18: not_applicable_no_statewide_ivf_treatment_mandate | AB18: not_applicable_no_statewide_ivf_treatment_mandate | AC18: none stated in source used | AD18: no_statewide_ivf_treatment_rule_identified_fertility_preservation_only_law | AE18: no_statewide_ivf_treatment_rule_identified_fertility_preservation_only_law | AF18: no_statewide_ivf_treatment_rule_identified_fertility_preservation_only_law | AG18: no_statewide_ivf_treatment_rule_identified_fertility_preservation_only_law | AH18: not_identified_in_secondary_sources_used | AI18: not_identified_in_secondary_sources_used | AJ18: not_identified_in_secondary_sources_used | AK18: not_identified_in_secondary_sources_used | AL18: not_identified_in_secondary_sources_used | AM18: restricted | AN18: no_expense_reimbursement_only | AO18: no_or_unclear | AP18: unclear | AQ18: adoption or post-birth process often required | AR18: no_fertility_specific_state_clinic_license_coded_in_this_pass | AS18: federal_CDC_NASS_reporting_baseline | AT18: federal_FCSRCA_CDC_public_reporting | AU18: CLIA_CMS_FDA_baseline; state_variation_not_fully_coded | AV18: 0 | AW18: 0 | AX18: 0 | AY18: =BU18 -> 30 | AZ18: 3 | BA18: 2100 | BB18: 4588372 | BC18: SBM | BD18: divided_government | BE18: near_total_ban_or_total_ban_environment | BF18: HB 170 (2023) | BG18: https://apps.legislature.ky.gov/record/23RS/hb170.html | BH18: https://triagecancer.org/state-laws/health-insurance-fertility-services; https://surrogacy360.org/wp-content/uploads/2024/08/Regulation-Details-in-the-US-by-State_8.6.24.pdf; https://www.asrm.org/advocacy-and-policy/reproductive-rights/summary-reports/state-abortion-laws-potential-implications-for-reproductive-medicine/; https://www.guttmacher.org/2025/12/state-policy-trends-2025-full-year-analysis; https://www.cdc.gov/art/php/nass/index.html; https://www.cdc.gov/art/success-rates/index.html; https://www.cms.gov/medicare/quality/clinical-laboratory-improvement-amendments; https://www.cms.gov/marketplace/in-person-assisters/training-webinars/training/marketplaces-map; https://ballotpedia.org/State_government_trifectas; https://www.britannica.com/topic/largest-U-S-state-by-population; https://www.guttmacher.org/united-states/abortion | BI18: Plans including Medicaid and student health must cover oocyte and sperm preservation for treatment-related infertility. Surrogacy fields coded from Surrogacy360 2024 state-by-state summary; interpret as starter classification requiring legal review for publication. Eligibility/LGBTQ fields on this row were filled as a 2026 starter classification based on absence of a statewide IVF-treatment mandate or unclear scope in the source used; this should not be interpreted as a full review of all private plans or clinic access in the state. Embryo/personhood/disposition fields were filled conservatively in this pass. Unless a state had a clear embryo-specific rule in the secondary sources used, values were set to not_identified_in_secondary_sources_used rather than treated as definitive absence of law. Clinic/reporting fields in this pass were coded from federal baselines: CDC NASS/FCSRCA reporting and CMS CLIA materials; insurance marketplace type from CMS Plan Year 2026 marketplace map; political control from Ballotpedia current trifecta status; population uses 2024 state estimate table summarized by Britannica from U.S. Census data. IVF clinic counts and cycle counts remain blank pending direct state-level CDC extraction. | BJ18: RRM | BK18: partially_filled_needs_primary_law_review | BL18: =IFERROR((AZ18/BB18)*1000000,0) -> 0.65382667 | BM18: =IFERROR((BA18/BB18)*1000000,0) -> 457.67867 | BN18: =IFERROR(VLOOKUP(H18,index_logic!$A$4:$B$8,2,FALSE),0) -> 4 | BO18: =IFERROR(VLOOKUP(AD18,index_logic!$D$4:$E$21,2,FALSE),0) -> 3 | BP18: =IFERROR(VLOOKUP(AM18,index_logic!$G$4:$H$6,2,FALSE),0) -> 3 | BQ18: =IFERROR(VLOOKUP(AH18,index_logic!$J$4:$K$6,2,FALSE),0) -> 15 | BR18: =IFERROR(VLOOKUP(BE18,index_logic!$M$4:$N$7,2,FALSE),0) -> 0 | BS18: =IFERROR(VLOOKUP(BL18,index_logic!$P$4:$Q$9,2,TRUE),0) -> 3 | BT18: =IFERROR(VLOOKUP(BM18,index_logic!$S$4:$T$9,2,TRUE),0) -> 2 | BU18: =BN18+BO18+BP18+BQ18+BR18+BS18+BT18 -> 30 | BV18: =IF(BU18>=80,"Very High",IF(BU18>=65,"High",IF(BU18>=50,"Moderate",IF(BU18>=35,"Low","Very Low")))) -> Very Low
A19: Louisiana | B19: LA | C19: 2026 | D19: active | E19: 0 | F19: NA | G19: 2026-03-12 | H19: none_for_ivf | I19: No statewide infertility/IVF coverage mandate identified in source; fertility preservation law only | J19: fertility_preservation_only | K19: 0 | L19: 0 | M19: 0 | N19: 0 | O19: yes | P19: 0 | Q19: 0 | R19: 0 | S19: not identified | T19: fertility_preservation_only | U19: none_identified | V19: 0 | W19: not identified | X19: no_statewide_ivf_treatment_rule_identified_fertility_preservation_only_law | Y19: no_statewide_ivf_treatment_rule_identified_fertility_preservation_only_law | Z19: no_statewide_ivf_treatment_rule_identified_fertility_preservation_only_law | AA19: not_applicable_no_statewide_ivf_treatment_mandate | AB19: not_applicable_no_statewide_ivf_treatment_mandate | AC19: none stated in source used | AD19: no_statewide_ivf_treatment_rule_identified_fertility_preservation_only_law | AE19: no_statewide_ivf_treatment_rule_identified_fertility_preservation_only_law | AF19: no_statewide_ivf_treatment_rule_identified_fertility_preservation_only_law | AG19: no_statewide_ivf_treatment_rule_identified_fertility_preservation_only_law | AH19: yes_juridical_person | AI19: physician_or_facility_responsible_for_safekeeping | AJ19: intentional destruction of viable embryo prohibited; renunciation transfers by notarial act to new intended parent(s) | AK19: embryos may not be farmed/cultured solely for research; sale prohibited | AL19: state embryo statutes define IVF embryo as juridical person/separate entity, not property | AM19: restricted | AN19: no_expense_reimbursement_only | AO19: limited | AP19: yes | AQ19: limited court recognition; extra conditions apply | AR19: no_fertility_specific_state_clinic_license_coded_in_this_pass | AS19: federal_CDC_NASS_reporting_baseline | AT19: federal_FCSRCA_CDC_public_reporting | AU19: CLIA_CMS_FDA_baseline; state_variation_not_fully_coded | AV19: 0 | AW19: 0 | AX19: 0 | AY19: =BU19 -> 19 | AZ19: 4 | BA19: 2224 | BB19: 4597740 | BC19: FFM | BD19: republican_trifecta | BE19: near_total_ban_or_total_ban_environment | BF19: HB 186 (2023) | BG19: https://www.legis.la.gov/legis/BillInfo.aspx?s=23rs&b=HB186 | BH19: https://triagecancer.org/state-laws/health-insurance-fertility-services; https://surrogacy360.org/wp-content/uploads/2024/08/Regulation-Details-in-the-US-by-State_8.6.24.pdf; https://legis.la.gov/Legis/Law.aspx?d=108440; https://www.asrm.org/advocacy-and-policy/reproductive-rights/summary-reports/state-abortion-laws-potential-implications-for-reproductive-medicine/; https://www.guttmacher.org/2025/12/state-policy-trends-2025-full-year-analysis; https://law.justia.com/codes/louisiana/revised-statutes/title-9/rs-9-122/; https://law.justia.com/codes/louisiana/revised-statutes/title-9/rs-9-123/; https://law.justia.com/codes/louisiana/revised-statutes/title-9/rs-9-126/; https://law.justia.com/codes/louisiana/revised-statutes/title-9/rs-9-129/; https://legis.la.gov/legis/Law.aspx?d=108447; https://www.cdc.gov/art/php/nass/index.html; https://www.cdc.gov/art/success-rates/index.html; https://www.cms.gov/medicare/quality/clinical-laboratory-improvement-amendments; https://www.cms.gov/marketplace/in-person-assisters/training-webinars/training/marketplaces-map; https://ballotpedia.org/State_government_trifectas; https://www.britannica.com/topic/largest-U-S-state-by-population; https://www.guttmacher.org/united-states/abortion | BI19: Plans including Medicaid and student health must cover standard fertility preservation effective 2024-01-01; storage up to 3 years. Surrogacy fields coded from Surrogacy360 2024 state-by-state summary; interpret as starter classification requiring legal review for publication. Eligibility/LGBTQ fields on this row were filled as a 2026 starter classification based on absence of a statewide IVF-treatment mandate or unclear scope in the source used; this should not be interpreted as a full review of all private plans or clinic access in the state. Embryo/personhood/disposition fields were filled conservatively in this pass. Unless a state had a clear embryo-specific rule in the secondary sources used, values were set to not_identified_in_secondary_sources_used rather than treated as definitive absence of law. Clinic/reporting fields in this pass were coded from federal baselines: CDC NASS/FCSRCA reporting and CMS CLIA materials; insurance marketplace type from CMS Plan Year 2026 marketplace map; political control from Ballotpedia current trifecta status; population uses 2024 state estimate table summarized by Britannica from U.S. Census data. IVF clinic counts and cycle counts remain blank pending direct state-level CDC extraction. | BJ19: RRM | BK19: partially_filled_needs_primary_law_review | BL19: =IFERROR((AZ19/BB19)*1000000,0) -> 0.86999265 | BM19: =IFERROR((BA19/BB19)*1000000,0) -> 483.71591 | BN19: =IFERROR(VLOOKUP(H19,index_logic!$A$4:$B$8,2,FALSE),0) -> 4 | BO19: =IFERROR(VLOOKUP(AD19,index_logic!$D$4:$E$21,2,FALSE),0) -> 3 | BP19: =IFERROR(VLOOKUP(AM19,index_logic!$G$4:$H$6,2,FALSE),0) -> 3 | BQ19: =IFERROR(VLOOKUP(AH19,index_logic!$J$4:$K$6,2,FALSE),0) -> 3 | BR19: =IFERROR(VLOOKUP(BE19,index_logic!$M$4:$N$7,2,FALSE),0) -> 0 | BS19: =IFERROR(VLOOKUP(BL19,index_logic!$P$4:$Q$9,2,TRUE),0) -> 4 | BT19: =IFERROR(VLOOKUP(BM19,index_logic!$S$4:$T$9,2,TRUE),0) -> 2 | BU19: =BN19+BO19+BP19+BQ19+BR19+BS19+BT19 -> 19 | BV19: =IF(BU19>=80,"Very High",IF(BU19>=65,"High",IF(BU19>=50,"Moderate",IF(BU19>=35,"Low","Very Low")))) -> Very Low
A20: Maine | B20: ME | C20: 2026 | D20: active | E20: 2023 | F20: NA | G20: 2026-03-12 | H20: cover | I20: Fertility diagnostic care, fertility treatment, and fertility preservation | J20: Comprehensive infertility treatment | K20: not specified | L20: not specified | M20: not specified | N20: yes | O20: yes | P20: yes (procurement of donor gametes included) | Q20: not specified | R20: not identified | S20: not identified | T20: not identified | U20: none_identified | V20: 0 | W20: not identified | X20: none stated | Y20: coverage includes fertility care where individual or couple lacks necessary gametes for conception | Z20: cannot deny coverage solely because enrollee foregoes a treatment deemed likely unsuccessful by provider | AA20: not specified in source used | AB20: not specified in source used | AC20: none stated in source used | AD20: explicitly inclusive per Maine regulator bulletin | AE20: explicitly inclusive per Maine regulator bulletin | AF20: not explicitly addressed in source used | AG20: procurement of donor gametes included | AH20: not_identified_in_secondary_sources_used | AI20: not_identified_in_secondary_sources_used | AJ20: not_identified_in_secondary_sources_used | AK20: not_identified_in_secondary_sources_used | AL20: not_identified_in_secondary_sources_used | AM20: legal | AN20: yes | AO20: yes | AP20: unclear | AQ20: court-recognized parentage available | AR20: no_fertility_specific_state_clinic_license_coded_in_this_pass | AS20: federal_CDC_NASS_reporting_baseline | AT20: federal_FCSRCA_CDC_public_reporting | AU20: CLIA_CMS_FDA_baseline; state_variation_not_fully_coded | AV20: 2021 | AW20: 2023 | AX20: 0 | AY20: =BU20 -> 92 | AZ20: 2 | BA20: 730 | BB20: 1405012 | BC20: SBM | BD20: democratic_trifecta | BE20: supportive_or_protective | BF20: LD 1539 / HP 1144 (2021) | BG20: https://legislature.maine.gov/legis/bills/getPDF.asp?paper=HP1144&item=1&snum=130 | BH20: https://triagecancer.org/state-laws/health-insurance-fertility-services; https://surrogacy360.org/wp-content/uploads/2024/08/Regulation-Details-in-the-US-by-State_8.6.24.pdf; https://www.maine.gov/pfr/insurance/sites/maine.gov.pfr.insurance/files/inline-files/476.pdf; https://www.asrm.org/advocacy-and-policy/reproductive-rights/summary-reports/state-abortion-laws-potential-implications-for-reproductive-medicine/; https://www.guttmacher.org/2025/12/state-policy-trends-2025-full-year-analysis; https://www.cdc.gov/art/php/nass/index.html; https://www.cdc.gov/art/success-rates/index.html; https://www.cms.gov/medicare/quality/clinical-laboratory-improvement-amendments; https://www.cms.gov/marketplace/in-person-assisters/training-webinars/training/marketplaces-map; https://ballotpedia.org/State_government_trifectas; https://www.britannica.com/topic/largest-U-S-state-by-population; https://www.guttmacher.org/united-states/abortion | BI20: Source says coverage may not be denied because an enrollee foregoes a treatment a provider views as unlikely to succeed. Surrogacy fields coded from Surrogacy360 2024 state-by-state summary; interpret as starter classification requiring legal review for publication. Eligibility/LGBTQ fields updated in this pass using current 2026 state-law summaries and/or statute text where available; some entries remain conservative where the source did not clearly resolve LGBTQ or gender-identity treatment eligibility. Embryo/personhood/disposition fields were filled conservatively in this pass. Unless a state had a clear embryo-specific rule in the secondary sources used, values were set to not_identified_in_secondary_sources_used rather than treated as definitive absence of law. Clinic/reporting fields in this pass were coded from federal baselines: CDC NASS/FCSRCA reporting and CMS CLIA materials; insurance marketplace type from CMS Plan Year 2026 marketplace map; political control from Ballotpedia current trifecta status; population uses 2024 state estimate table summarized by Britannica from U.S. Census data. IVF clinic counts and cycle counts remain blank pending direct state-level CDC extraction. | BJ20: RRM | BK20: partially_filled_needs_primary_law_review | BL20: =IFERROR((AZ20/BB20)*1000000,0) -> 1.4234754 | BM20: =IFERROR((BA20/BB20)*1000000,0) -> 519.56852 | BN20: =IFERROR(VLOOKUP(H20,index_logic!$A$4:$B$8,2,FALSE),0) -> 30 | BO20: =IFERROR(VLOOKUP(AD20,index_logic!$D$4:$E$21,2,FALSE),0) -> 20 | BP20: =IFERROR(VLOOKUP(AM20,index_logic!$G$4:$H$6,2,FALSE),0) -> 10 | BQ20: =IFERROR(VLOOKUP(AH20,index_logic!$J$4:$K$6,2,FALSE),0) -> 15 | BR20: =IFERROR(VLOOKUP(BE20,index_logic!$M$4:$N$7,2,FALSE),0) -> 10 | BS20: =IFERROR(VLOOKUP(BL20,index_logic!$P$4:$Q$9,2,TRUE),0) -> 5 | BT20: =IFERROR(VLOOKUP(BM20,index_logic!$S$4:$T$9,2,TRUE),0) -> 2 | BU20: =BN20+BO20+BP20+BQ20+BR20+BS20+BT20 -> 92 | BV20: =IF(BU20>=80,"Very High",IF(BU20>=65,"High",IF(BU20>=50,"Moderate",IF(BU20>=35,"Low","Very Low")))) -> Very High
A21: Maryland | B21: MD | C21: 2026 | D21: active | E21: 1985 | F21: NA | G21: 2026-03-12 | H21: cover | I21: IVF coverage in individual/group policies with pregnancy benefits; separate fertility preservation law | J21: IVF-specific | K21: 3 IVF cycles per live birth | L21: $100,000 lifetime maximum | M21: 100000 | N21: not specified | O21: yes | P21: not specified | Q21: not specified | R21: yes | S21: not required | T21: not identified | U21: none_identified | V21: 0 | W21: not identified | X21: married or unmarried patient pathways specified | Y21: opposite-sex spouse: 1 year intercourse; same-sex spouse: 3 artificial insemination attempts over 1 year; unmarried patient: 3 artificial insemination attempts over 1 year or specified medical conditions | Z21: must first try less costly treatments | AA21: not specified in source used | AB21: not specified in source used | AC21: none stated in source used | AD21: partially inclusive same-sex spouse pathway included | AE21: included through unmarried-patient pathway | AF21: not explicitly addressed; sex-specific statutory framing | AG21: none stated in source used | AH21: not_identified_in_secondary_sources_used | AI21: not_identified_in_secondary_sources_used | AJ21: not_identified_in_secondary_sources_used | AK21: not_identified_in_secondary_sources_used | AL21: not_identified_in_secondary_sources_used | AM21: restricted | AN21: unclear | AO21: no_or_unclear | AP21: unclear | AQ21: adoption or post-birth process often required | AR21: no_fertility_specific_state_clinic_license_coded_in_this_pass | AS21: federal_CDC_NASS_reporting_baseline | AT21: federal_FCSRCA_CDC_public_reporting | AU21: CLIA_CMS_FDA_baseline; state_variation_not_fully_coded | AV21: 1985 | AW21: 2019 | AX21: 0 | AY21: =BU21 -> 79 | AZ21: 9 | BA21: 6153 | BB21: 6263220 | BC21: SBM | BD21: democratic_trifecta | BE21: supportive_or_protective | BF21: MD Insurance Code Ann. § 15-810; SB 271 (2018); HB 908 (2018) | BG21: https://mgaleg.maryland.gov/mgawebsite/Laws/StatuteText?article=gin&section=15-810&enactments=false | BH21: https://triagecancer.org/state-laws/health-insurance-fertility-services; https://surrogacy360.org/wp-content/uploads/2024/08/Regulation-Details-in-the-US-by-State_8.6.24.pdf; https://www.reproductivefacts.org/patient-advocacy/state-and-territory-infertility-insurance-laws/maryland/; https://mgaleg.maryland.gov/mgawebsite/laws/StatuteText?article=gin&section=15-810; https://www.asrm.org/advocacy-and-policy/reproductive-rights/summary-reports/state-abortion-laws-potential-implications-for-reproductive-medicine/; https://www.guttmacher.org/2025/12/state-policy-trends-2025-full-year-analysis; https://www.cdc.gov/art/php/nass/index.html; https://www.cdc.gov/art/success-rates/index.html; https://www.cms.gov/medicare/quality/clinical-laboratory-improvement-amendments; https://www.cms.gov/marketplace/in-person-assisters/training-webinars/training/marketplaces-map; https://ballotpedia.org/State_government_trifectas; https://www.britannica.com/topic/largest-U-S-state-by-population; https://www.guttmacher.org/united-states/abortion | BI21: Source says IVF coverage excludes sperm/oocyte storage and does not apply to small employers under 50 employees or self-insured plans. Surrogacy fields coded from Surrogacy360 2024 state-by-state summary; interpret as starter classification requiring legal review for publication. Eligibility/LGBTQ fields updated in this pass using current 2026 state-law summaries and/or statute text where available; some entries remain conservative where the source did not clearly resolve LGBTQ or gender-identity treatment eligibility. Embryo/personhood/disposition fields were filled conservatively in this pass. Unless a state had a clear embryo-specific rule in the secondary sources used, values were set to not_identified_in_secondary_sources_used rather than treated as definitive absence of law. Clinic/reporting fields in this pass were coded from federal baselines: CDC NASS/FCSRCA reporting and CMS CLIA materials; insurance marketplace type from CMS Plan Year 2026 marketplace map; political control from Ballotpedia current trifecta status; population uses 2024 state estimate table summarized by Britannica from U.S. Census data. IVF clinic counts and cycle counts remain blank pending direct state-level CDC extraction. | BJ21: RRM | BK21: partially_filled_needs_primary_law_review | BL21: =IFERROR((AZ21/BB21)*1000000,0) -> 1.4369605 | BM21: =IFERROR((BA21/BB21)*1000000,0) -> 982.40202 | BN21: =IFERROR(VLOOKUP(H21,index_logic!$A$4:$B$8,2,FALSE),0) -> 30 | BO21: =IFERROR(VLOOKUP(AD21,index_logic!$D$4:$E$21,2,FALSE),0) -> 12 | BP21: =IFERROR(VLOOKUP(AM21,index_logic!$G$4:$H$6,2,FALSE),0) -> 3 | BQ21: =IFERROR(VLOOKUP(AH21,index_logic!$J$4:$K$6,2,FALSE),0) -> 15 | BR21: =IFERROR(VLOOKUP(BE21,index_logic!$M$4:$N$7,2,FALSE),0) -> 10 | BS21: =IFERROR(VLOOKUP(BL21,index_logic!$P$4:$Q$9,2,TRUE),0) -> 5 | BT21: =IFERROR(VLOOKUP(BM21,index_logic!$S$4:$T$9,2,TRUE),0) -> 4 | BU21: =BN21+BO21+BP21+BQ21+BR21+BS21+BT21 -> 79 | BV21: =IF(BU21>=80,"Very High",IF(BU21>=65,"High",IF(BU21>=50,"Moderate",IF(BU21>=35,"Low","Very Low")))) -> High
A22: Massachusetts | B22: MA | C22: 2026 | D22: active | E22: 1987 | F22: NA | G22: 2026-03-12 | H22: cover | I22: Infertility diagnosis and treatment including IVF, AI, gamete procurement, cryopreservation | J22: Comprehensive infertility + IVF | K22: none stated | L22: no lifetime cap noted by source | M22: none stated | N22: not specified | O22: yes | P22: not specified | Q22: not specified | R22: not identified | S22: not identified | T22: not identified | U22: none_identified | V22: 0 | W22: not identified | X22: none stated | Y22: not specified in source used; insurers with pregnancy benefits must cover infertility diagnosis and treatment | Z22: none | AA22: none stated in source used | AB22: none stated in source used | AC22: none stated in source used | AD22: no express exclusion identified in source used | AE22: no express exclusion identified in source used | AF22: not explicitly addressed in source used | AG22: none stated in source used | AH22: not_identified_in_secondary_sources_used | AI22: not_identified_in_secondary_sources_used | AJ22: not_identified_in_secondary_sources_used | AK22: not_identified_in_secondary_sources_used | AL22: not_identified_in_secondary_sources_used | AM22: legal_with_restrictions | AN22: unclear | AO22: yes | AP22: unclear | AQ22: court-recognized parentage available | AR22: no_fertility_specific_state_clinic_license_coded_in_this_pass | AS22: federal_CDC_NASS_reporting_baseline | AT22: federal_FCSRCA_CDC_public_reporting | AU22: CLIA_CMS_FDA_baseline; state_variation_not_fully_coded | AV22: 1987 | AW22: 2024 | AX22: 0 | AY22: =BU22 -> 83 | AZ22: 10 | BA22: 9600 | BB22: 7136171 | BC22: SBM | BD22: democratic_trifecta | BE22: supportive_or_protective | BF22: 211 CMR 37.00; St. 2024, c. 140, § 74 | BG22: https://www.mass.gov/regulations/211-CMR-3700-infertility-benefits | BH22: https://triagecancer.org/state-laws/health-insurance-fertility-services; https://surrogacy360.org/wp-content/uploads/2024/08/Regulation-Details-in-the-US-by-State_8.6.24.pdf; https://www.reproductivefacts.org/patient-advocacy/state-and-territory-infertility-insurance-laws/massachusetts/; https://www.asrm.org/advocacy-and-policy/reproductive-rights/summary-reports/state-abortion-laws-potential-implications-for-reproductive-medicine/; https://www.guttmacher.org/2025/12/state-policy-trends-2025-full-year-analysis; https://www.cdc.gov/art/php/nass/index.html; https://www.cdc.gov/art/success-rates/index.html; https://www.cms.gov/medicare/quality/clinical-laboratory-improvement-amendments; https://www.cms.gov/marketplace/in-person-assisters/training-webinars/training/marketplaces-map; https://ballotpedia.org/State_government_trifectas; https://www.britannica.com/topic/largest-U-S-state-by-population; https://www.guttmacher.org/united-states/abortion | BI22: Source says surrogacy and sterilization reversal are not required benefits; 2024 act added fertility preservation. Surrogacy fields coded from Surrogacy360 2024 state-by-state summary; interpret as starter classification requiring legal review for publication. Eligibility/LGBTQ fields updated in this pass using current 2026 state-law summaries and/or statute text where available; some entries remain conservative where the source did not clearly resolve LGBTQ or gender-identity treatment eligibility. Embryo/personhood/disposition fields were filled conservatively in this pass. Unless a state had a clear embryo-specific rule in the secondary sources used, values were set to not_identified_in_secondary_sources_used rather than treated as definitive absence of law. Clinic/reporting fields in this pass were coded from federal baselines: CDC NASS/FCSRCA reporting and CMS CLIA materials; insurance marketplace type from CMS Plan Year 2026 marketplace map; political control from Ballotpedia current trifecta status; population uses 2024 state estimate table summarized by Britannica from U.S. Census data. IVF clinic counts and cycle counts remain blank pending direct state-level CDC extraction. | BJ22: RRM | BK22: partially_filled_needs_primary_law_review | BL22: =IFERROR((AZ22/BB22)*1000000,0) -> 1.4013117 | BM22: =IFERROR((BA22/BB22)*1000000,0) -> 1345.2592 | BN22: =IFERROR(VLOOKUP(H22,index_logic!$A$4:$B$8,2,FALSE),0) -> 30 | BO22: =IFERROR(VLOOKUP(AD22,index_logic!$D$4:$E$21,2,FALSE),0) -> 10 | BP22: =IFERROR(VLOOKUP(AM22,index_logic!$G$4:$H$6,2,FALSE),0) -> 7 | BQ22: =IFERROR(VLOOKUP(AH22,index_logic!$J$4:$K$6,2,FALSE),0) -> 15 | BR22: =IFERROR(VLOOKUP(BE22,index_logic!$M$4:$N$7,2,FALSE),0) -> 10 | BS22: =IFERROR(VLOOKUP(BL22,index_logic!$P$4:$Q$9,2,TRUE),0) -> 5 | BT22: =IFERROR(VLOOKUP(BM22,index_logic!$S$4:$T$9,2,TRUE),0) -> 6 | BU22: =BN22+BO22+BP22+BQ22+BR22+BS22+BT22 -> 83 | BV22: =IF(BU22>=80,"Very High",IF(BU22>=65,"High",IF(BU22>=50,"Moderate",IF(BU22>=35,"Low","Very Low")))) -> Very High
A23: Michigan | B23: MI | C23: 2026 | D23: current_snapshot | E23: 0 | F23: NA | G23: 2026-03-12 | H23: none_identified | I23: No statewide infertility/IVF coverage mandate identified in source used | J23: no_statewide_ivf_mandate_identified | K23: 0 | L23: 0 | M23: 0 | N23: 0 | O23: not identified | P23: 0 | Q23: 0 | R23: 0 | U23: none_identified | V23: 0 | X23: no_statewide_ivf_treatment_eligibility_rule_identified | Y23: no_statewide_ivf_treatment_eligibility_rule_identified | Z23: no_statewide_ivf_treatment_eligibility_rule_identified | AA23: not_applicable_no_statewide_ivf_treatment_mandate | AB23: not_applicable_no_statewide_ivf_treatment_mandate | AC23: none stated in source used | AD23: no_statewide_ivf_treatment_eligibility_rule_identified | AE23: no_statewide_ivf_treatment_eligibility_rule_identified | AF23: no_statewide_ivf_treatment_eligibility_rule_identified | AG23: no_statewide_ivf_treatment_eligibility_rule_identified | AH23: not_identified_in_secondary_sources_used | AI23: not_identified_in_secondary_sources_used | AJ23: not_identified_in_secondary_sources_used | AK23: not_identified_in_secondary_sources_used | AL23: not_identified_in_secondary_sources_used | AM23: legal | AN23: yes | AO23: yes | AP23: unclear | AQ23: court-recognized parentage available | AR23: no_fertility_specific_state_clinic_license_coded_in_this_pass | AS23: federal_CDC_NASS_reporting_baseline | AT23: federal_FCSRCA_CDC_public_reporting | AU23: CLIA_CMS_FDA_baseline; state_variation_not_fully_coded | AV23: 0 | AW23: 0 | AX23: 0 | AY23: =BU23 -> 44 | AZ23: 10 | BA23: 5660 | BB23: 10140459 | BC23: FFM | BD23: divided_government | BE23: supportive_or_protective | BF23: No statewide infertility/IVF mandate identified in Triage Cancer state-law chart | BG23: https://triagecancer.org/state-laws/health-insurance-fertility-services | BH23: https://triagecancer.org/state-laws/health-insurance-fertility-services; https://surrogacy360.org/wp-content/uploads/2024/08/Regulation-Details-in-the-US-by-State_8.6.24.pdf; https://www.asrm.org/advocacy-and-policy/reproductive-rights/summary-reports/state-abortion-laws-potential-implications-for-reproductive-medicine/; https://www.guttmacher.org/2025/12/state-policy-trends-2025-full-year-analysis; https://www.cdc.gov/art/php/nass/index.html; https://www.cdc.gov/art/success-rates/index.html; https://www.cms.gov/medicare/quality/clinical-laboratory-improvement-amendments; https://www.cms.gov/marketplace/in-person-assisters/training-webinars/training/marketplaces-map; https://ballotpedia.org/State_government_trifectas; https://www.britannica.com/topic/largest-U-S-state-by-population; https://www.guttmacher.org/united-states/abortion | BI23: Starter row only. Needs primary-law verification for Medicaid, public funding, eligibility, embryo rules, surrogacy, clinic regulation, and utilization variables. Surrogacy fields coded from Surrogacy360 2024 state-by-state summary; interpret as starter classification requiring legal review for publication. Eligibility/LGBTQ fields on this row were filled as a 2026 starter classification based on absence of a statewide IVF-treatment mandate or unclear scope in the source used; this should not be interpreted as a full review of all private plans or clinic access in the state. Embryo/personhood/disposition fields were filled conservatively in this pass. Unless a state had a clear embryo-specific rule in the secondary sources used, values were set to not_identified_in_secondary_sources_used rather than treated as definitive absence of law. Clinic/reporting fields in this pass were coded from federal baselines: CDC NASS/FCSRCA reporting and CMS CLIA materials; insurance marketplace type from CMS Plan Year 2026 marketplace map; political control from Ballotpedia current trifecta status; population uses 2024 state estimate table summarized by Britannica from U.S. Census data. IVF clinic counts and cycle counts remain blank pending direct state-level CDC extraction. | BJ23: RRM | BK23: partially_filled_needs_primary_law_review | BL23: =IFERROR((AZ23/BB23)*1000000,0) -> 0.98614865 | BM23: =IFERROR((BA23/BB23)*1000000,0) -> 558.16014 | BN23: =IFERROR(VLOOKUP(H23,index_logic!$A$4:$B$8,2,FALSE),0) -> 0 | BO23: =IFERROR(VLOOKUP(AD23,index_logic!$D$4:$E$21,2,FALSE),0) -> 3 | BP23: =IFERROR(VLOOKUP(AM23,index_logic!$G$4:$H$6,2,FALSE),0) -> 10 | BQ23: =IFERROR(VLOOKUP(AH23,index_logic!$J$4:$K$6,2,FALSE),0) -> 15 | BR23: =IFERROR(VLOOKUP(BE23,index_logic!$M$4:$N$7,2,FALSE),0) -> 10 | BS23: =IFERROR(VLOOKUP(BL23,index_logic!$P$4:$Q$9,2,TRUE),0) -> 4 | BT23: =IFERROR(VLOOKUP(BM23,index_logic!$S$4:$T$9,2,TRUE),0) -> 2 | BU23: =BN23+BO23+BP23+BQ23+BR23+BS23+BT23 -> 44 | BV23: =IF(BU23>=80,"Very High",IF(BU23>=65,"High",IF(BU23>=50,"Moderate",IF(BU23>=35,"Low","Very Low")))) -> Low
A24: Minnesota | B24: MN | C24: 2026 | D24: current_snapshot | E24: 0 | F24: NA | G24: 2026-03-12 | H24: none_identified | I24: No statewide infertility/IVF coverage mandate identified in source used | J24: no_statewide_ivf_mandate_identified | K24: 0 | L24: 0 | M24: 0 | N24: 0 | O24: not identified | P24: 0 | Q24: 0 | R24: 0 | U24: none_identified | V24: 0 | X24: no_statewide_ivf_treatment_eligibility_rule_identified | Y24: no_statewide_ivf_treatment_eligibility_rule_identified | Z24: no_statewide_ivf_treatment_eligibility_rule_identified | AA24: not_applicable_no_statewide_ivf_treatment_mandate | AB24: not_applicable_no_statewide_ivf_treatment_mandate | AC24: none stated in source used | AD24: no_statewide_ivf_treatment_eligibility_rule_identified | AE24: no_statewide_ivf_treatment_eligibility_rule_identified | AF24: no_statewide_ivf_treatment_eligibility_rule_identified | AG24: no_statewide_ivf_treatment_eligibility_rule_identified | AH24: not_identified_in_secondary_sources_used | AI24: not_identified_in_secondary_sources_used | AJ24: not_identified_in_secondary_sources_used | AK24: not_identified_in_secondary_sources_used | AL24: not_identified_in_secondary_sources_used | AM24: restricted | AN24: unclear | AO24: no_or_unclear | AP24: unclear | AQ24: adoption or post-birth process often required | AR24: no_fertility_specific_state_clinic_license_coded_in_this_pass | AS24: federal_CDC_NASS_reporting_baseline | AT24: federal_FCSRCA_CDC_public_reporting | AU24: CLIA_CMS_FDA_baseline; state_variation_not_fully_coded | AV24: 0 | AW24: 0 | AX24: 0 | AY24: =BU24 -> 40 | AZ24: 8 | BA24: 4808 | BB24: 5793151 | BC24: SBM | BD24: divided_government | BE24: supportive_or_protective | BF24: No statewide infertility/IVF mandate identified in Triage Cancer state-law chart | BG24: https://triagecancer.org/state-laws/health-insurance-fertility-services | BH24: https://triagecancer.org/state-laws/health-insurance-fertility-services; https://surrogacy360.org/wp-content/uploads/2024/08/Regulation-Details-in-the-US-by-State_8.6.24.pdf; https://www.asrm.org/advocacy-and-policy/reproductive-rights/summary-reports/state-abortion-laws-potential-implications-for-reproductive-medicine/; https://www.guttmacher.org/2025/12/state-policy-trends-2025-full-year-analysis; https://www.cdc.gov/art/php/nass/index.html; https://www.cdc.gov/art/success-rates/index.html; https://www.cms.gov/medicare/quality/clinical-laboratory-improvement-amendments; https://www.cms.gov/marketplace/in-person-assisters/training-webinars/training/marketplaces-map; https://ballotpedia.org/State_government_trifectas; https://www.britannica.com/topic/largest-U-S-state-by-population; https://www.guttmacher.org/united-states/abortion | BI24: Starter row only. Needs primary-law verification for Medicaid, public funding, eligibility, embryo rules, surrogacy, clinic regulation, and utilization variables. Surrogacy fields coded from Surrogacy360 2024 state-by-state summary; interpret as starter classification requiring legal review for publication. Eligibility/LGBTQ fields on this row were filled as a 2026 starter classification based on absence of a statewide IVF-treatment mandate or unclear scope in the source used; this should not be interpreted as a full review of all private plans or clinic access in the state. Embryo/personhood/disposition fields were filled conservatively in this pass. Unless a state had a clear embryo-specific rule in the secondary sources used, values were set to not_identified_in_secondary_sources_used rather than treated as definitive absence of law. Clinic/reporting fields in this pass were coded from federal baselines: CDC NASS/FCSRCA reporting and CMS CLIA materials; insurance marketplace type from CMS Plan Year 2026 marketplace map; political control from Ballotpedia current trifecta status; population uses 2024 state estimate table summarized by Britannica from U.S. Census data. IVF clinic counts and cycle counts remain blank pending direct state-level CDC extraction. | BJ24: RRM | BK24: partially_filled_needs_primary_law_review | BL24: =IFERROR((AZ24/BB24)*1000000,0) -> 1.380941 | BM24: =IFERROR((BA24/BB24)*1000000,0) -> 829.94557 | BN24: =IFERROR(VLOOKUP(H24,index_logic!$A$4:$B$8,2,FALSE),0) -> 0 | BO24: =IFERROR(VLOOKUP(AD24,index_logic!$D$4:$E$21,2,FALSE),0) -> 3 | BP24: =IFERROR(VLOOKUP(AM24,index_logic!$G$4:$H$6,2,FALSE),0) -> 3 | BQ24: =IFERROR(VLOOKUP(AH24,index_logic!$J$4:$K$6,2,FALSE),0) -> 15 | BR24: =IFERROR(VLOOKUP(BE24,index_logic!$M$4:$N$7,2,FALSE),0) -> 10 | BS24: =IFERROR(VLOOKUP(BL24,index_logic!$P$4:$Q$9,2,TRUE),0) -> 5 | BT24: =IFERROR(VLOOKUP(BM24,index_logic!$S$4:$T$9,2,TRUE),0) -> 4 | BU24: =BN24+BO24+BP24+BQ24+BR24+BS24+BT24 -> 40 | BV24: =IF(BU24>=80,"Very High",IF(BU24>=65,"High",IF(BU24>=50,"Moderate",IF(BU24>=35,"Low","Very Low")))) -> Low
A25: Mississippi | B25: MS | C25: 2026 | D25: current_snapshot | E25: 0 | F25: NA | G25: 2026-03-12 | H25: none_identified | I25: No statewide infertility/IVF coverage mandate identified in source used | J25: no_statewide_ivf_mandate_identified | K25: 0 | L25: 0 | M25: 0 | N25: 0 | O25: not identified | P25: 0 | Q25: 0 | R25: 0 | U25: none_identified | V25: 0 | X25: no_statewide_ivf_treatment_eligibility_rule_identified | Y25: no_statewide_ivf_treatment_eligibility_rule_identified | Z25: no_statewide_ivf_treatment_eligibility_rule_identified | AA25: not_applicable_no_statewide_ivf_treatment_mandate | AB25: not_applicable_no_statewide_ivf_treatment_mandate | AC25: none stated in source used | AD25: no_statewide_ivf_treatment_eligibility_rule_identified | AE25: no_statewide_ivf_treatment_eligibility_rule_identified | AF25: no_statewide_ivf_treatment_eligibility_rule_identified | AG25: no_statewide_ivf_treatment_eligibility_rule_identified | AH25: not_identified_in_secondary_sources_used | AI25: not_identified_in_secondary_sources_used | AJ25: not_identified_in_secondary_sources_used | AK25: not_identified_in_secondary_sources_used | AL25: not_identified_in_secondary_sources_used | AM25: restricted | AN25: unclear | AO25: no_or_unclear | AP25: unclear | AQ25: adoption or post-birth process often required | AR25: no_fertility_specific_state_clinic_license_coded_in_this_pass | AS25: federal_CDC_NASS_reporting_baseline | AT25: federal_FCSRCA_CDC_public_reporting | AU25: CLIA_CMS_FDA_baseline; state_variation_not_fully_coded | AV25: 0 | AW25: 0 | AX25: 0 | AY25: =BU25 -> 26 | AZ25: 2 | BA25: 847 | BB25: 2943045 | BC25: FFM | BD25: republican_trifecta | BE25: near_total_ban_or_total_ban_environment | BF25: No statewide infertility/IVF mandate identified in Triage Cancer state-law chart | BG25: https://triagecancer.org/state-laws/health-insurance-fertility-services | BH25: https://triagecancer.org/state-laws/health-insurance-fertility-services; https://surrogacy360.org/wp-content/uploads/2024/08/Regulation-Details-in-the-US-by-State_8.6.24.pdf; https://www.asrm.org/advocacy-and-policy/reproductive-rights/summary-reports/state-abortion-laws-potential-implications-for-reproductive-medicine/; https://www.guttmacher.org/2025/12/state-policy-trends-2025-full-year-analysis; https://www.cdc.gov/art/php/nass/index.html; https://www.cdc.gov/art/success-rates/index.html; https://www.cms.gov/medicare/quality/clinical-laboratory-improvement-amendments; https://www.cms.gov/marketplace/in-person-assisters/training-webinars/training/marketplaces-map; https://ballotpedia.org/State_government_trifectas; https://www.britannica.com/topic/largest-U-S-state-by-population; https://www.guttmacher.org/united-states/abortion | BI25: Starter row only. Needs primary-law verification for Medicaid, public funding, eligibility, embryo rules, surrogacy, clinic regulation, and utilization variables. Surrogacy fields coded from Surrogacy360 2024 state-by-state summary; interpret as starter classification requiring legal review for publication. Eligibility/LGBTQ fields on this row were filled as a 2026 starter classification based on absence of a statewide IVF-treatment mandate or unclear scope in the source used; this should not be interpreted as a full review of all private plans or clinic access in the state. Embryo/personhood/disposition fields were filled conservatively in this pass. Unless a state had a clear embryo-specific rule in the secondary sources used, values were set to not_identified_in_secondary_sources_used rather than treated as definitive absence of law. Clinic/reporting fields in this pass were coded from federal baselines: CDC NASS/FCSRCA reporting and CMS CLIA materials; insurance marketplace type from CMS Plan Year 2026 marketplace map; political control from Ballotpedia current trifecta status; population uses 2024 state estimate table summarized by Britannica from U.S. Census data. IVF clinic counts and cycle counts remain blank pending direct state-level CDC extraction. | BJ25: RRM | BK25: partially_filled_needs_primary_law_review | BL25: =IFERROR((AZ25/BB25)*1000000,0) -> 0.67956827 | BM25: =IFERROR((BA25/BB25)*1000000,0) -> 287.79716 | BN25: =IFERROR(VLOOKUP(H25,index_logic!$A$4:$B$8,2,FALSE),0) -> 0 | BO25: =IFERROR(VLOOKUP(AD25,index_logic!$D$4:$E$21,2,FALSE),0) -> 3 | BP25: =IFERROR(VLOOKUP(AM25,index_logic!$G$4:$H$6,2,FALSE),0) -> 3 | BQ25: =IFERROR(VLOOKUP(AH25,index_logic!$J$4:$K$6,2,FALSE),0) -> 15 | BR25: =IFERROR(VLOOKUP(BE25,index_logic!$M$4:$N$7,2,FALSE),0) -> 0 | BS25: =IFERROR(VLOOKUP(BL25,index_logic!$P$4:$Q$9,2,TRUE),0) -> 3 | BT25: =IFERROR(VLOOKUP(BM25,index_logic!$S$4:$T$9,2,TRUE),0) -> 2 | BU25: =BN25+BO25+BP25+BQ25+BR25+BS25+BT25 -> 26 | BV25: =IF(BU25>=80,"Very High",IF(BU25>=65,"High",IF(BU25>=50,"Moderate",IF(BU25>=35,"Low","Very Low")))) -> Very Low
A26: Missouri | B26: MO | C26: 2026 | D26: current_snapshot | E26: 0 | F26: NA | G26: 2026-03-12 | H26: none_identified | I26: No statewide infertility/IVF coverage mandate identified in source used | J26: no_statewide_ivf_mandate_identified | K26: 0 | L26: 0 | M26: 0 | N26: 0 | O26: not identified | P26: 0 | Q26: 0 | R26: 0 | U26: none_identified | V26: 0 | X26: no_statewide_ivf_treatment_eligibility_rule_identified | Y26: no_statewide_ivf_treatment_eligibility_rule_identified | Z26: no_statewide_ivf_treatment_eligibility_rule_identified | AA26: not_applicable_no_statewide_ivf_treatment_mandate | AB26: not_applicable_no_statewide_ivf_treatment_mandate | AC26: none stated in source used | AD26: no_statewide_ivf_treatment_eligibility_rule_identified | AE26: no_statewide_ivf_treatment_eligibility_rule_identified | AF26: no_statewide_ivf_treatment_eligibility_rule_identified | AG26: no_statewide_ivf_treatment_eligibility_rule_identified | AH26: not_identified_in_secondary_sources_used | AI26: not_identified_in_secondary_sources_used | AJ26: not_identified_in_secondary_sources_used | AK26: not_identified_in_secondary_sources_used | AL26: not_identified_in_secondary_sources_used | AM26: restricted | AN26: unclear | AO26: no_or_unclear | AP26: unclear | AQ26: adoption or post-birth process often required | AR26: no_fertility_specific_state_clinic_license_coded_in_this_pass | AS26: federal_CDC_NASS_reporting_baseline | AT26: federal_FCSRCA_CDC_public_reporting | AU26: CLIA_CMS_FDA_baseline; state_variation_not_fully_coded | AV26: 0 | AW26: 0 | AX26: 0 | AY26: =BU26 -> 27 | AZ26: 6 | BA26: 4048 | BB26: 6245466 | BC26: FFM | BD26: republican_trifecta | BE26: near_total_ban_or_total_ban_environment | BF26: No statewide infertility/IVF mandate identified in Triage Cancer state-law chart | BG26: https://triagecancer.org/state-laws/health-insurance-fertility-services | BH26: https://triagecancer.org/state-laws/health-insurance-fertility-services; https://surrogacy360.org/wp-content/uploads/2024/08/Regulation-Details-in-the-US-by-State_8.6.24.pdf; https://www.asrm.org/advocacy-and-policy/reproductive-rights/summary-reports/state-abortion-laws-potential-implications-for-reproductive-medicine/; https://www.guttmacher.org/2025/12/state-policy-trends-2025-full-year-analysis; https://www.cdc.gov/art/php/nass/index.html; https://www.cdc.gov/art/success-rates/index.html; https://www.cms.gov/medicare/quality/clinical-laboratory-improvement-amendments; https://www.cms.gov/marketplace/in-person-assisters/training-webinars/training/marketplaces-map; https://ballotpedia.org/State_government_trifectas; https://www.britannica.com/topic/largest-U-S-state-by-population; https://www.guttmacher.org/united-states/abortion | BI26: Starter row only. Needs primary-law verification for Medicaid, public funding, eligibility, embryo rules, surrogacy, clinic regulation, and utilization variables. Surrogacy fields coded from Surrogacy360 2024 state-by-state summary; interpret as starter classification requiring legal review for publication. Eligibility/LGBTQ fields on this row were filled as a 2026 starter classification based on absence of a statewide IVF-treatment mandate or unclear scope in the source used; this should not be interpreted as a full review of all private plans or clinic access in the state. Embryo/personhood/disposition fields were filled conservatively in this pass. Unless a state had a clear embryo-specific rule in the secondary sources used, values were set to not_identified_in_secondary_sources_used rather than treated as definitive absence of law. Clinic/reporting fields in this pass were coded from federal baselines: CDC NASS/FCSRCA reporting and CMS CLIA materials; insurance marketplace type from CMS Plan Year 2026 marketplace map; political control from Ballotpedia current trifecta status; population uses 2024 state estimate table summarized by Britannica from U.S. Census data. IVF clinic counts and cycle counts remain blank pending direct state-level CDC extraction. | BJ26: RRM | BK26: partially_filled_needs_primary_law_review | BL26: =IFERROR((AZ26/BB26)*1000000,0) -> 0.96069693 | BM26: =IFERROR((BA26/BB26)*1000000,0) -> 648.15019 | BN26: =IFERROR(VLOOKUP(H26,index_logic!$A$4:$B$8,2,FALSE),0) -> 0 | BO26: =IFERROR(VLOOKUP(AD26,index_logic!$D$4:$E$21,2,FALSE),0) -> 3 | BP26: =IFERROR(VLOOKUP(AM26,index_logic!$G$4:$H$6,2,FALSE),0) -> 3 | BQ26: =IFERROR(VLOOKUP(AH26,index_logic!$J$4:$K$6,2,FALSE),0) -> 15 | BR26: =IFERROR(VLOOKUP(BE26,index_logic!$M$4:$N$7,2,FALSE),0) -> 0 | BS26: =IFERROR(VLOOKUP(BL26,index_logic!$P$4:$Q$9,2,TRUE),0) -> 4 | BT26: =IFERROR(VLOOKUP(BM26,index_logic!$S$4:$T$9,2,TRUE),0) -> 2 | BU26: =BN26+BO26+BP26+BQ26+BR26+BS26+BT26 -> 27 | BV26: =IF(BU26>=80,"Very High",IF(BU26>=65,"High",IF(BU26>=50,"Moderate",IF(BU26>=35,"Low","Very Low")))) -> Very Low
A27: Montana | B27: MT | C27: 2026 | D27: active | E27: 1987 | F27: NA | G27: 2026-03-12 | H27: limited | I27: HMO basic health care services include infertility services, but scope is undefined | J27: HMO-only / unspecified infertility services | K27: not specified | L27: not specified | M27: not specified | N27: unclear | O27: yes | P27: not specified | Q27: not specified | R27: not identified | S27: not identified | T27: not identified | U27: none_identified | V27: 0 | W27: not identified | X27: not_specified_scope_unclear_in_source_used | Y27: infertility_services_required_but_scope_undefined_in_source_used | Z27: not_specified_in_source_used | AA27: not specified in source used | AB27: not specified in source used | AC27: none stated in source used | AD27: not_specified_scope_unclear_in_source_used | AE27: not_specified_scope_unclear_in_source_used | AF27: not_specified_scope_unclear_in_source_used | AG27: not_specified_scope_unclear_in_source_used | AH27: not_identified_in_secondary_sources_used | AI27: not_identified_in_secondary_sources_used | AJ27: not_identified_in_secondary_sources_used | AK27: not_identified_in_secondary_sources_used | AL27: not_identified_in_secondary_sources_used | AM27: restricted | AN27: unclear | AO27: no_or_unclear | AP27: unclear | AQ27: adoption or post-birth process often required | AR27: no_fertility_specific_state_clinic_license_coded_in_this_pass | AS27: federal_CDC_NASS_reporting_baseline | AT27: federal_FCSRCA_CDC_public_reporting | AU27: CLIA_CMS_FDA_baseline; state_variation_not_fully_coded | AV27: 1987 | AW27: 2023 | AX27: 0 | AY27: =BU27 -> 52 | AZ27: 1 | BA27: 462 | BB27: 1137233 | BC27: FFM | BD27: republican_trifecta | BE27: supportive_or_protective | BF27: Mont. Code Ann. § 33-31-102(2)(v); SB 516 (2023) for fertility preservation | BG27: https://leg.mt.gov/bills/mca/title_0330/chapter_0310/part_0010/section_0020/0330-0310-0010-0020.html | BH27: https://triagecancer.org/state-laws/health-insurance-fertility-services; https://surrogacy360.org/wp-content/uploads/2024/08/Regulation-Details-in-the-US-by-State_8.6.24.pdf; https://www.asrm.org/advocacy-and-policy/reproductive-rights/summary-reports/state-abortion-laws-potential-implications-for-reproductive-medicine/; https://www.guttmacher.org/2025/12/state-policy-trends-2025-full-year-analysis; https://www.cdc.gov/art/php/nass/index.html; https://www.cdc.gov/art/success-rates/index.html; https://www.cms.gov/medicare/quality/clinical-laboratory-improvement-amendments; https://www.cms.gov/marketplace/in-person-assisters/training-webinars/training/marketplaces-map; https://ballotpedia.org/State_government_trifectas; https://www.britannica.com/topic/largest-U-S-state-by-population; https://www.guttmacher.org/united-states/abortion | BI27: Treat as limited because source says extent of IVF coverage under HMO requirement is unclear. Surrogacy fields coded from Surrogacy360 2024 state-by-state summary; interpret as starter classification requiring legal review for publication. Eligibility/LGBTQ fields on this row were filled as a 2026 starter classification based on absence of a statewide IVF-treatment mandate or unclear scope in the source used; this should not be interpreted as a full review of all private plans or clinic access in the state. Eligibility/LGBTQ fields updated in this pass using current 2026 state-law summaries and/or statute text where available; some entries remain conservative where the source did not clearly resolve LGBTQ or gender-identity treatment eligibility. Embryo/personhood/disposition fields were filled conservatively in this pass. Unless a state had a clear embryo-specific rule in the secondary sources used, values were set to not_identified_in_secondary_sources_used rather than treated as definitive absence of law. Clinic/reporting fields in this pass were coded from federal baselines: CDC NASS/FCSRCA reporting and CMS CLIA materials; insurance marketplace type from CMS Plan Year 2026 marketplace map; political control from Ballotpedia current trifecta status; population uses 2024 state estimate table summarized by Britannica from U.S. Census data. IVF clinic counts and cycle counts remain blank pending direct state-level CDC extraction. | BJ27: RRM | BK27: partially_filled_needs_primary_law_review | BL27: =IFERROR((AZ27/BB27)*1000000,0) -> 0.87932728 | BM27: =IFERROR((BA27/BB27)*1000000,0) -> 406.2492 | BN27: =IFERROR(VLOOKUP(H27,index_logic!$A$4:$B$8,2,FALSE),0) -> 12 | BO27: =IFERROR(VLOOKUP(AD27,index_logic!$D$4:$E$21,2,FALSE),0) -> 6 | BP27: =IFERROR(VLOOKUP(AM27,index_logic!$G$4:$H$6,2,FALSE),0) -> 3 | BQ27: =IFERROR(VLOOKUP(AH27,index_logic!$J$4:$K$6,2,FALSE),0) -> 15 | BR27: =IFERROR(VLOOKUP(BE27,index_logic!$M$4:$N$7,2,FALSE),0) -> 10 | BS27: =IFERROR(VLOOKUP(BL27,index_logic!$P$4:$Q$9,2,TRUE),0) -> 4 | BT27: =IFERROR(VLOOKUP(BM27,index_logic!$S$4:$T$9,2,TRUE),0) -> 2 | BU27: =BN27+BO27+BP27+BQ27+BR27+BS27+BT27 -> 52 | BV27: =IF(BU27>=80,"Very High",IF(BU27>=65,"High",IF(BU27>=50,"Moderate",IF(BU27>=35,"Low","Very Low")))) -> Moderate
A28: Nebraska | B28: NE | C28: 2026 | D28: current_snapshot | E28: 0 | F28: NA | G28: 2026-03-12 | H28: none_identified | I28: No statewide infertility/IVF coverage mandate identified in source used | J28: no_statewide_ivf_mandate_identified | K28: 0 | L28: 0 | M28: 0 | N28: 0 | O28: not identified | P28: 0 | Q28: 0 | R28: 0 | U28: none_identified | V28: 0 | X28: no_statewide_ivf_treatment_eligibility_rule_identified | Y28: no_statewide_ivf_treatment_eligibility_rule_identified | Z28: no_statewide_ivf_treatment_eligibility_rule_identified | AA28: not_applicable_no_statewide_ivf_treatment_mandate | AB28: not_applicable_no_statewide_ivf_treatment_mandate | AC28: none stated in source used | AD28: no_statewide_ivf_treatment_eligibility_rule_identified | AE28: no_statewide_ivf_treatment_eligibility_rule_identified | AF28: no_statewide_ivf_treatment_eligibility_rule_identified | AG28: no_statewide_ivf_treatment_eligibility_rule_identified | AH28: not_identified_in_secondary_sources_used | AI28: not_identified_in_secondary_sources_used | AJ28: not_identified_in_secondary_sources_used | AK28: not_identified_in_secondary_sources_used | AL28: not_identified_in_secondary_sources_used | AM28: restricted | AN28: no_expense_reimbursement_only | AO28: no_or_unclear | AP28: unclear | AQ28: adoption or post-birth process often required | AR28: no_fertility_specific_state_clinic_license_coded_in_this_pass | AS28: federal_CDC_NASS_reporting_baseline | AT28: federal_FCSRCA_CDC_public_reporting | AU28: CLIA_CMS_FDA_baseline; state_variation_not_fully_coded | AV28: 0 | AW28: 0 | AX28: 0 | AY28: =BU28 -> 31 | AZ28: 3 | BA28: 1398 | BB28: 2005465 | BC28: FFM | BD28: republican_trifecta | BE28: restrictive | BF28: No statewide infertility/IVF mandate identified in Triage Cancer state-law chart | BG28: https://triagecancer.org/state-laws/health-insurance-fertility-services | BH28: https://triagecancer.org/state-laws/health-insurance-fertility-services; https://surrogacy360.org/wp-content/uploads/2024/08/Regulation-Details-in-the-US-by-State_8.6.24.pdf; https://www.asrm.org/advocacy-and-policy/reproductive-rights/summary-reports/state-abortion-laws-potential-implications-for-reproductive-medicine/; https://www.guttmacher.org/2025/12/state-policy-trends-2025-full-year-analysis; https://www.cdc.gov/art/php/nass/index.html; https://www.cdc.gov/art/success-rates/index.html; https://www.cms.gov/medicare/quality/clinical-laboratory-improvement-amendments; https://www.cms.gov/marketplace/in-person-assisters/training-webinars/training/marketplaces-map; https://ballotpedia.org/State_government_trifectas; https://www.britannica.com/topic/largest-U-S-state-by-population; https://www.guttmacher.org/united-states/abortion | BI28: Starter row only. Needs primary-law verification for Medicaid, public funding, eligibility, embryo rules, surrogacy, clinic regulation, and utilization variables. Surrogacy fields coded from Surrogacy360 2024 state-by-state summary; interpret as starter classification requiring legal review for publication. Eligibility/LGBTQ fields on this row were filled as a 2026 starter classification based on absence of a statewide IVF-treatment mandate or unclear scope in the source used; this should not be interpreted as a full review of all private plans or clinic access in the state. Embryo/personhood/disposition fields were filled conservatively in this pass. Unless a state had a clear embryo-specific rule in the secondary sources used, values were set to not_identified_in_secondary_sources_used rather than treated as definitive absence of law. Clinic/reporting fields in this pass were coded from federal baselines: CDC NASS/FCSRCA reporting and CMS CLIA materials; insurance marketplace type from CMS Plan Year 2026 marketplace map; political control from Ballotpedia current trifecta status; population uses 2024 state estimate table summarized by Britannica from U.S. Census data. IVF clinic counts and cycle counts remain blank pending direct state-level CDC extraction. | BJ28: RRM | BK28: partially_filled_needs_primary_law_review | BL28: =IFERROR((AZ28/BB28)*1000000,0) -> 1.4959124 | BM28: =IFERROR((BA28/BB28)*1000000,0) -> 697.09519 | BN28: =IFERROR(VLOOKUP(H28,index_logic!$A$4:$B$8,2,FALSE),0) -> 0 | BO28: =IFERROR(VLOOKUP(AD28,index_logic!$D$4:$E$21,2,FALSE),0) -> 3 | BP28: =IFERROR(VLOOKUP(AM28,index_logic!$G$4:$H$6,2,FALSE),0) -> 3 | BQ28: =IFERROR(VLOOKUP(AH28,index_logic!$J$4:$K$6,2,FALSE),0) -> 15 | BR28: =IFERROR(VLOOKUP(BE28,index_logic!$M$4:$N$7,2,FALSE),0) -> 3 | BS28: =IFERROR(VLOOKUP(BL28,index_logic!$P$4:$Q$9,2,TRUE),0) -> 5 | BT28: =IFERROR(VLOOKUP(BM28,index_logic!$S$4:$T$9,2,TRUE),0) -> 2 | BU28: =BN28+BO28+BP28+BQ28+BR28+BS28+BT28 -> 31 | BV28: =IF(BU28>=80,"Very High",IF(BU28>=65,"High",IF(BU28>=50,"Moderate",IF(BU28>=35,"Low","Very Low")))) -> Very Low
A29: Nevada | B29: NV | C29: 2026 | D29: active | E29: 0 | F29: NA | G29: 2026-03-12 | H29: none_for_ivf | I29: No statewide infertility/IVF coverage mandate identified in source; fertility preservation law only | J29: fertility_preservation_only | K29: 0 | L29: 0 | M29: 0 | N29: 0 | O29: yes | P29: 0 | Q29: 0 | R29: 0 | S29: not identified | T29: fertility_preservation_only | U29: none_identified | V29: 0 | W29: fertility_preservation_only for state/local employees | X29: no_statewide_ivf_treatment_rule_identified_fertility_preservation_only_law | Y29: no_statewide_ivf_treatment_rule_identified_fertility_preservation_only_law | Z29: no_statewide_ivf_treatment_rule_identified_fertility_preservation_only_law | AA29: not_applicable_no_statewide_ivf_treatment_mandate | AB29: not_applicable_no_statewide_ivf_treatment_mandate | AC29: none stated in source used | AD29: no_statewide_ivf_treatment_rule_identified_fertility_preservation_only_law | AE29: no_statewide_ivf_treatment_rule_identified_fertility_preservation_only_law | AF29: no_statewide_ivf_treatment_rule_identified_fertility_preservation_only_law | AG29: no_statewide_ivf_treatment_rule_identified_fertility_preservation_only_law | AH29: not_identified_in_secondary_sources_used | AI29: not_identified_in_secondary_sources_used | AJ29: not_identified_in_secondary_sources_used | AK29: not_identified_in_secondary_sources_used | AL29: not_identified_in_secondary_sources_used | AM29: legal_with_restrictions | AN29: yes | AO29: yes | AP29: yes_or_unspecified_genetic | AQ29: court-recognized parentage available | AR29: no_fertility_specific_state_clinic_license_coded_in_this_pass | AS29: federal_CDC_NASS_reporting_baseline | AT29: federal_FCSRCA_CDC_public_reporting | AU29: CLIA_CMS_FDA_baseline; state_variation_not_fully_coded | AV29: 0 | AW29: 0 | AX29: 0 | AY29: =BU29 -> 45 | AZ29: 3 | BA29: 2013 | BB29: 3267467 | BC29: SBM | BD29: divided_government | BE29: supportive_or_protective | BF29: AB 428 (2025) | BG29: https://www.leg.state.nv.us/App/NELIS/REL/83rd2025/Bill/12625/Overview | BH29: https://triagecancer.org/state-laws/health-insurance-fertility-services; https://surrogacy360.org/wp-content/uploads/2024/08/Regulation-Details-in-the-US-by-State_8.6.24.pdf; https://www.asrm.org/advocacy-and-policy/reproductive-rights/summary-reports/state-abortion-laws-potential-implications-for-reproductive-medicine/; https://www.guttmacher.org/2025/12/state-policy-trends-2025-full-year-analysis; https://www.cdc.gov/art/php/nass/index.html; https://www.cdc.gov/art/success-rates/index.html; https://www.cms.gov/medicare/quality/clinical-laboratory-improvement-amendments; https://www.cms.gov/marketplace/in-person-assisters/training-webinars/training/marketplaces-map; https://ballotpedia.org/State_government_trifectas; https://www.britannica.com/topic/largest-U-S-state-by-population; https://www.guttmacher.org/united-states/abortion | BI29: Public/private health plans incl Medicaid and state/local employees must cover medically necessary fertility preservation for breast/ovarian cancer effective 2025-07-01. Surrogacy fields coded from Surrogacy360 2024 state-by-state summary; interpret as starter classification requiring legal review for publication. Eligibility/LGBTQ fields on this row were filled as a 2026 starter classification based on absence of a statewide IVF-treatment mandate or unclear scope in the source used; this should not be interpreted as a full review of all private plans or clinic access in the state. Embryo/personhood/disposition fields were filled conservatively in this pass. Unless a state had a clear embryo-specific rule in the secondary sources used, values were set to not_identified_in_secondary_sources_used rather than treated as definitive absence of law. Clinic/reporting fields in this pass were coded from federal baselines: CDC NASS/FCSRCA reporting and CMS CLIA materials; insurance marketplace type from CMS Plan Year 2026 marketplace map; political control from Ballotpedia current trifecta status; population uses 2024 state estimate table summarized by Britannica from U.S. Census data. IVF clinic counts and cycle counts remain blank pending direct state-level CDC extraction. | BJ29: RRM | BK29: partially_filled_needs_primary_law_review | BL29: =IFERROR((AZ29/BB29)*1000000,0) -> 0.9181424 | BM29: =IFERROR((BA29/BB29)*1000000,0) -> 616.07355 | BN29: =IFERROR(VLOOKUP(H29,index_logic!$A$4:$B$8,2,FALSE),0) -> 4 | BO29: =IFERROR(VLOOKUP(AD29,index_logic!$D$4:$E$21,2,FALSE),0) -> 3 | BP29: =IFERROR(VLOOKUP(AM29,index_logic!$G$4:$H$6,2,FALSE),0) -> 7 | BQ29: =IFERROR(VLOOKUP(AH29,index_logic!$J$4:$K$6,2,FALSE),0) -> 15 | BR29: =IFERROR(VLOOKUP(BE29,index_logic!$M$4:$N$7,2,FALSE),0) -> 10 | BS29: =IFERROR(VLOOKUP(BL29,index_logic!$P$4:$Q$9,2,TRUE),0) -> 4 | BT29: =IFERROR(VLOOKUP(BM29,index_logic!$S$4:$T$9,2,TRUE),0) -> 2 | BU29: =BN29+BO29+BP29+BQ29+BR29+BS29+BT29 -> 45 | BV29: =IF(BU29>=80,"Very High",IF(BU29>=65,"High",IF(BU29>=50,"Moderate",IF(BU29>=35,"Low","Very Low")))) -> Low
A30: New Hampshire | B30: NH | C30: 2026 | D30: active | E30: 2020 | F30: NA | G30: 2026-03-12 | H30: cover | I30: Infertility diagnosis, medically necessary fertility treatment, and fertility preservation for group plans | J30: Infertility treatment (group plans) | K30: not specified | L30: not specified | M30: not specified | N30: yes | O30: yes | P30: not specified | Q30: not specified | R30: not identified | S30: not identified | T30: not identified | U30: none_identified | V30: 0 | W30: not identified | X30: none stated | Y30: individual ability to become pregnant/carry to live birth is impaired, or individual's ability to cause pregnancy/live birth in partner is impaired | Z30: no differential waiting periods or arbitrary limits allowed | AA30: no arbitrary age limits allowed | AB30: no arbitrary age limits allowed | AC30: none stated in source used | AD30: inclusive individual-and-partner definition | AE30: likely inclusive individual-centered definition | AF30: not explicitly addressed in source used | AG30: donor eggs, sperm, and embryos included | AH30: not_identified_in_secondary_sources_used | AI30: not_identified_in_secondary_sources_used | AJ30: not_identified_in_secondary_sources_used | AK30: not_identified_in_secondary_sources_used | AL30: not_identified_in_secondary_sources_used | AM30: legal | AN30: yes | AO30: yes | AP30: yes_or_unspecified_genetic | AQ30: court-recognized parentage available | AR30: no_fertility_specific_state_clinic_license_coded_in_this_pass | AS30: federal_CDC_NASS_reporting_baseline | AT30: federal_FCSRCA_CDC_public_reporting | AU30: CLIA_CMS_FDA_baseline; state_variation_not_fully_coded | AV30: 2019 | AW30: 2020 | AX30: 0 | AY30: =BU30 -> 89 | AZ30: 2 | BA30: 1304 | BB30: 1409032 | BC30: FFM | BD30: republican_trifecta | BE30: mixed | BF30: SB 279 (2019) | BG30: https://gc.nh.gov/bill_status/legacy/bs2016/bill_status.aspx?lsr=868&sy=2019&sortoption=&txtsessionyear=2019&txtbillnumber=SB279 | BH30: https://triagecancer.org/state-laws/health-insurance-fertility-services; https://surrogacy360.org/wp-content/uploads/2024/08/Regulation-Details-in-the-US-by-State_8.6.24.pdf; https://www.reproductivefacts.org/patient-advocacy/state-and-territory-infertility-insurance-laws/new-hampshire/; https://www.asrm.org/advocacy-and-policy/reproductive-rights/summary-reports/state-abortion-laws-potential-implications-for-reproductive-medicine/; https://www.guttmacher.org/2025/12/state-policy-trends-2025-full-year-analysis; https://www.cdc.gov/art/php/nass/index.html; https://www.cdc.gov/art/success-rates/index.html; https://www.cms.gov/medicare/quality/clinical-laboratory-improvement-amendments; https://www.cms.gov/marketplace/in-person-assisters/training-webinars/training/marketplaces-map; https://ballotpedia.org/State_government_trifectas; https://www.britannica.com/topic/largest-U-S-state-by-population; https://www.guttmacher.org/united-states/abortion | BI30: Source says no pre-existing-condition exclusions. Surrogacy fields coded from Surrogacy360 2024 state-by-state summary; interpret as starter classification requiring legal review for publication. Eligibility/LGBTQ fields updated in this pass using current 2026 state-law summaries and/or statute text where available; some entries remain conservative where the source did not clearly resolve LGBTQ or gender-identity treatment eligibility. Embryo/personhood/disposition fields were filled conservatively in this pass. Unless a state had a clear embryo-specific rule in the secondary sources used, values were set to not_identified_in_secondary_sources_used rather than treated as definitive absence of law. Clinic/reporting fields in this pass were coded from federal baselines: CDC NASS/FCSRCA reporting and CMS CLIA materials; insurance marketplace type from CMS Plan Year 2026 marketplace map; political control from Ballotpedia current trifecta status; population uses 2024 state estimate table summarized by Britannica from U.S. Census data. IVF clinic counts and cycle counts remain blank pending direct state-level CDC extraction. | BJ30: RRM | BK30: partially_filled_needs_primary_law_review | BL30: =IFERROR((AZ30/BB30)*1000000,0) -> 1.4194142 | BM30: =IFERROR((BA30/BB30)*1000000,0) -> 925.45804 | BN30: =IFERROR(VLOOKUP(H30,index_logic!$A$4:$B$8,2,FALSE),0) -> 30 | BO30: =IFERROR(VLOOKUP(AD30,index_logic!$D$4:$E$21,2,FALSE),0) -> 18 | BP30: =IFERROR(VLOOKUP(AM30,index_logic!$G$4:$H$6,2,FALSE),0) -> 10 | BQ30: =IFERROR(VLOOKUP(AH30,index_logic!$J$4:$K$6,2,FALSE),0) -> 15 | BR30: =IFERROR(VLOOKUP(BE30,index_logic!$M$4:$N$7,2,FALSE),0) -> 7 | BS30: =IFERROR(VLOOKUP(BL30,index_logic!$P$4:$Q$9,2,TRUE),0) -> 5 | BT30: =IFERROR(VLOOKUP(BM30,index_logic!$S$4:$T$9,2,TRUE),0) -> 4 | BU30: =BN30+BO30+BP30+BQ30+BR30+BS30+BT30 -> 89 | BV30: =IF(BU30>=80,"Very High",IF(BU30>=65,"High",IF(BU30>=50,"Moderate",IF(BU30>=35,"Low","Very Low")))) -> Very High
A31: New Jersey | B31: NJ | C31: 2026 | D31: active | E31: 2001 | F31: NA | G31: 2026-03-12 | H31: cover | I31: Medically necessary infertility treatment including IVF and related procedures; separate fertility preservation law | J31: Infertility + IVF | K31: 4 completed egg retrievals per lifetime | L31: 4 retrievals lifetime | M31: not specified | N31: not specified | O31: yes | P31: not specified | Q31: not specified | R31: yes | S31: not required | T31: not required | U31: none_identified | V31: 0 | W31: not identified | X31: none; pathways include female without male partner | Y31: includes female without male partner after failed IUI attempts, involuntary medical sterility, inability to carry pregnancy to live birth, or prior infertility determination | Z31: must first fail less costly covered infertility treatments | AA31: less than 46 years old | AB31: not specified in source used | AC31: none stated in source used | AD31: partially inclusive same-sex/single-female pathways included | AE31: included for female without male partner | AF31: not explicitly addressed; sex-specific statutory framing | AG31: none stated in source used | AH31: not_identified_in_secondary_sources_used | AI31: not_identified_in_secondary_sources_used | AJ31: not_identified_in_secondary_sources_used | AK31: not_identified_in_secondary_sources_used | AL31: not_identified_in_secondary_sources_used | AM31: legal | AN31: yes | AO31: yes | AP31: yes | AQ31: court-recognized parentage available | AR31: no_fertility_specific_state_clinic_license_coded_in_this_pass | AS31: federal_CDC_NASS_reporting_baseline | AT31: federal_FCSRCA_CDC_public_reporting | AU31: CLIA_CMS_FDA_baseline; state_variation_not_fully_coded | AV31: 2001 | AW31: 2020 | AX31: 0 | AY31: =BU31 -> 88 | AZ31: 12 | BA31: 17074 | BB31: 9500851 | BC31: SBM | BD31: democratic_trifecta | BE31: supportive_or_protective | BF31: N.J. P.L. 2001, c. 236; SB 2133 (2018) | BG31: https://pub.njleg.gov/bills/2000/pl01/236_.htm | BH31: https://triagecancer.org/state-laws/health-insurance-fertility-services; https://surrogacy360.org/wp-content/uploads/2024/08/Regulation-Details-in-the-US-by-State_8.6.24.pdf; https://www.reproductivefacts.org/patient-advocacy/state-and-territory-infertility-insurance-laws/new-jersey/; https://www.asrm.org/advocacy-and-policy/reproductive-rights/summary-reports/state-abortion-laws-potential-implications-for-reproductive-medicine/; https://www.guttmacher.org/2025/12/state-policy-trends-2025-full-year-analysis; https://www.cdc.gov/art/php/nass/index.html; https://www.cdc.gov/art/success-rates/index.html; https://www.cms.gov/medicare/quality/clinical-laboratory-improvement-amendments; https://www.cms.gov/marketplace/in-person-assisters/training-webinars/training/marketplaces-map; https://ballotpedia.org/State_government_trifectas; https://www.britannica.com/topic/largest-U-S-state-by-population; https://www.guttmacher.org/united-states/abortion | BI31: Infertility treatment coverage limited to individuals under 45 who meet statutory infertility definition and have attempted less costly treatments. Surrogacy fields coded from Surrogacy360 2024 state-by-state summary; interpret as starter classification requiring legal review for publication. Eligibility/LGBTQ fields updated in this pass using current 2026 state-law summaries and/or statute text where available; some entries remain conservative where the source did not clearly resolve LGBTQ or gender-identity treatment eligibility. Embryo/personhood/disposition fields were filled conservatively in this pass. Unless a state had a clear embryo-specific rule in the secondary sources used, values were set to not_identified_in_secondary_sources_used rather than treated as definitive absence of law. Clinic/reporting fields in this pass were coded from federal baselines: CDC NASS/FCSRCA reporting and CMS CLIA materials; insurance marketplace type from CMS Plan Year 2026 marketplace map; political control from Ballotpedia current trifecta status; population uses 2024 state estimate table summarized by Britannica from U.S. Census data. IVF clinic counts and cycle counts remain blank pending direct state-level CDC extraction. | BJ31: RRM | BK31: partially_filled_needs_primary_law_review | BL31: =IFERROR((AZ31/BB31)*1000000,0) -> 1.2630448 | BM31: =IFERROR((BA31/BB31)*1000000,0) -> 1797.1022 | BN31: =IFERROR(VLOOKUP(H31,index_logic!$A$4:$B$8,2,FALSE),0) -> 30 | BO31: =IFERROR(VLOOKUP(AD31,index_logic!$D$4:$E$21,2,FALSE),0) -> 12 | BP31: =IFERROR(VLOOKUP(AM31,index_logic!$G$4:$H$6,2,FALSE),0) -> 10 | BQ31: =IFERROR(VLOOKUP(AH31,index_logic!$J$4:$K$6,2,FALSE),0) -> 15 | BR31: =IFERROR(VLOOKUP(BE31,index_logic!$M$4:$N$7,2,FALSE),0) -> 10 | BS31: =IFERROR(VLOOKUP(BL31,index_logic!$P$4:$Q$9,2,TRUE),0) -> 5 | BT31: =IFERROR(VLOOKUP(BM31,index_logic!$S$4:$T$9,2,TRUE),0) -> 6 | BU31: =BN31+BO31+BP31+BQ31+BR31+BS31+BT31 -> 88 | BV31: =IF(BU31>=80,"Very High",IF(BU31>=65,"High",IF(BU31>=50,"Moderate",IF(BU31>=35,"Low","Very Low")))) -> Very High
A32: New Mexico | B32: NM | C32: 2026 | D32: current_snapshot | E32: 0 | F32: NA | G32: 2026-03-12 | H32: none_identified | I32: No statewide infertility/IVF coverage mandate identified in source used | J32: no_statewide_ivf_mandate_identified | K32: 0 | L32: 0 | M32: 0 | N32: 0 | O32: not identified | P32: 0 | Q32: 0 | R32: 0 | U32: none_identified | V32: 0 | X32: no_statewide_ivf_treatment_eligibility_rule_identified | Y32: no_statewide_ivf_treatment_eligibility_rule_identified | Z32: no_statewide_ivf_treatment_eligibility_rule_identified | AA32: not_applicable_no_statewide_ivf_treatment_mandate | AB32: not_applicable_no_statewide_ivf_treatment_mandate | AC32: none stated in source used | AD32: no_statewide_ivf_treatment_eligibility_rule_identified | AE32: no_statewide_ivf_treatment_eligibility_rule_identified | AF32: no_statewide_ivf_treatment_eligibility_rule_identified | AG32: no_statewide_ivf_treatment_eligibility_rule_identified | AH32: not_identified_in_secondary_sources_used | AI32: not_identified_in_secondary_sources_used | AJ32: not_identified_in_secondary_sources_used | AK32: not_identified_in_secondary_sources_used | AL32: not_identified_in_secondary_sources_used | AM32: restricted | AN32: unclear | AO32: no_or_unclear | AP32: unclear | AQ32: adoption or post-birth process often required | AR32: no_fertility_specific_state_clinic_license_coded_in_this_pass | AS32: federal_CDC_NASS_reporting_baseline | AT32: federal_FCSRCA_CDC_public_reporting | AU32: CLIA_CMS_FDA_baseline; state_variation_not_fully_coded | AV32: 0 | AW32: 0 | AX32: 0 | AY32: =BU32 -> 37 | AZ32: 2 | BA32: 571 | BB32: 2130256 | BC32: SBM | BD32: democratic_trifecta | BE32: supportive_or_protective | BF32: No statewide infertility/IVF mandate identified in Triage Cancer state-law chart | BG32: https://triagecancer.org/state-laws/health-insurance-fertility-services | BH32: https://triagecancer.org/state-laws/health-insurance-fertility-services; https://surrogacy360.org/wp-content/uploads/2024/08/Regulation-Details-in-the-US-by-State_8.6.24.pdf; https://www.asrm.org/advocacy-and-policy/reproductive-rights/summary-reports/state-abortion-laws-potential-implications-for-reproductive-medicine/; https://www.guttmacher.org/2025/12/state-policy-trends-2025-full-year-analysis; https://www.cdc.gov/art/php/nass/index.html; https://www.cdc.gov/art/success-rates/index.html; https://www.cms.gov/medicare/quality/clinical-laboratory-improvement-amendments; https://www.cms.gov/marketplace/in-person-assisters/training-webinars/training/marketplaces-map; https://ballotpedia.org/State_government_trifectas; https://www.britannica.com/topic/largest-U-S-state-by-population; https://www.guttmacher.org/united-states/abortion | BI32: Starter row only. Needs primary-law verification for Medicaid, public funding, eligibility, embryo rules, surrogacy, clinic regulation, and utilization variables. Surrogacy fields coded from Surrogacy360 2024 state-by-state summary; interpret as starter classification requiring legal review for publication. Eligibility/LGBTQ fields on this row were filled as a 2026 starter classification based on absence of a statewide IVF-treatment mandate or unclear scope in the source used; this should not be interpreted as a full review of all private plans or clinic access in the state. Embryo/personhood/disposition fields were filled conservatively in this pass. Unless a state had a clear embryo-specific rule in the secondary sources used, values were set to not_identified_in_secondary_sources_used rather than treated as definitive absence of law. Clinic/reporting fields in this pass were coded from federal baselines: CDC NASS/FCSRCA reporting and CMS CLIA materials; insurance marketplace type from CMS Plan Year 2026 marketplace map; political control from Ballotpedia current trifecta status; population uses 2024 state estimate table summarized by Britannica from U.S. Census data. IVF clinic counts and cycle counts remain blank pending direct state-level CDC extraction. | BJ32: RRM | BK32: partially_filled_needs_primary_law_review | BL32: =IFERROR((AZ32/BB32)*1000000,0) -> 0.9388543 | BM32: =IFERROR((BA32/BB32)*1000000,0) -> 268.0429 | BN32: =IFERROR(VLOOKUP(H32,index_logic!$A$4:$B$8,2,FALSE),0) -> 0 | BO32: =IFERROR(VLOOKUP(AD32,index_logic!$D$4:$E$21,2,FALSE),0) -> 3 | BP32: =IFERROR(VLOOKUP(AM32,index_logic!$G$4:$H$6,2,FALSE),0) -> 3 | BQ32: =IFERROR(VLOOKUP(AH32,index_logic!$J$4:$K$6,2,FALSE),0) -> 15 | BR32: =IFERROR(VLOOKUP(BE32,index_logic!$M$4:$N$7,2,FALSE),0) -> 10 | BS32: =IFERROR(VLOOKUP(BL32,index_logic!$P$4:$Q$9,2,TRUE),0) -> 4 | BT32: =IFERROR(VLOOKUP(BM32,index_logic!$S$4:$T$9,2,TRUE),0) -> 2 | BU32: =BN32+BO32+BP32+BQ32+BR32+BS32+BT32 -> 37 | BV32: =IF(BU32>=80,"Very High",IF(BU32>=65,"High",IF(BU32>=50,"Moderate",IF(BU32>=35,"Low","Very Low")))) -> Low
A33: New York | B33: NY | C33: 2026 | D33: active | E33: 2020 | F33: NA | G33: 2026-03-12 | H33: cover | I33: Large-group IVF coverage plus fertility preservation | J33: IVF-specific for large groups (>100 employees) | K33: 3 IVF cycles | L33: No age restriction; no lifetime limit on fertility preservation | M33: not specified | N33: yes | O33: yes | P33: not specified | Q33: not specified | R33: not identified | S33: not covered | T33: not covered | U33: none_identified | V33: 0 | W33: not identified | X33: none stated in source used | Y33: 12 months regular unprotected intercourse or therapeutic donor insemination; 6 months if female age 35+ | Z33: not specified in source used | AA33: 35+ gets 6-month infertility timeline; no IVF age cap stated in source used | AB33: not specified in source used | AC33: policy issued or renewed in New York | AD33: partially inclusive donor-insemination pathway | AE33: partially inclusive donor-insemination pathway | AF33: not explicitly addressed in source used | AG33: therapeutic donor insemination recognized in infertility definition | AH33: not_identified_in_secondary_sources_used | AI33: not_identified_in_secondary_sources_used | AJ33: not_identified_in_secondary_sources_used | AK33: not_identified_in_secondary_sources_used | AL33: not_identified_in_secondary_sources_used | AM33: legal | AN33: yes | AO33: yes | AP33: unclear | AQ33: court-recognized parentage available | AR33: no_fertility_specific_state_clinic_license_coded_in_this_pass | AS33: federal_CDC_NASS_reporting_baseline | AT33: federal_FCSRCA_CDC_public_reporting | AU33: CLIA_CMS_FDA_baseline; state_variation_not_fully_coded | AV33: 2019 | AW33: 2020 | AX33: 0 | AY33: =BU33 -> 88 | AZ33: 28 | BA33: 29218 | BB33: 19867248 | BC33: SBM | BD33: democratic_trifecta | BE33: supportive_or_protective | BF33: N.Y. Ins. Law §§ 3221(k)(6)(C) and 4303(s)(3) | BG33: https://www.dfs.ny.gov/apps_and_licensing/health_insurers/ivf_fertility_preservation_law_qa_guidance | BH33: https://triagecancer.org/state-laws/health-insurance-fertility-services; https://surrogacy360.org/wp-content/uploads/2024/08/Regulation-Details-in-the-US-by-State_8.6.24.pdf; https://www.reproductivefacts.org/patient-advocacy/state-and-territory-infertility-insurance-laws/new-york/; https://www.asrm.org/advocacy-and-policy/reproductive-rights/summary-reports/state-abortion-laws-potential-implications-for-reproductive-medicine/; https://www.guttmacher.org/2025/12/state-policy-trends-2025-full-year-analysis; https://www.cdc.gov/art/php/nass/index.html; https://www.cdc.gov/art/success-rates/index.html; https://www.cms.gov/medicare/quality/clinical-laboratory-improvement-amendments; https://www.cms.gov/marketplace/in-person-assisters/training-webinars/training/marketplaces-map; https://ballotpedia.org/State_government_trifectas; https://www.britannica.com/topic/largest-U-S-state-by-population; https://www.guttmacher.org/united-states/abortion | BI33: Source says applies to policies issued or renewed on or after 2020-01-01. Surrogacy fields coded from Surrogacy360 2024 state-by-state summary; interpret as starter classification requiring legal review for publication. Eligibility/LGBTQ fields updated in this pass using current 2026 state-law summaries and/or statute text where available; some entries remain conservative where the source did not clearly resolve LGBTQ or gender-identity treatment eligibility. Embryo/personhood/disposition fields were filled conservatively in this pass. Unless a state had a clear embryo-specific rule in the secondary sources used, values were set to not_identified_in_secondary_sources_used rather than treated as definitive absence of law. Clinic/reporting fields in this pass were coded from federal baselines: CDC NASS/FCSRCA reporting and CMS CLIA materials; insurance marketplace type from CMS Plan Year 2026 marketplace map; political control from Ballotpedia current trifecta status; population uses 2024 state estimate table summarized by Britannica from U.S. Census data. IVF clinic counts and cycle counts remain blank pending direct state-level CDC extraction. | BJ33: RRM | BK33: partially_filled_needs_primary_law_review | BL33: =IFERROR((AZ33/BB33)*1000000,0) -> 1.4093547 | BM33: =IFERROR((BA33/BB33)*1000000,0) -> 1470.6617 | BN33: =IFERROR(VLOOKUP(H33,index_logic!$A$4:$B$8,2,FALSE),0) -> 30 | BO33: =IFERROR(VLOOKUP(AD33,index_logic!$D$4:$E$21,2,FALSE),0) -> 12 | BP33: =IFERROR(VLOOKUP(AM33,index_logic!$G$4:$H$6,2,FALSE),0) -> 10 | BQ33: =IFERROR(VLOOKUP(AH33,index_logic!$J$4:$K$6,2,FALSE),0) -> 15 | BR33: =IFERROR(VLOOKUP(BE33,index_logic!$M$4:$N$7,2,FALSE),0) -> 10 | BS33: =IFERROR(VLOOKUP(BL33,index_logic!$P$4:$Q$9,2,TRUE),0) -> 5 | BT33: =IFERROR(VLOOKUP(BM33,index_logic!$S$4:$T$9,2,TRUE),0) -> 6 | BU33: =BN33+BO33+BP33+BQ33+BR33+BS33+BT33 -> 88 | BV33: =IF(BU33>=80,"Very High",IF(BU33>=65,"High",IF(BU33>=50,"Moderate",IF(BU33>=35,"Low","Very Low")))) -> Very High
A34: North Carolina | B34: NC | C34: 2026 | D34: current_snapshot | E34: 0 | F34: NA | G34: 2026-03-12 | H34: none_identified | I34: No statewide infertility/IVF coverage mandate identified in source used | J34: no_statewide_ivf_mandate_identified | K34: 0 | L34: 0 | M34: 0 | N34: 0 | O34: not identified | P34: 0 | Q34: 0 | R34: 0 | U34: none_identified | V34: 0 | X34: no_statewide_ivf_treatment_eligibility_rule_identified | Y34: no_statewide_ivf_treatment_eligibility_rule_identified | Z34: no_statewide_ivf_treatment_eligibility_rule_identified | AA34: not_applicable_no_statewide_ivf_treatment_mandate | AB34: not_applicable_no_statewide_ivf_treatment_mandate | AC34: none stated in source used | AD34: no_statewide_ivf_treatment_eligibility_rule_identified | AE34: no_statewide_ivf_treatment_eligibility_rule_identified | AF34: no_statewide_ivf_treatment_eligibility_rule_identified | AG34: no_statewide_ivf_treatment_eligibility_rule_identified | AH34: not_identified_in_secondary_sources_used | AI34: not_identified_in_secondary_sources_used | AJ34: not_identified_in_secondary_sources_used | AK34: not_identified_in_secondary_sources_used | AL34: not_identified_in_secondary_sources_used | AM34: restricted | AN34: unclear | AO34: no_or_unclear | AP34: unclear | AQ34: adoption or post-birth process often required | AR34: no_fertility_specific_state_clinic_license_coded_in_this_pass | AS34: federal_CDC_NASS_reporting_baseline | AT34: federal_FCSRCA_CDC_public_reporting | AU34: CLIA_CMS_FDA_baseline; state_variation_not_fully_coded | AV34: 0 | AW34: 0 | AX34: 0 | AY34: =BU34 -> 30 | AZ34: 9 | BA34: 6170 | BB34: 11046024 | BC34: FFM | BD34: divided_government | BE34: restrictive | BF34: No statewide infertility/IVF mandate identified in Triage Cancer state-law chart | BG34: https://triagecancer.org/state-laws/health-insurance-fertility-services | BH34: https://triagecancer.org/state-laws/health-insurance-fertility-services; https://surrogacy360.org/wp-content/uploads/2024/08/Regulation-Details-in-the-US-by-State_8.6.24.pdf; https://www.asrm.org/advocacy-and-policy/reproductive-rights/summary-reports/state-abortion-laws-potential-implications-for-reproductive-medicine/; https://www.guttmacher.org/2025/12/state-policy-trends-2025-full-year-analysis; https://www.cdc.gov/art/php/nass/index.html; https://www.cdc.gov/art/success-rates/index.html; https://www.cms.gov/medicare/quality/clinical-laboratory-improvement-amendments; https://www.cms.gov/marketplace/in-person-assisters/training-webinars/training/marketplaces-map; https://ballotpedia.org/State_government_trifectas; https://www.britannica.com/topic/largest-U-S-state-by-population; https://www.guttmacher.org/united-states/abortion | BI34: Starter row only. Needs primary-law verification for Medicaid, public funding, eligibility, embryo rules, surrogacy, clinic regulation, and utilization variables. Surrogacy fields coded from Surrogacy360 2024 state-by-state summary; interpret as starter classification requiring legal review for publication. Eligibility/LGBTQ fields on this row were filled as a 2026 starter classification based on absence of a statewide IVF-treatment mandate or unclear scope in the source used; this should not be interpreted as a full review of all private plans or clinic access in the state. Embryo/personhood/disposition fields were filled conservatively in this pass. Unless a state had a clear embryo-specific rule in the secondary sources used, values were set to not_identified_in_secondary_sources_used rather than treated as definitive absence of law. Clinic/reporting fields in this pass were coded from federal baselines: CDC NASS/FCSRCA reporting and CMS CLIA materials; insurance marketplace type from CMS Plan Year 2026 marketplace map; political control from Ballotpedia current trifecta status; population uses 2024 state estimate table summarized by Britannica from U.S. Census data. IVF clinic counts and cycle counts remain blank pending direct state-level CDC extraction. | BJ34: RRM | BK34: partially_filled_needs_primary_law_review | BL34: =IFERROR((AZ34/BB34)*1000000,0) -> 0.81477281 | BM34: =IFERROR((BA34/BB34)*1000000,0) -> 558.57203 | BN34: =IFERROR(VLOOKUP(H34,index_logic!$A$4:$B$8,2,FALSE),0) -> 0 | BO34: =IFERROR(VLOOKUP(AD34,index_logic!$D$4:$E$21,2,FALSE),0) -> 3 | BP34: =IFERROR(VLOOKUP(AM34,index_logic!$G$4:$H$6,2,FALSE),0) -> 3 | BQ34: =IFERROR(VLOOKUP(AH34,index_logic!$J$4:$K$6,2,FALSE),0) -> 15 | BR34: =IFERROR(VLOOKUP(BE34,index_logic!$M$4:$N$7,2,FALSE),0) -> 3 | BS34: =IFERROR(VLOOKUP(BL34,index_logic!$P$4:$Q$9,2,TRUE),0) -> 4 | BT34: =IFERROR(VLOOKUP(BM34,index_logic!$S$4:$T$9,2,TRUE),0) -> 2 | BU34: =BN34+BO34+BP34+BQ34+BR34+BS34+BT34 -> 30 | BV34: =IF(BU34>=80,"Very High",IF(BU34>=65,"High",IF(BU34>=50,"Moderate",IF(BU34>=35,"Low","Very Low")))) -> Very Low
A35: North Dakota | B35: ND | C35: 2026 | D35: current_snapshot | E35: 0 | F35: NA | G35: 2026-03-12 | H35: none_identified | I35: No statewide infertility/IVF coverage mandate identified in source used | J35: no_statewide_ivf_mandate_identified | K35: 0 | L35: 0 | M35: 0 | N35: 0 | O35: not identified | P35: 0 | Q35: 0 | R35: 0 | U35: none_identified | V35: 0 | X35: no_statewide_ivf_treatment_eligibility_rule_identified | Y35: no_statewide_ivf_treatment_eligibility_rule_identified | Z35: no_statewide_ivf_treatment_eligibility_rule_identified | AA35: not_applicable_no_statewide_ivf_treatment_mandate | AB35: not_applicable_no_statewide_ivf_treatment_mandate | AC35: none stated in source used | AD35: no_statewide_ivf_treatment_eligibility_rule_identified | AE35: no_statewide_ivf_treatment_eligibility_rule_identified | AF35: no_statewide_ivf_treatment_eligibility_rule_identified | AG35: no_statewide_ivf_treatment_eligibility_rule_identified | AH35: not_identified_in_secondary_sources_used | AI35: not_identified_in_secondary_sources_used | AJ35: not_identified_in_secondary_sources_used | AK35: not_identified_in_secondary_sources_used | AL35: not_identified_in_secondary_sources_used | AM35: restricted | AN35: unclear | AO35: no_or_unclear | AP35: unclear | AQ35: adoption or post-birth process often required | AR35: no_fertility_specific_state_clinic_license_coded_in_this_pass | AS35: federal_CDC_NASS_reporting_baseline | AT35: federal_FCSRCA_CDC_public_reporting | AU35: CLIA_CMS_FDA_baseline; state_variation_not_fully_coded | AV35: 0 | AW35: 0 | AX35: 0 | AY35: =BU35 -> 31 | AZ35: 1 | BA35: 457 | BB35: 796568 | BC35: FFM | BD35: republican_trifecta | BE35: restrictive | BF35: No statewide infertility/IVF mandate identified in Triage Cancer state-law chart | BG35: https://triagecancer.org/state-laws/health-insurance-fertility-services | BH35: https://triagecancer.org/state-laws/health-insurance-fertility-services; https://surrogacy360.org/wp-content/uploads/2024/08/Regulation-Details-in-the-US-by-State_8.6.24.pdf; https://www.asrm.org/advocacy-and-policy/reproductive-rights/summary-reports/state-abortion-laws-potential-implications-for-reproductive-medicine/; https://www.guttmacher.org/2025/12/state-policy-trends-2025-full-year-analysis; https://www.cdc.gov/art/php/nass/index.html; https://www.cdc.gov/art/success-rates/index.html; https://www.cms.gov/medicare/quality/clinical-laboratory-improvement-amendments; https://www.cms.gov/marketplace/in-person-assisters/training-webinars/training/marketplaces-map; https://ballotpedia.org/State_government_trifectas; https://www.britannica.com/topic/largest-U-S-state-by-population; https://www.guttmacher.org/united-states/abortion | BI35: Starter row only. Needs primary-law verification for Medicaid, public funding, eligibility, embryo rules, surrogacy, clinic regulation, and utilization variables. Surrogacy fields coded from Surrogacy360 2024 state-by-state summary; interpret as starter classification requiring legal review for publication. Eligibility/LGBTQ fields on this row were filled as a 2026 starter classification based on absence of a statewide IVF-treatment mandate or unclear scope in the source used; this should not be interpreted as a full review of all private plans or clinic access in the state. Embryo/personhood/disposition fields were filled conservatively in this pass. Unless a state had a clear embryo-specific rule in the secondary sources used, values were set to not_identified_in_secondary_sources_used rather than treated as definitive absence of law. Clinic/reporting fields in this pass were coded from federal baselines: CDC NASS/FCSRCA reporting and CMS CLIA materials; insurance marketplace type from CMS Plan Year 2026 marketplace map; political control from Ballotpedia current trifecta status; population uses 2024 state estimate table summarized by Britannica from U.S. Census data. IVF clinic counts and cycle counts remain blank pending direct state-level CDC extraction. | BJ35: RRM | BK35: partially_filled_needs_primary_law_review | BL35: =IFERROR((AZ35/BB35)*1000000,0) -> 1.2553856 | BM35: =IFERROR((BA35/BB35)*1000000,0) -> 573.71122 | BN35: =IFERROR(VLOOKUP(H35,index_logic!$A$4:$B$8,2,FALSE),0) -> 0 | BO35: =IFERROR(VLOOKUP(AD35,index_logic!$D$4:$E$21,2,FALSE),0) -> 3 | BP35: =IFERROR(VLOOKUP(AM35,index_logic!$G$4:$H$6,2,FALSE),0) -> 3 | BQ35: =IFERROR(VLOOKUP(AH35,index_logic!$J$4:$K$6,2,FALSE),0) -> 15 | BR35: =IFERROR(VLOOKUP(BE35,index_logic!$M$4:$N$7,2,FALSE),0) -> 3 | BS35: =IFERROR(VLOOKUP(BL35,index_logic!$P$4:$Q$9,2,TRUE),0) -> 5 | BT35: =IFERROR(VLOOKUP(BM35,index_logic!$S$4:$T$9,2,TRUE),0) -> 2 | BU35: =BN35+BO35+BP35+BQ35+BR35+BS35+BT35 -> 31 | BV35: =IF(BU35>=80,"Very High",IF(BU35>=65,"High",IF(BU35>=50,"Moderate",IF(BU35>=35,"Low","Very Low")))) -> Very Low
A36: Ohio | B36: OH | C36: 2026 | D36: active | E36: 1997 | F36: NA | G36: 2026-03-12 | H36: limited | I36: Health insuring corporations must offer basic health care services including infertility services such as IVF when medically necessary | J36: HIC/HMO-only infertility services | K36: not specified | L36: not specified | M36: not specified | N36: unclear | O36: not identified | P36: not specified | Q36: not specified | R36: not identified | S36: not identified | T36: not identified | U36: none_identified | V36: 0 | W36: not identified | X36: not_specified_scope_unclear_in_source_used | Y36: infertility_services_required_but_scope_undefined_in_source_used | Z36: not_specified_in_source_used | AA36: not specified in source used | AB36: not specified in source used | AC36: none stated in source used | AD36: not_specified_scope_unclear_in_source_used | AE36: not_specified_scope_unclear_in_source_used | AF36: not_specified_scope_unclear_in_source_used | AG36: not_specified_scope_unclear_in_source_used | AH36: not_identified_in_secondary_sources_used | AI36: not_identified_in_secondary_sources_used | AJ36: not_identified_in_secondary_sources_used | AK36: not_identified_in_secondary_sources_used | AL36: not_identified_in_secondary_sources_used | AM36: legal | AN36: yes | AO36: yes | AP36: yes_or_unspecified_genetic | AQ36: court-recognized parentage available | AR36: no_fertility_specific_state_clinic_license_coded_in_this_pass | AS36: federal_CDC_NASS_reporting_baseline | AT36: federal_FCSRCA_CDC_public_reporting | AU36: CLIA_CMS_FDA_baseline; state_variation_not_fully_coded | AV36: 1997 | AW36: 2026 | AX36: 0 | AY36: =BU36 -> 59 | AZ36: 10 | BA36: 6517 | BB36: 11883304 | BC36: FFM | BD36: republican_trifecta | BE36: supportive_or_protective | BF36: Ohio Rev. Code Ann. § 1751.01(A)(7) | BG36: https://codes.ohio.gov/ohio-revised-code/section-1751.01 | BH36: https://triagecancer.org/state-laws/health-insurance-fertility-services; https://surrogacy360.org/wp-content/uploads/2024/08/Regulation-Details-in-the-US-by-State_8.6.24.pdf; https://www.asrm.org/advocacy-and-policy/reproductive-rights/summary-reports/state-abortion-laws-potential-implications-for-reproductive-medicine/; https://www.guttmacher.org/2025/12/state-policy-trends-2025-full-year-analysis; https://www.cdc.gov/art/php/nass/index.html; https://www.cdc.gov/art/success-rates/index.html; https://www.cms.gov/medicare/quality/clinical-laboratory-improvement-amendments; https://www.cms.gov/marketplace/in-person-assisters/training-webinars/training/marketplaces-map; https://ballotpedia.org/State_government_trifectas; https://www.britannica.com/topic/largest-U-S-state-by-population; https://www.guttmacher.org/united-states/abortion | BI36: Source treats infertility services as part of basic health care services for health insuring corporations; experimental procedures not required. Surrogacy fields coded from Surrogacy360 2024 state-by-state summary; interpret as starter classification requiring legal review for publication. Eligibility/LGBTQ fields on this row were filled as a 2026 starter classification based on absence of a statewide IVF-treatment mandate or unclear scope in the source used; this should not be interpreted as a full review of all private plans or clinic access in the state. Eligibility/LGBTQ fields updated in this pass using current 2026 state-law summaries and/or statute text where available; some entries remain conservative where the source did not clearly resolve LGBTQ or gender-identity treatment eligibility. Embryo/personhood/disposition fields were filled conservatively in this pass. Unless a state had a clear embryo-specific rule in the secondary sources used, values were set to not_identified_in_secondary_sources_used rather than treated as definitive absence of law. Clinic/reporting fields in this pass were coded from federal baselines: CDC NASS/FCSRCA reporting and CMS CLIA materials; insurance marketplace type from CMS Plan Year 2026 marketplace map; political control from Ballotpedia current trifecta status; population uses 2024 state estimate table summarized by Britannica from U.S. Census data. IVF clinic counts and cycle counts remain blank pending direct state-level CDC extraction. | BJ36: RRM | BK36: partially_filled_needs_primary_law_review | BL36: =IFERROR((AZ36/BB36)*1000000,0) -> 0.8415168 | BM36: =IFERROR((BA36/BB36)*1000000,0) -> 548.4165 | BN36: =IFERROR(VLOOKUP(H36,index_logic!$A$4:$B$8,2,FALSE),0) -> 12 | BO36: =IFERROR(VLOOKUP(AD36,index_logic!$D$4:$E$21,2,FALSE),0) -> 6 | BP36: =IFERROR(VLOOKUP(AM36,index_logic!$G$4:$H$6,2,FALSE),0) -> 10 | BQ36: =IFERROR(VLOOKUP(AH36,index_logic!$J$4:$K$6,2,FALSE),0) -> 15 | BR36: =IFERROR(VLOOKUP(BE36,index_logic!$M$4:$N$7,2,FALSE),0) -> 10 | BS36: =IFERROR(VLOOKUP(BL36,index_logic!$P$4:$Q$9,2,TRUE),0) -> 4 | BT36: =IFERROR(VLOOKUP(BM36,index_logic!$S$4:$T$9,2,TRUE),0) -> 2 | BU36: =BN36+BO36+BP36+BQ36+BR36+BS36+BT36 -> 59 | BV36: =IF(BU36>=80,"Very High",IF(BU36>=65,"High",IF(BU36>=50,"Moderate",IF(BU36>=35,"Low","Very Low")))) -> Moderate
A37: Oklahoma | B37: OK | C37: 2026 | D37: active | E37: 0 | F37: NA | G37: 2026-03-12 | H37: none_for_ivf | I37: No statewide infertility/IVF coverage mandate identified in source; fertility preservation law only | J37: fertility_preservation_only | K37: 0 | L37: 0 | M37: 0 | N37: 0 | O37: yes | P37: 0 | Q37: 0 | R37: 0 | U37: none_identified | V37: 0 | X37: no_statewide_ivf_treatment_rule_identified_fertility_preservation_only_law | Y37: no_statewide_ivf_treatment_rule_identified_fertility_preservation_only_law | Z37: no_statewide_ivf_treatment_rule_identified_fertility_preservation_only_law | AA37: not_applicable_no_statewide_ivf_treatment_mandate | AB37: not_applicable_no_statewide_ivf_treatment_mandate | AC37: none stated in source used | AD37: no_statewide_ivf_treatment_rule_identified_fertility_preservation_only_law | AE37: no_statewide_ivf_treatment_rule_identified_fertility_preservation_only_law | AF37: no_statewide_ivf_treatment_rule_identified_fertility_preservation_only_law | AG37: no_statewide_ivf_treatment_rule_identified_fertility_preservation_only_law | AH37: not_identified_in_secondary_sources_used | AI37: not_identified_in_secondary_sources_used | AJ37: not_identified_in_secondary_sources_used | AK37: not_identified_in_secondary_sources_used | AL37: not_identified_in_secondary_sources_used | AM37: restricted | AN37: yes | AO37: limited | AP37: yes_or_unspecified_genetic | AQ37: limited court recognition; extra conditions apply | AR37: no_fertility_specific_state_clinic_license_coded_in_this_pass | AS37: federal_CDC_NASS_reporting_baseline | AT37: federal_FCSRCA_CDC_public_reporting | AU37: CLIA_CMS_FDA_baseline; state_variation_not_fully_coded | AV37: 0 | AW37: 0 | AX37: 0 | AY37: =BU37 -> 30 | AZ37: 3 | BA37: 1183 | BB37: 4095393 | BC37: FFM | BD37: republican_trifecta | BE37: near_total_ban_or_total_ban_environment | BF37: SB 1334 (2024) | BG37: https://www.oklegislature.gov/BillInfo.aspx?Bill=SB1334&Session=2400 | BH37: https://triagecancer.org/state-laws/health-insurance-fertility-services; https://surrogacy360.org/wp-content/uploads/2024/08/Regulation-Details-in-the-US-by-State_8.6.24.pdf; https://www.asrm.org/advocacy-and-policy/reproductive-rights/summary-reports/state-abortion-laws-potential-implications-for-reproductive-medicine/; https://www.guttmacher.org/2025/12/state-policy-trends-2025-full-year-analysis; https://www.cdc.gov/art/php/nass/index.html; https://www.cdc.gov/art/success-rates/index.html; https://www.cms.gov/medicare/quality/clinical-laboratory-improvement-amendments; https://www.cms.gov/marketplace/in-person-assisters/training-webinars/training/marketplaces-map; https://ballotpedia.org/State_government_trifectas; https://www.britannica.com/topic/largest-U-S-state-by-population; https://www.guttmacher.org/united-states/abortion | BI37: Corinne’s Law requires all health plans to cover standard fertility preservation for cancer-related iatrogenic infertility effective 2025-01-01. Surrogacy fields coded from Surrogacy360 2024 state-by-state summary; interpret as starter classification requiring legal review for publication. Eligibility/LGBTQ fields on this row were filled as a 2026 starter classification based on absence of a statewide IVF-treatment mandate or unclear scope in the source used; this should not be interpreted as a full review of all private plans or clinic access in the state. Embryo/personhood/disposition fields were filled conservatively in this pass. Unless a state had a clear embryo-specific rule in the secondary sources used, values were set to not_identified_in_secondary_sources_used rather than treated as definitive absence of law. Clinic/reporting fields in this pass were coded from federal baselines: CDC NASS/FCSRCA reporting and CMS CLIA materials; insurance marketplace type from CMS Plan Year 2026 marketplace map; political control from Ballotpedia current trifecta status; population uses 2024 state estimate table summarized by Britannica from U.S. Census data. IVF clinic counts and cycle counts remain blank pending direct state-level CDC extraction. | BJ37: RRM | BK37: partially_filled_needs_primary_law_review | BL37: =IFERROR((AZ37/BB37)*1000000,0) -> 0.73253043 | BM37: =IFERROR((BA37/BB37)*1000000,0) -> 288.86117 | BN37: =IFERROR(VLOOKUP(H37,index_logic!$A$4:$B$8,2,FALSE),0) -> 4 | BO37: =IFERROR(VLOOKUP(AD37,index_logic!$D$4:$E$21,2,FALSE),0) -> 3 | BP37: =IFERROR(VLOOKUP(AM37,index_logic!$G$4:$H$6,2,FALSE),0) -> 3 | BQ37: =IFERROR(VLOOKUP(AH37,index_logic!$J$4:$K$6,2,FALSE),0) -> 15 | BR37: =IFERROR(VLOOKUP(BE37,index_logic!$M$4:$N$7,2,FALSE),0) -> 0 | BS37: =IFERROR(VLOOKUP(BL37,index_logic!$P$4:$Q$9,2,TRUE),0) -> 3 | BT37: =IFERROR(VLOOKUP(BM37,index_logic!$S$4:$T$9,2,TRUE),0) -> 2 | BU37: =BN37+BO37+BP37+BQ37+BR37+BS37+BT37 -> 30 | BV37: =IF(BU37>=80,"Very High",IF(BU37>=65,"High",IF(BU37>=50,"Moderate",IF(BU37>=35,"Low","Very Low")))) -> Very Low
A38: Oregon | B38: OR | C38: 2026 | D38: current_snapshot | E38: 0 | F38: NA | G38: 2026-03-12 | H38: none_identified | I38: No statewide infertility/IVF coverage mandate identified in source used | J38: no_statewide_ivf_mandate_identified | K38: 0 | L38: 0 | M38: 0 | N38: 0 | O38: not identified | P38: 0 | Q38: 0 | R38: 0 | U38: none_identified | V38: 0 | X38: no_statewide_ivf_treatment_eligibility_rule_identified | Y38: no_statewide_ivf_treatment_eligibility_rule_identified | Z38: no_statewide_ivf_treatment_eligibility_rule_identified | AA38: not_applicable_no_statewide_ivf_treatment_mandate | AB38: not_applicable_no_statewide_ivf_treatment_mandate | AC38: none stated in source used | AD38: no_statewide_ivf_treatment_eligibility_rule_identified | AE38: no_statewide_ivf_treatment_eligibility_rule_identified | AF38: no_statewide_ivf_treatment_eligibility_rule_identified | AG38: no_statewide_ivf_treatment_eligibility_rule_identified | AH38: not_identified_in_secondary_sources_used | AI38: not_identified_in_secondary_sources_used | AJ38: not_identified_in_secondary_sources_used | AK38: not_identified_in_secondary_sources_used | AL38: not_identified_in_secondary_sources_used | AM38: restricted | AN38: unclear | AO38: no_or_unclear | AP38: yes | AQ38: adoption or post-birth process often required | AR38: no_fertility_specific_state_clinic_license_coded_in_this_pass | AS38: federal_CDC_NASS_reporting_baseline | AT38: federal_FCSRCA_CDC_public_reporting | AU38: CLIA_CMS_FDA_baseline; state_variation_not_fully_coded | AV38: 0 | AW38: 0 | AX38: 0 | AY38: =BU38 -> 37 | AZ38: 4 | BA38: 2460 | BB38: 4272371 | BC38: SBM-FP | BD38: democratic_trifecta | BE38: supportive_or_protective | BF38: No statewide infertility/IVF mandate identified in Triage Cancer state-law chart | BG38: https://triagecancer.org/state-laws/health-insurance-fertility-services | BH38: https://triagecancer.org/state-laws/health-insurance-fertility-services; https://surrogacy360.org/wp-content/uploads/2024/08/Regulation-Details-in-the-US-by-State_8.6.24.pdf; https://www.asrm.org/advocacy-and-policy/reproductive-rights/summary-reports/state-abortion-laws-potential-implications-for-reproductive-medicine/; https://www.guttmacher.org/2025/12/state-policy-trends-2025-full-year-analysis; https://www.cdc.gov/art/php/nass/index.html; https://www.cdc.gov/art/success-rates/index.html; https://www.cms.gov/medicare/quality/clinical-laboratory-improvement-amendments; https://www.cms.gov/marketplace/in-person-assisters/training-webinars/training/marketplaces-map; https://ballotpedia.org/State_government_trifectas; https://www.britannica.com/topic/largest-U-S-state-by-population; https://www.guttmacher.org/united-states/abortion | BI38: Starter row only. Needs primary-law verification for Medicaid, public funding, eligibility, embryo rules, surrogacy, clinic regulation, and utilization variables. Surrogacy fields coded from Surrogacy360 2024 state-by-state summary; interpret as starter classification requiring legal review for publication. Eligibility/LGBTQ fields on this row were filled as a 2026 starter classification based on absence of a statewide IVF-treatment mandate or unclear scope in the source used; this should not be interpreted as a full review of all private plans or clinic access in the state. Embryo/personhood/disposition fields were filled conservatively in this pass. Unless a state had a clear embryo-specific rule in the secondary sources used, values were set to not_identified_in_secondary_sources_used rather than treated as definitive absence of law. Clinic/reporting fields in this pass were coded from federal baselines: CDC NASS/FCSRCA reporting and CMS CLIA materials; insurance marketplace type from CMS Plan Year 2026 marketplace map; political control from Ballotpedia current trifecta status; population uses 2024 state estimate table summarized by Britannica from U.S. Census data. IVF clinic counts and cycle counts remain blank pending direct state-level CDC extraction. | BJ38: RRM | BK38: partially_filled_needs_primary_law_review | BL38: =IFERROR((AZ38/BB38)*1000000,0) -> 0.93624828 | BM38: =IFERROR((BA38/BB38)*1000000,0) -> 575.79269 | BN38: =IFERROR(VLOOKUP(H38,index_logic!$A$4:$B$8,2,FALSE),0) -> 0 | BO38: =IFERROR(VLOOKUP(AD38,index_logic!$D$4:$E$21,2,FALSE),0) -> 3 | BP38: =IFERROR(VLOOKUP(AM38,index_logic!$G$4:$H$6,2,FALSE),0) -> 3 | BQ38: =IFERROR(VLOOKUP(AH38,index_logic!$J$4:$K$6,2,FALSE),0) -> 15 | BR38: =IFERROR(VLOOKUP(BE38,index_logic!$M$4:$N$7,2,FALSE),0) -> 10 | BS38: =IFERROR(VLOOKUP(BL38,index_logic!$P$4:$Q$9,2,TRUE),0) -> 4 | BT38: =IFERROR(VLOOKUP(BM38,index_logic!$S$4:$T$9,2,TRUE),0) -> 2 | BU38: =BN38+BO38+BP38+BQ38+BR38+BS38+BT38 -> 37 | BV38: =IF(BU38>=80,"Very High",IF(BU38>=65,"High",IF(BU38>=50,"Moderate",IF(BU38>=35,"Low","Very Low")))) -> Low
A39: Pennsylvania | B39: PA | C39: 2026 | D39: current_snapshot | E39: 0 | F39: NA | G39: 2026-03-12 | H39: none_identified | I39: No statewide infertility/IVF coverage mandate identified in source used | J39: no_statewide_ivf_mandate_identified | K39: 0 | L39: 0 | M39: 0 | N39: 0 | O39: not identified | P39: 0 | Q39: 0 | R39: 0 | U39: none_identified | V39: 0 | X39: no_statewide_ivf_treatment_eligibility_rule_identified | Y39: no_statewide_ivf_treatment_eligibility_rule_identified | Z39: no_statewide_ivf_treatment_eligibility_rule_identified | AA39: not_applicable_no_statewide_ivf_treatment_mandate | AB39: not_applicable_no_statewide_ivf_treatment_mandate | AC39: none stated in source used | AD39: no_statewide_ivf_treatment_eligibility_rule_identified | AE39: no_statewide_ivf_treatment_eligibility_rule_identified | AF39: no_statewide_ivf_treatment_eligibility_rule_identified | AG39: no_statewide_ivf_treatment_eligibility_rule_identified | AH39: not_identified_in_secondary_sources_used | AI39: not_identified_in_secondary_sources_used | AJ39: not_identified_in_secondary_sources_used | AK39: not_identified_in_secondary_sources_used | AL39: not_identified_in_secondary_sources_used | AM39: restricted | AN39: unclear | AO39: no_or_unclear | AP39: unclear | AQ39: adoption or post-birth process often required | AR39: no_fertility_specific_state_clinic_license_coded_in_this_pass | AS39: federal_CDC_NASS_reporting_baseline | AT39: federal_FCSRCA_CDC_public_reporting | AU39: CLIA_CMS_FDA_baseline; state_variation_not_fully_coded | AV39: 0 | AW39: 0 | AX39: 0 | AY39: =BU39 -> 34 | AZ39: 14 | BA39: 8931 | BB39: 13078751 | BC39: SBM | BD39: divided_government | BE39: mixed | BF39: No statewide infertility/IVF mandate identified in Triage Cancer state-law chart | BG39: https://triagecancer.org/state-laws/health-insurance-fertility-services | BH39: https://triagecancer.org/state-laws/health-insurance-fertility-services; https://surrogacy360.org/wp-content/uploads/2024/08/Regulation-Details-in-the-US-by-State_8.6.24.pdf; https://www.asrm.org/advocacy-and-policy/reproductive-rights/summary-reports/state-abortion-laws-potential-implications-for-reproductive-medicine/; https://www.guttmacher.org/2025/12/state-policy-trends-2025-full-year-analysis; https://www.cdc.gov/art/php/nass/index.html; https://www.cdc.gov/art/success-rates/index.html; https://www.cms.gov/medicare/quality/clinical-laboratory-improvement-amendments; https://www.cms.gov/marketplace/in-person-assisters/training-webinars/training/marketplaces-map; https://ballotpedia.org/State_government_trifectas; https://www.britannica.com/topic/largest-U-S-state-by-population; https://www.guttmacher.org/united-states/abortion | BI39: Starter row only. Needs primary-law verification for Medicaid, public funding, eligibility, embryo rules, surrogacy, clinic regulation, and utilization variables. Surrogacy fields coded from Surrogacy360 2024 state-by-state summary; interpret as starter classification requiring legal review for publication. Eligibility/LGBTQ fields on this row were filled as a 2026 starter classification based on absence of a statewide IVF-treatment mandate or unclear scope in the source used; this should not be interpreted as a full review of all private plans or clinic access in the state. Embryo/personhood/disposition fields were filled conservatively in this pass. Unless a state had a clear embryo-specific rule in the secondary sources used, values were set to not_identified_in_secondary_sources_used rather than treated as definitive absence of law. Clinic/reporting fields in this pass were coded from federal baselines: CDC NASS/FCSRCA reporting and CMS CLIA materials; insurance marketplace type from CMS Plan Year 2026 marketplace map; political control from Ballotpedia current trifecta status; population uses 2024 state estimate table summarized by Britannica from U.S. Census data. IVF clinic counts and cycle counts remain blank pending direct state-level CDC extraction. | BJ39: RRM | BK39: partially_filled_needs_primary_law_review | BL39: =IFERROR((AZ39/BB39)*1000000,0) -> 1.0704386 | BM39: =IFERROR((BA39/BB39)*1000000,0) -> 682.86337 | BN39: =IFERROR(VLOOKUP(H39,index_logic!$A$4:$B$8,2,FALSE),0) -> 0 | BO39: =IFERROR(VLOOKUP(AD39,index_logic!$D$4:$E$21,2,FALSE),0) -> 3 | BP39: =IFERROR(VLOOKUP(AM39,index_logic!$G$4:$H$6,2,FALSE),0) -> 3 | BQ39: =IFERROR(VLOOKUP(AH39,index_logic!$J$4:$K$6,2,FALSE),0) -> 15 | BR39: =IFERROR(VLOOKUP(BE39,index_logic!$M$4:$N$7,2,FALSE),0) -> 7 | BS39: =IFERROR(VLOOKUP(BL39,index_logic!$P$4:$Q$9,2,TRUE),0) -> 4 | BT39: =IFERROR(VLOOKUP(BM39,index_logic!$S$4:$T$9,2,TRUE),0) -> 2 | BU39: =BN39+BO39+BP39+BQ39+BR39+BS39+BT39 -> 34 | BV39: =IF(BU39>=80,"Very High",IF(BU39>=65,"High",IF(BU39>=50,"Moderate",IF(BU39>=35,"Low","Very Low")))) -> Very Low
A40: Rhode Island | B40: RI | C40: 2026 | D40: active | E40: 1989 | F40: NA | G40: 2026-03-12 | H40: cover | I40: Infertility diagnosis and treatment plus fertility preservation | J40: Infertility treatment | K40: not specified | L40: $100,000 lifetime cap may apply | M40: 100000 | N40: not specified | O40: yes | P40: not specified | Q40: not specified | R40: yes (for fertility preservation law) | S40: not identified | T40: not identified | U40: none_identified | V40: 0 | W40: not identified | X40: none stated | Y40: otherwise healthy individual unable to conceive or sustain pregnancy during 1 year | Z40: not specified in source used | AA40: women aged 25-42 | AB40: not specified in source used | AC40: policy delivered, issued, or renewed in state | AD40: individual definition but women-only age criterion limits inclusivity | AE40: likely inclusive for women meeting definition | AF40: not explicitly addressed; women-specific statutory language | AG40: none stated in source used | AH40: not_identified_in_secondary_sources_used | AI40: not_identified_in_secondary_sources_used | AJ40: not_identified_in_secondary_sources_used | AK40: not_identified_in_secondary_sources_used | AL40: not_identified_in_secondary_sources_used | AM40: legal | AN40: yes | AO40: yes | AP40: unclear | AQ40: court-recognized parentage available | AR40: no_fertility_specific_state_clinic_license_coded_in_this_pass | AS40: federal_CDC_NASS_reporting_baseline | AT40: federal_FCSRCA_CDC_public_reporting | AU40: CLIA_CMS_FDA_baseline; state_variation_not_fully_coded | AV40: 1989 | AW40: 2018 | AX40: 0 | AY40: =BU40 -> 83 | AZ40: 1 | BA40: 1004 | BB40: 1112308 | BC40: SBM | BD40: democratic_trifecta | BE40: supportive_or_protective | BF40: RI Gen. Laws § 27-18-30; 2017-S 0821A / 2017-H 6170A | BG40: https://law.justia.com/codes/rhode-island/title-27/chapter-27-18/section-27-18-30/ | BH40: https://triagecancer.org/state-laws/health-insurance-fertility-services; https://surrogacy360.org/wp-content/uploads/2024/08/Regulation-Details-in-the-US-by-State_8.6.24.pdf; https://www.reproductivefacts.org/patient-advocacy/state-and-territory-infertility-insurance-laws/rhode-island/; https://www.asrm.org/advocacy-and-policy/reproductive-rights/summary-reports/state-abortion-laws-potential-implications-for-reproductive-medicine/; https://www.guttmacher.org/2025/12/state-policy-trends-2025-full-year-analysis; https://www.cdc.gov/art/php/nass/index.html; https://www.cdc.gov/art/success-rates/index.html; https://www.cms.gov/medicare/quality/clinical-laboratory-improvement-amendments; https://www.cms.gov/marketplace/in-person-assisters/training-webinars/training/marketplaces-map; https://ballotpedia.org/State_government_trifectas; https://www.britannica.com/topic/largest-U-S-state-by-population; https://www.guttmacher.org/united-states/abortion | BI40: Source applies age range 25–42 to women in infertility coverage summary. Surrogacy fields coded from Surrogacy360 2024 state-by-state summary; interpret as starter classification requiring legal review for publication. Eligibility/LGBTQ fields updated in this pass using current 2026 state-law summaries and/or statute text where available; some entries remain conservative where the source did not clearly resolve LGBTQ or gender-identity treatment eligibility. Embryo/personhood/disposition fields were filled conservatively in this pass. Unless a state had a clear embryo-specific rule in the secondary sources used, values were set to not_identified_in_secondary_sources_used rather than treated as definitive absence of law. Clinic/reporting fields in this pass were coded from federal baselines: CDC NASS/FCSRCA reporting and CMS CLIA materials; insurance marketplace type from CMS Plan Year 2026 marketplace map; political control from Ballotpedia current trifecta status; population uses 2024 state estimate table summarized by Britannica from U.S. Census data. IVF clinic counts and cycle counts remain blank pending direct state-level CDC extraction. | BJ40: RRM | BK40: partially_filled_needs_primary_law_review | BL40: =IFERROR((AZ40/BB40)*1000000,0) -> 0.89903156 | BM40: =IFERROR((BA40/BB40)*1000000,0) -> 902.62769 | BN40: =IFERROR(VLOOKUP(H40,index_logic!$A$4:$B$8,2,FALSE),0) -> 30 | BO40: =IFERROR(VLOOKUP(AD40,index_logic!$D$4:$E$21,2,FALSE),0) -> 10 | BP40: =IFERROR(VLOOKUP(AM40,index_logic!$G$4:$H$6,2,FALSE),0) -> 10 | BQ40: =IFERROR(VLOOKUP(AH40,index_logic!$J$4:$K$6,2,FALSE),0) -> 15 | BR40: =IFERROR(VLOOKUP(BE40,index_logic!$M$4:$N$7,2,FALSE),0) -> 10 | BS40: =IFERROR(VLOOKUP(BL40,index_logic!$P$4:$Q$9,2,TRUE),0) -> 4 | BT40: =IFERROR(VLOOKUP(BM40,index_logic!$S$4:$T$9,2,TRUE),0) -> 4 | BU40: =BN40+BO40+BP40+BQ40+BR40+BS40+BT40 -> 83 | BV40: =IF(BU40>=80,"Very High",IF(BU40>=65,"High",IF(BU40>=50,"Moderate",IF(BU40>=35,"Low","Very Low")))) -> Very High
A41: South Carolina | B41: SC | C41: 2026 | D41: current_snapshot | E41: 0 | F41: NA | G41: 2026-03-12 | H41: none_identified | I41: No statewide infertility/IVF coverage mandate identified in source used | J41: no_statewide_ivf_mandate_identified | K41: 0 | L41: 0 | M41: 0 | N41: 0 | O41: not identified | P41: 0 | Q41: 0 | R41: 0 | U41: none_identified | V41: 0 | X41: no_statewide_ivf_treatment_eligibility_rule_identified | Y41: no_statewide_ivf_treatment_eligibility_rule_identified | Z41: no_statewide_ivf_treatment_eligibility_rule_identified | AA41: not_applicable_no_statewide_ivf_treatment_mandate | AB41: not_applicable_no_statewide_ivf_treatment_mandate | AC41: none stated in source used | AD41: no_statewide_ivf_treatment_eligibility_rule_identified | AE41: no_statewide_ivf_treatment_eligibility_rule_identified | AF41: no_statewide_ivf_treatment_eligibility_rule_identified | AG41: no_statewide_ivf_treatment_eligibility_rule_identified | AH41: not_identified_in_secondary_sources_used | AI41: not_identified_in_secondary_sources_used | AJ41: not_identified_in_secondary_sources_used | AK41: not_identified_in_secondary_sources_used | AL41: not_identified_in_secondary_sources_used | AM41: restricted | AN41: unclear | AO41: no_or_unclear | AP41: unclear | AQ41: adoption or post-birth process often required | AR41: no_fertility_specific_state_clinic_license_coded_in_this_pass | AS41: federal_CDC_NASS_reporting_baseline | AT41: federal_FCSRCA_CDC_public_reporting | AU41: CLIA_CMS_FDA_baseline; state_variation_not_fully_coded | AV41: 0 | AW41: 0 | AX41: 0 | AY41: =BU41 -> 30 | AZ41: 5 | BA41: 3198 | BB41: 5478831 | BC41: FFM | BD41: republican_trifecta | BE41: restrictive | BF41: No statewide infertility/IVF mandate identified in Triage Cancer state-law chart | BG41: https://triagecancer.org/state-laws/health-insurance-fertility-services | BH41: https://triagecancer.org/state-laws/health-insurance-fertility-services; https://surrogacy360.org/wp-content/uploads/2024/08/Regulation-Details-in-the-US-by-State_8.6.24.pdf; https://www.asrm.org/advocacy-and-policy/reproductive-rights/summary-reports/state-abortion-laws-potential-implications-for-reproductive-medicine/; https://www.guttmacher.org/2025/12/state-policy-trends-2025-full-year-analysis; https://www.cdc.gov/art/php/nass/index.html; https://www.cdc.gov/art/success-rates/index.html; https://www.cms.gov/medicare/quality/clinical-laboratory-improvement-amendments; https://www.cms.gov/marketplace/in-person-assisters/training-webinars/training/marketplaces-map; https://ballotpedia.org/State_government_trifectas; https://www.britannica.com/topic/largest-U-S-state-by-population; https://www.guttmacher.org/united-states/abortion | BI41: Starter row only. Needs primary-law verification for Medicaid, public funding, eligibility, embryo rules, surrogacy, clinic regulation, and utilization variables. Surrogacy fields coded from Surrogacy360 2024 state-by-state summary; interpret as starter classification requiring legal review for publication. Eligibility/LGBTQ fields on this row were filled as a 2026 starter classification based on absence of a statewide IVF-treatment mandate or unclear scope in the source used; this should not be interpreted as a full review of all private plans or clinic access in the state. Embryo/personhood/disposition fields were filled conservatively in this pass. Unless a state had a clear embryo-specific rule in the secondary sources used, values were set to not_identified_in_secondary_sources_used rather than treated as definitive absence of law. Clinic/reporting fields in this pass were coded from federal baselines: CDC NASS/FCSRCA reporting and CMS CLIA materials; insurance marketplace type from CMS Plan Year 2026 marketplace map; political control from Ballotpedia current trifecta status; population uses 2024 state estimate table summarized by Britannica from U.S. Census data. IVF clinic counts and cycle counts remain blank pending direct state-level CDC extraction. | BJ41: RRM | BK41: partially_filled_needs_primary_law_review | BL41: =IFERROR((AZ41/BB41)*1000000,0) -> 0.91260344 | BM41: =IFERROR((BA41/BB41)*1000000,0) -> 583.70116 | BN41: =IFERROR(VLOOKUP(H41,index_logic!$A$4:$B$8,2,FALSE),0) -> 0 | BO41: =IFERROR(VLOOKUP(AD41,index_logic!$D$4:$E$21,2,FALSE),0) -> 3 | BP41: =IFERROR(VLOOKUP(AM41,index_logic!$G$4:$H$6,2,FALSE),0) -> 3 | BQ41: =IFERROR(VLOOKUP(AH41,index_logic!$J$4:$K$6,2,FALSE),0) -> 15 | BR41: =IFERROR(VLOOKUP(BE41,index_logic!$M$4:$N$7,2,FALSE),0) -> 3 | BS41: =IFERROR(VLOOKUP(BL41,index_logic!$P$4:$Q$9,2,TRUE),0) -> 4 | BT41: =IFERROR(VLOOKUP(BM41,index_logic!$S$4:$T$9,2,TRUE),0) -> 2 | BU41: =BN41+BO41+BP41+BQ41+BR41+BS41+BT41 -> 30 | BV41: =IF(BU41>=80,"Very High",IF(BU41>=65,"High",IF(BU41>=50,"Moderate",IF(BU41>=35,"Low","Very Low")))) -> Very Low
